Workbook
Name Slicer_TYPE: #N/A

Sheet New_Costing
G1: NOTE: THAT THE DIFFERENCE OF DECLARED VAT IMPORTATION IS 2-3% ONLY | AE1: Source | AF1: Date | AG1: Product Type | AH1: Supplier | AI1: Document Type | AJ1: Number | AK1: Particulars | AL1: Size | AM1: Code | AN1: Quantity | AP1: CPU | AQ1: Total Invoice | AR1: Less: VAT | AS1: Net of VAT | AT1: Computations
B2: OIL COSTING | G2: PROFITABILITY
I3: PALM OIL | P3: CANOLA OIL | S3: SOYA OIL | BH3: PAYMENT SUMMARY AND COST PER UNIT (Formulated Table)
BH4: Description | BI4: Amount | BJ4: CPU (KG) | BK4: CPU (LTR)
G5: DESCRIPTION | I5: 350ML | J5: 36 | K5: 500ML | L5: 24 | M5: 1LSWAK | N5: 12 | P5: 1LITER | Q5: 12 | S5: 1LITER | T5: 12 | BH5: As per Foreign Cost | BI5: =BF21+BF37 -> 2026160 | BJ5: =BI5/BD15 -> 94.24 | BK5: =BI5/BF16 -> 82.928546
B6: Description | C6: Date | D6: Price | E6: isUsed | G6: SALES | I6: 36 | J6: =I6/I6 -> 1 | K6: 50 | L6: =K6/K6 -> 1 | M6: 95 | N6: =M6/M6 -> 1 | P6: 105 | Q6: =P6/P6 -> 1 | S6: 115 | T6: =S6/S6 -> 1 | V6: MIXES | AA6: MOST RECENT PURCHASE PRICES | AT6: Price per KG ($) | AU6: Net Weight (L) | AV6: FX Rate | AW6: Total for COGS | AX6: COGS per KG | AY6: COGS per L | AZ6: COGS per bottle | BH6: As per Local Cost | BI6: =BK34+BJ20 -> 320231.29 | BJ6: =BI6/BD15 -> 14.894479 | BK6: =BI6/BF16 -> 13.106722
B7: ='Pricing Trends'!R13 -> RBD SOYA BEAN OIL | C7: ='Pricing Trends'!S13 -> 45314 | D7: ='Pricing Trends'!U13 -> 69.078872 | E7: FALSE | G7: RBD SOYA BEAN OIL | I7: =IFERROR(VLOOKUP($I$2&$G7,Validation!$E:$O,4,FALSE),0) -> 0 | J7: =I7/I$6 -> 0 | K7: =IFERROR(VLOOKUP($I$2&$G7,Validation!$E:$O,5,FALSE),0) -> 0 | L7: =K7/K$6 -> 0 | M7: =IFERROR(VLOOKUP($I$2&$G7,Validation!$E:$O,6,FALSE),0) -> 0 | N7: =M7/M$6 -> 0 | P7: =IFERROR(VLOOKUP($P$2&$G7,Validation!$E:$O,6,FALSE),0) -> 0 | Q7: =P7/P$6 -> 0 | S7: =Y15 -> 90.6633 | T7: =S7/S$6 -> 0.78837652 | V7: PALM | Y7: =SUM(Y8:Y13) -> 81.6612 | AA7: PALM (Local) | AB7: =AF33 -> 46158 | AC7: =AY33 -> 75.061598 | AE7: Wennie - Payables | AF7: 45901 | AG7: Corn | AH7: O.V. INTERNATIONAL IMPORT-EXPORT CO., LTD. | AK7: 24/15OZ CANNED WHOLE SWEET KERNEL CORN | AN7: 1050 | AO7: unit | AP7: 9.5 | AQ7: =AP7*AN7 -> 9975 | BH7: As per Gross of BOC | BI7: =BI5+BI6 -> 2346391.3 | BJ7: =BI7/BD15 -> 109.13448 | BK7: =BI7/BF16 -> 96.035268
B8: ='Pricing Trends'!R14 -> RBD SOYA BEAN OIL | C8: ='Pricing Trends'!S14 -> 45256 | D8: ='Pricing Trends'!U14 -> 68.75434 | E8: FALSE | G8: RBD PALM OLEIN (LOCAL) | I8: =IFERROR(VLOOKUP($I$2&$G8,Validation!$E:$O,4,FALSE),0) -> 0 | J8: =I8/I$6 -> 0 | K8: =IFERROR(VLOOKUP($I$2&$G8,Validation!$E:$O,5,FALSE),0) -> 0 | L8: =K8/K$6 -> 0 | M8: =IFERROR(VLOOKUP($I$2&$G8,Validation!$E:$O,6,FALSE),0) -> 0 | N8: =M8/M$6 -> 0 | P8: =IFERROR(VLOOKUP($P$2&$G8,Validation!$E:$O,6,FALSE),0) -> 0 | Q8: =P8/P$6 -> 0 | S8: =IFERROR(VLOOKUP($S$2&$G8,Validation!$E:$O,6,FALSE),0) -> 0 | T8: =S8/S$6 -> 0 | V8: PALM (Local) | W8: =$AC$7 -> 75.061598 | X8: 0 | Y8: =W8*X8 -> 0 | AA8: PALM (Foreign) | AB8: =AF12 -> 46093 | AC8: =AY12 -> 81.6612 | AE8: Wennie - Payables | AF8: 45901 | AG8: Corn | AH8: O.V. INTERNATIONAL IMPORT-EXPORT CO., LTD. | AK8: 24/15OZ CANNED CREAM STYLE CORN | AN8: 300 | AO8: unit | AP8: 9.5 | AQ8: =AP8*AN8 -> 2850 | BH8: As per Net of BOC | BI8: =BI7-BJ20 -> 2157411.1 | BJ8: =BI8/BD15 -> 100.3447 | BK8: =BI8/BF16 -> 88.300512
B9: ='Pricing Trends'!R15 -> RBD SOYA BEAN OIL | C9: ='Pricing Trends'!S15 -> 45132 | D9: ='Pricing Trends'!U15 -> 64.59293 | E9: FALSE | G9: RBD PALM OLEIN (FOREIGN) | I9: =M9*(350/1000) -> 28.58142 | J9: =I9/I$6 -> 0.79392833 | K9: =M9/2 -> 40.8306 | L9: =K9/K$6 -> 0.816612 | M9: =Y7 -> 81.6612 | N9: =M9/M$6 -> 0.85959158 | P9: =IFERROR(VLOOKUP($P$2&$G9,Validation!$E:$O,6,FALSE),0) -> 0 | Q9: =P9/P$6 -> 0 | S9: =IFERROR(VLOOKUP($S$2&$G9,Validation!$E:$O,6,FALSE),0) -> 0 | T9: =S9/S$6 -> 0 | V9: PALM (Foreign) | W9: =$AC$8 -> 81.6612 | X9: 1 | Y9: =W9*X9 -> 81.6612 | AA9: SOYA (Local) | AC9: 0 | AE9: Wennie - Payables | AF9: 45901 | AG9: Corn | AH9: O.V. INTERNATIONAL IMPORT-EXPORT CO., LTD. | AK9: 06/108OZ CANNED WHOLE KERNEL CORN | AN9: 200 | AO9: unit | AP9: 13.5 | AQ9: =AP9*AN9 -> 2700 | BH9: For COGS | BI9: =BF21+BJ20+BF37 -> 2215140.2 | BJ9: =BI9/BD15 -> 103.02978 | BK9: =BI9/BF16 -> 90.663303
B10: ='Pricing Trends'!R16 -> RBD SOYA BEAN OIL | C10: ='Pricing Trends'!S16 -> 44961 | D10: ='Pricing Trends'!U16 -> 81.901482 | E10: FALSE | G10: RBD CANOLA OIL | I10: =IFERROR(VLOOKUP($I$2&$G10,Validation!$E:$O,4,FALSE),0) -> 0 | J10: =I10/I$6 -> 0 | K10: =IFERROR(VLOOKUP($I$2&$G10,Validation!$E:$O,5,FALSE),0) -> 0 | L10: =K10/K$6 -> 0 | M10: =IFERROR(VLOOKUP($I$2&$G10,Validation!$E:$O,6,FALSE),0) -> 0 | N10: =M10/M$6 -> 0 | P10: =Y23 -> 84.3891 | Q10: =P10/P$6 -> 0.80370571 | S10: =IFERROR(VLOOKUP($S$2&$G10,Validation!$E:$O,6,FALSE),0) -> 0 | T10: =S10/S$6 -> 0 | V10: SOYA (Local) | W10: =$AC$9 -> 0 | X10: 0 | Y10: =W10*X10 -> 0 | AA10: SOYA (Foreign) | AB10: =AF13 -> 46093 | AC10: =AY13 -> 90.6633 | AE10: Wennie - Payables | AF10: 45960 | AG10: Coconut Milk | AH10: SUREE INTERFOODS CO. LTD | AK10: COCONUT MILK | AN10: 1800 | AO10: unit | AP10: 13.05 | AQ10: =AP10*AN10 -> 23490
B11: ='Pricing Trends'!R17 -> 0 | C11: ='Pricing Trends'!S17 -> 0 | D11: ='Pricing Trends'!U17 -> 0 | E11: FALSE | G11: RBD COCONUT OIL | I11: =IFERROR(VLOOKUP($I$2&$G11,Validation!$E:$O,4,FALSE),0) -> 0 | J11: =I11/I$6 -> 0 | K11: =IFERROR(VLOOKUP($I$2&$G11,Validation!$E:$O,5,FALSE),0) -> 0 | L11: =K11/K$6 -> 0 | M11: =IFERROR(VLOOKUP($I$2&$G11,Validation!$E:$O,6,FALSE),0) -> 0 | N11: =M11/M$6 -> 0 | P11: =IFERROR(VLOOKUP($P$2&$G11,Validation!$E:$O,6,FALSE),0) -> 0 | Q11: =P11/P$6 -> 0 | S11: =IFERROR(VLOOKUP($S$2&$G11,Validation!$E:$O,6,FALSE),0) -> 0 | T11: =S11/S$6 -> 0 | V11: SOYA (Foreign) | W11: =$AC$10 -> 90.6633 | X11: 0 | Y11: =W11*X11 -> 0 | AA11: CANOLA (LOCAL) | AC11: 0 | AE11: Wennie - Payables | AF11: 45964 | AG11: Canola Oil | AH11: MOI INTERNATIONAL (SIGNAPORE) PTE LTD | AK11: RBD CANOLA OIL | AN11: 21.5 | AO11: MT | AP11: 1405 | AQ11: =AP11*AN11 -> 30207.5 | AR11: =AN11*1000 -> 21500 | AS11: =AQ11/AR11 -> 1.405 | AT11: 1.405 | AU11: 24433 | AV11: 62 | AW11: 2061845.2 | AX11: 95.8998 | AY11: 84.3891 | BB11: DETAILS OF PAYMENT
B12: ='Pricing Trends'!R18 -> RBD COCONUT OIL | C12: ='Pricing Trends'!S18 -> 45468 | D12: ='Pricing Trends'!U18 -> 64.678486 | E12: FALSE | G12: LABEL | I12: =IFERROR(VLOOKUP("350ML LABEL PALM",'Pricing Trends'!$K:$N,4,FALSE),0) -> 0.3 | J12: =I12/I$6 -> 0.0083333333 | K12: =IFERROR(VLOOKUP("500ML LABEL PALM",'Pricing Trends'!$K:$N,4,FALSE),0) -> 0.45 | L12: =K12/K$6 -> 0.009 | M12: =IFERROR(VLOOKUP("1LITER LABEL PALM",'Pricing Trends'!$K:$N,4,FALSE),0) -> 0.55 | N12: =M12/M$6 -> 0.0057894737 | P12: =IFERROR(VLOOKUP("1LITER LABEL CANOLEIN",'Pricing Trends'!$K:$N,4,FALSE),0) -> 0.72 | Q12: =P12/P$6 -> 0.0068571429 | S12: =IFERROR(VLOOKUP("1LITER LABEL SOYA",'Pricing Trends'!$K:$N,4,FALSE),0) -> 0.72 | T12: =S12/S$6 -> 0.0062608696 | V12: CANOLA (LOCAL) | W12: =$AC$11 -> 0 | X12: 0 | Y12: =W12*X12 -> 0 | AA12: CANOLA (Foreign) | AB12: =AF11 -> 45964 | AC12: =AY11 -> 84.3891 | AE12: Wennie - Payables | AF12: 46093 | AG12: Palm Oil | AH12: MOI INTERNATIONAL (SIGNAPORE) PTE LTD | AK12: RBD PALM OLEIN - IV 60 MIN | AN12: 21.5 | AO12: MT | AP12: 1355 | AQ12: =AP12*AN12 -> 29132.5 | AR12: =AN12*1000 -> 21500 | AS12: =AQ12/AR12 -> 1.355 | AT12: 1.355 | AU12: 24433 | AV12: 62 | AW12: 1995195.2 | AX12: 92.7998 | AY12: 81.6612
B13: ='Pricing Trends'!R19 -> RBD COCONUT OIL | C13: ='Pricing Trends'!S19 -> 45222 | D13: ='Pricing Trends'!U19 -> 51.4783 | E13: FALSE | G13: BOTTLE / POUCH | I13: =AC18 -> 3.95 | J13: =I13/I$6 -> 0.10972222 | K13: =IFERROR(VLOOKUP("500ML BOTTLE PALM [SWAK]",'Pricing Trends'!$A:$D,4,FALSE),0) -> 3.65 | L13: =K13/K$6 -> 0.073 | M13: =AC20 -> 7.9 | N13: =M13/M$6 -> 0.083157895 | P13: =AC20 -> 7.9 | Q13: =P13/P$6 -> 0.075238095 | S13: =AC20 -> 7.9 | T13: =S13/S$6 -> 0.068695652 | V13: CANOLA (Foreign) | W13: =$AC$12 -> 84.3891 | X13: 0 | Y13: =W13*X13 -> 0 | AE13: Wennie - Payables | AF13: 46093 | AG13: Soybean Oil | AH13: MOI INTERNATIONAL (SIGNAPORE) PTE LTD | AK13: RBD SOYBEAN OIL | AN13: 21.5 | AO13: MT | AP13: 1520 | AQ13: =AP13*AN13 -> 32680 | AR13: =AN13*1000 -> 21500 | AS13: =AQ13/AR13 -> 1.52 | AT13: 1.52 | AU13: 24433 | AV13: 62 | AW13: 2215140.2 | AX13: 103.0298 | AY13: 90.6633
B14: ='Pricing Trends'!R20 -> RBD COCONUT OIL | C14: ='Pricing Trends'!S20 -> 45133 | D14: ='Pricing Trends'!U20 -> 54.559 | E14: FALSE | G14: BOX | I14: =AC14 -> 0.72222222 | J14: =I14/I$6 -> 0.020061728 | K14: =AC15 -> 0.87083333 | L14: =K14/K$6 -> 0.017416667 | M14: =AC16 -> 2.15 | N14: =M14/M$6 -> 0.022631579 | P14: =AC16 -> 2.15 | Q14: =P14/P$6 -> 0.02047619 | S14: =AC16 -> 2.15 | T14: =S14/S$6 -> 0.018695652 | AA14: Box 350mL | AB14: =AF36 -> 46180 | AC14: =AZ36 -> 0.72222222 | AE14: Wennie - Payables | AF14: 46119 | AG14: Corn Starch | AH14: QINGDAO BAONA BIOLOGICAL TECHNOLOGY CP., LTD | AK14: CORN STARCH | AN14: 28.4 | AO14: MT | AP14: 450 | AQ14: =AP14*AN14 -> 12780 | BB14: ORDER DETAILS (FOREIGN) | BH14: COMPUTATION OF TAXES AND DUTIES
B15: ='Pricing Trends'!R21 -> RBD COCONUT OIL | C15: ='Pricing Trends'!S21 -> 44965 | D15: ='Pricing Trends'!U21 -> 52.7983 | E15: FALSE | G15: PACKAGING TAPE CLEAR | I15: =((IFERROR(VLOOKUP($G$15,'Pricing Trends'!$W:$Z,4,FALSE),0)/10000)*200)/J5 -> 0.013888889 | J15: =I15/I$6 -> 0.00038580247 | K15: =((IFERROR(VLOOKUP($G$15,'Pricing Trends'!$W:$Z,4,FALSE),0)/10000)*200)/L5 -> 0.020833333 | L15: =K15/K$6 -> 0.00041666667 | M15: =((IFERROR(VLOOKUP($G$15,'Pricing Trends'!$W:$Z,4,FALSE),0)/10000)*200)/N5 -> 0.041666667 | N15: =M15/M$6 -> 0.00043859649 | P15: =((IFERROR(VLOOKUP($G$15,'Pricing Trends'!$W:$Z,4,FALSE),0)/10000)*200)/Q5 -> 0.041666667 | Q15: =P15/P$6 -> 0.0003968254 | S15: =((IFERROR(VLOOKUP($G$15,'Pricing Trends'!$W:$Z,4,FALSE),0)/10000)*200)/T5 -> 0.041666667 | T15: =S15/S$6 -> 0.00036231884 | V15: SOYA | Y15: =SUM(Y16:Y21) -> 90.6633 | AA15: Box 500mL | AB15: =AF34 -> 46178 | AC15: =AZ34 -> 0.87083333 | AE15: Wennie - Receipts | AF15: 46140 | AG15: Bottle 1L | AH15: RMC RICOR MILLS CORP. | AI15: CLIENT ACKNOWLEDGEMENT RECEIPT | AJ15: 0010628 | AK15: 1LTR36G1810 Clear-Swak | AL15: 91 Bags x 110 pcs | AM15: FG082 | AN15: 10010 | AO15: pcs | AP15: 7.2 | AQ15: =AN15*AP15 -> 72072 | BB15: ITEM NET WEIGHT (KG) | BD15: =21.5*1000 -> 21500 | BE15: PRICE PER KG | BF15: =BD16/BD15 -> 1.52 | BH15: VAT PH (12%) | BJ15: Formulated | BK15: =BF34*0.12 -> 253684.78
B16: ='Pricing Trends'!R22 -> 0 | C16: ='Pricing Trends'!S22 -> 0 | D16: ='Pricing Trends'!U22 -> 0 | E16: FALSE | G16: DOUBLE SIDED TAPE 3/4"X30M | I16: =((45/3000)*7) -> 0.105 | J16: =I16/I$6 -> 0.0029166667 | K16: =((45/3000)*7) -> 0.105 | L16: =K16/K$6 -> 0.0021 | M16: =((45/3000)*12) -> 0.18 | N16: =M16/M$6 -> 0.0018947368 | Q16: =P16/P$6 -> 0 | T16: =S16/S$6 -> 0 | V16: PALM (Local) | W16: =$AC$7 -> 75.061598 | X16: 0 | Y16: =W16*X16 -> 0 | AA16: Box 1L | AB16: =AF35 -> 46179 | AC16: =AZ35 -> 2.15 | AE16: Wennie - Receipts | AF16: 46140 | AG16: Bottle 350mL | AH16: RMC RICOR MILLS CORP. | AI16: CLIENT ACKNOWLEDGEMENT RECEIPT | AJ16: 0010628 | AK16: 350ML17G1810 Clear-Swak | AL16: 72 Bags x 210 pcs | AM16: FG179A | AN16: 15120 | AO16: pcs | AP16: 3.1 | AQ16: =AN16*AP16 -> 46872 | BB16: DOLLAR PAYMENT | BD16: =AQ13 -> 32680 | BE16: NET WEIGHT (LTR) | BF16: =BD15*1.1364 -> 24432.6 | BH16: Minimum VAT | BJ16: 186569.21 | BK16: =BJ16-BK15 -> -67115.572
B17: ='Pricing Trends'!R23 -> RBD PALM OLEIN (FOREIGN) | C17: ='Pricing Trends'!S23 -> 45547 | D17: ='Pricing Trends'!U23 -> 60.65316 | E17: FALSE | G17: COST OF GOODS SOLD | I17: =SUM(I7:I16) -> 33.672531 | J17: =I17/I6 -> 0.93534809 | K17: =SUM(K7:K16) -> 45.927267 | L17: =K17/K6 -> 0.91854533 | M17: =SUM(M7:M16) -> 92.482867 | N17: =M17/M6 -> 0.97350386 | P17: =SUM(P7:P16) -> 95.200767 | Q17: =P17/P6 -> 0.90667397 | S17: =SUM(S7:S16) -> 101.47497 | T17: =S17/S6 -> 0.88239101 | V17: PALM (Foreign) | W17: =$AC$8 -> 81.6612 | X17: 0 | Y17: =W17*X17 -> 0 | AE17: Wennie - Receipts | AF17: 46140 | AG17: Bottle Caps | AI17: CLIENT ACKNOWLEDGEMENT RECEIPT | AJ17: 0010628 | AK17: 1810Caps-Yellow | AL17: 6 Bags x 4000 + 1130 pcs | AM17: CP105 | AN17: 25130 | AO17: pcs | AP17: 0.7 | AQ17: =AP17*AN17 -> 17591 | AZ17: =AP17 -> 0.7 | BB17: FOREIGN EXCHANGE RATE | BF17: 62 | BH17: Import Processing Fee (IPF) | BJ17: Formulated | BK17: 2000
B18: ='Pricing Trends'!R24 -> RBD PALM OLEIN (FOREIGN) | C18: ='Pricing Trends'!S24 -> 45517 | D18: ='Pricing Trends'!U24 -> 60.97 | E18: FALSE | G18: GROSS PROFIT | I18: =I6-I17 -> 2.3274689 | J18: =I18/I6 -> 0.064651914 | K18: =K6-K17 -> 4.0727333 | L18: =K18/K6 -> 0.081454667 | M18: =M6-M17 -> 2.5171333 | N18: =M18/M6 -> 0.02649614 | P18: =P6-P17 -> 9.7992333 | Q18: =P18/P6 -> 0.093326032 | S18: =S6-S17 -> 13.525033 | T18: =S18/S6 -> 0.11760899 | V18: SOYA (Local) | W18: =$AC$9 -> 0 | X18: 0 | Y18: =W18*X18 -> 0 | AA18: Bottle 350mL | AB18: =AF36 -> 46180 | AC18: =AZ26 -> 3.95 | AE18: Angie | AF18: 46140 | AG18: Bottle 1L | AH18: MCBRIDE | AK18: 1 LTER BOTTLE PALM (SWAK) | AN18: 10010 | AO18: pcs | AP18: 7.9 | AQ18: =AN18*AP18 -> 79079 | BH18: Customs Documentary Stamp (CDS) | BJ18: Fixed | BK18: 130
B19: ='Pricing Trends'!R25 -> RBD PALM OLEIN (FOREIGN) | C19: ='Pricing Trends'!S25 -> 45494 | D19: ='Pricing Trends'!U25 -> 60.49687 | E19: FALSE | G19: EXPENSES | I19: =SUM(I20:I35) -> 1.1308955 | J19: =I19/I6 -> 0.031413763 | K19: =SUM(K20:K35) -> 4.4376435 | L19: =K19/K6 -> 0.08875287 | M19: =SUM(M20:M35) -> 2.7025585 | N19: =M19/M6 -> 0.028447984 | P19: =SUM(P20:P35) -> 14.019373 | Q19: =P19/P6 -> 0.13351784 | S19: =SUM(S20:S35) -> 15.432276 | T19: =S19/S6 -> 0.1341937 | V19: SOYA (Foreign) | W19: =$AC$10 -> 90.6633 | X19: 1 | Y19: =W19*X19 -> 90.6633 | AA19: Bottle 500mL | AC19: 0 | AE19: Angie | AF19: 46140 | AG19: Bottle 350mL | AH19: MCBRIDE | AK19: 350ML BOTTLE PALM (SWAK) | AN19: 15120 | AO19: pcs | AP19: 3.8 | AQ19: =AN19*AP19 -> 57456 | BB19: BOC COMPUTATION | BH19: Container Security Fees (CSF) | BJ19: Fixed | BK19: 281
B20: ='Pricing Trends'!R26 -> RBD PALM OLEIN (FOREIGN) | C20: ='Pricing Trends'!S26 -> 45314 | D20: ='Pricing Trends'!U26 -> 57.51356 | E20: FALSE | G20: Production Expenses - Labelling | I20: 0.2 | J20: =I20/I$6 -> 0.0055555556 | K20: 0.2 | L20: =K20/K$6 -> 0.004 | M20: 0.2 | N20: =M20/M$6 -> 0.0021052632 | Q20: =P20/P$6 -> 0 | V20: CANOLA (LOCAL) | W20: =$AC$11 -> 0 | X20: 0 | Y20: =W20*X20 -> 0 | AA20: Bottle 1L | AB20: =AF32 -> 46151 | AC20: =AZ32 -> 7.9 | AE20: Wennie - Receipts | AF20: 46148 | AG20: Box 350mL | AH20: SUPERIOR PACKAGING CORPORATION | AI20: SALES INVOICE | AJ20: 552335 | AK20: Corrugated Carton RSC IN-GLUED Joint, B Flute, 175# lbs. 2 color | AL20: 385 X 385 X 190 | AM20: 350ML BOX PALM | AN20: 6225 | AO20: pcs | AP20: 26 | AQ20: =AN20*AP20 -> 161850 | AR20: =AQ20/1.12*0.12 -> 17341.071 | AS20: =AQ20-AR20 -> 144508.93 | AZ20: =AP20/36 -> 0.72222222 | BB20: MEN2 PAYMENT IN PESO VALUE | BH20: TOTAL DUTIES AND TAXES | BJ20: =SUM(BK15:BK19) -> 188980.21
B21: ='Pricing Trends'!R27 -> RBD PALM OLEIN (FOREIGN) | C21: ='Pricing Trends'!S27 -> 45248 | D21: ='Pricing Trends'!U27 -> 61.45051 | E21: FALSE | G21: Production Expenses - Packaging | I21: =0.4*0.35 -> 0.14 | J21: =I21/I$6 -> 0.0038888889 | K21: =0.4*0.5 -> 0.2 | L21: =K21/K$6 -> 0.004 | M21: 0.4 | N21: =M21/M$6 -> 0.0042105263 | P21: 0.4 | Q21: =P21/P$6 -> 0.0038095238 | S21: 0.4 | T21: =S21/S$6 -> 0.0034782609 | V21: CANOLA (Foreign) | W21: =$AC$12 -> 84.3891 | X21: 0 | Y21: =W21*X21 -> 0 | AA21: Bottle 350mL - Price increase | AC21: =AZ38 -> 4.1 | AE21: Wennie - Receipts | AF21: 46148 | AG21: Box 500mL | AH21: SUPERIOR PACKAGING CORPORATION | AI21: SALES INVOICE | AJ21: 552333 | AK21: Corrugated Carton RSC IN-GLUED Joint, B Flute, 175# lbs. 2 color | AL21: 2416 X 285 X 230 | AM21: 500ML BOX PALM | AN21: 2000 | AO21: pcs | AP21: 20.9 | AQ21: =AN21*AP21 -> 41800 | AR21: =AQ21/1.12*0.12 -> 4478.5714 | AS21: =AQ21-AR21 -> 37321.429 | AZ21: =AP21/24 -> 0.87083333 | BB21: Item Custom Value (Oil) | BE21: Formulated | BF21: =BD16*BF17 -> 2026160
B22: ='Pricing Trends'!R28 -> RBD PALM OLEIN (FOREIGN) | C22: ='Pricing Trends'!S28 -> 45244 | D22: ='Pricing Trends'!U28 -> 63.35264 | E22: FALSE | G22: Distributors Discount | AA22: Bottle 500mL - Price Increase | AC22: 0 | AE22: Wennie - Receipts | AF22: 46149 | AG22: Box 1L | AH22: SUPERIOR PACKAGING CORPORATION | AI22: SALES INVOICE | AJ22: 552334 | AK22: Corrugated Carton RSC IN-GLUED Joint, B Flute, 200 lbs. 2 color | AL22: 344 X 258 X 281 | AM22: 1 LITER BOX PALM - SWAK | AN22: 7425 | AO22: pcs | AP22: 25.8 | AQ22: =AN22*AP22 -> 191565 | AR22: =AQ22/1.12*0.12 -> 20524.821 | AS22: =AQ22-AR22 -> 171040.18 | AZ22: =AP22/12 -> 2.15 | BB22: SUPPLIER DUTIES | BH22: COMPUTATION OF SHIPPING FEE
B23: ='Pricing Trends'!R29 -> RBD PALM OLEIN (FOREIGN) | C23: ='Pricing Trends'!S29 -> 45234 | D23: ='Pricing Trends'!U29 -> 56.63575 | E23: FALSE | G23: Sales Expenses - Internal | V23: CANOLA | Y23: =SUM(Y24:Y29) -> 84.3891 | AA23: Bottle 1L - Price Increase | AC23: =AZ37 -> 8.6 | AE23: Wennie - Receipts | AF23: 46150 | AG23: Bottle 350mL | AI23: CLIENT ACKNOWLEDGEMENT RECEIPT | AJ23: 0010679 | AK23: 350ml17g1810Clear-Swak | AL23: 209 Bags x 230 pcs | AM23: FG179S | AN23: 43890 | AO23: pcs | AP23: 3.25 | AQ23: =AP23*AN23 -> 142642.5 | AZ23: =AP23 -> 3.25 | BB23: InsuranceInFreight | BD23: Formulated | BE23: 25029 | BF23: =SUM(BE23:BE24) -> 73205 | BH23: Shippine Lines THC Fee | BJ23: Variable | BK23: 42510
B24: ='Pricing Trends'!R30 -> 0 | C24: ='Pricing Trends'!S30 -> 0 | D24: ='Pricing Trends'!U30 -> 0 | E24: FALSE | G24: Sales Expenses - External | J24: =I24/I$6 -> 0 | K24: 1 | N24: =M24/M$6 -> 0 | P24: 1 | Q24: =P24/P$6 -> 0.0095238095 | S24: 1 | T24: =S24/S$6 -> 0.0086956522 | V24: PALM (Local) | W24: =$AC$7 -> 75.061598 | X24: 0 | Y24: =W24*X24 -> 0 | AE24: Wennie - Receipts | AF24: 46150 | AG24: Bottle Caps | AI24: CLIENT ACKNOWLEDGEMENT RECEIPT | AJ24: 0010679 | AK24: 1810Caps-Yellow | AL24: 10 Bags x 4000 + 3890 pcs | AM24: CP105 | AN24: 43890 | AO24: pcs | AP24: 0.7 | AQ24: =AP24*AN24 -> 30723 | AZ24: =AP24 -> 0.7 | BB24: OTHinEV | BD24: Formulated | BE24: 48176 | BH24: Storage Fee | BJ24: Variable | BK24: 2846.23
B25: ='Pricing Trends'!R31 -> RBD CANOLA OIL | C25: ='Pricing Trends'!S31 -> 45269 | D25: ='Pricing Trends'!U31 -> 73.180847 | E25: FALSE | G25: Marketing Expenses - Trade Investment | V25: PALM (Foreign) | W25: =$AC$8 -> 81.6612 | X25: 0 | Y25: =W25*X25 -> 0 | AA25: PALM Pickup Logistics | AB25: 5/23/26 | AC25: =AZ40 -> 0.20255846 | AE25: Wennie - Receipts | AF25: 46150 | AG25: Pancit Canton | AI25: Finished Good Form | AK25: Mama Pina's Pancit Canton 300g x 18 | AN25: 120 | AO25: box | AP25: 820.8 | AQ25: =AP25*AN25 -> 98496 | BB25: CUSTOMS DUTIABLE VALUE (CUD) | BF25: =SUM(BF21:BF23) -> 2099365 | BH25: Custom SOP | BJ25: Variable | BK25: 18000
B26: ='Pricing Trends'!R32 -> RBD CANOLA OIL | C26: ='Pricing Trends'!S32 -> 45118 | D26: ='Pricing Trends'!U32 -> 80.463781 | E26: FALSE | G26: Marketing Expenses - Brand Building | V26: SOYA (Local) | W26: =$AC$9 -> 0 | X26: 0 | Y26: =W26*X26 -> 0 | AE26: Angie | AF26: 46150 | AG26: Bottle 350mL | AH26: MCBRIDE | AK26: 350ML BOTTLE PALM (SWAK) | AN26: 43890 | AO26: pcs | AP26: 3.95 | AQ26: =AN26*AP26 -> 173365.5 | AZ26: =AP26 -> 3.95 | BB26: CUSTOM DUTIES | BH26: Processing Fee | BJ26: Fixed | BK26: 6000
B27: ='Pricing Trends'!R33 -> 0 | C27: ='Pricing Trends'!S33 -> 0 | D27: ='Pricing Trends'!U33 -> 0 | E27: FALSE | G27: General and Administrative Expenses | I27: =I6*0.01 -> 0.36 | J27: =I27/I$6 -> 0.01 | K27: =K6*0.01 -> 0.5 | L27: =K27/K$6 -> 0.01 | M27: =M6*0.01 -> 0.95 | N27: =M27/M$6 -> 0.01 | P27: =P6*0.01 -> 1.05 | Q27: =P27/P$6 -> 0.01 | S27: =S6*0.01 -> 1.15 | T27: =S27/S$6 -> 0.01 | V27: SOYA (Foreign) | W27: =$AC$10 -> 90.6633 | X27: 0 | Y27: =W27*X27 -> 0 | AE27: Wennie - Receipts | AF27: 46151 | AG27: Bottle 1L | AI27: CLIENT ACKNOWLEDGEMENT RECEIPT | AJ27: 0010686 | AK27: 1LTR36G1810Clear-Swak | AL27: 158 Bags x 110 Pcs | AM27: FG082 | AN27: 17380 | AO27: pcs | AP27: 7.2 | AQ27: =AP27*AN27 -> 125136 | AZ27: =AP27 -> 7.2 | BB27: Bank Charges | BD27: Variable | BE27: 0 | BF27: =SUM(BE27:BE33) -> 14674.85 | BH27: Documentation | BJ27: Fixed | BK27: 2000
B28: ='Pricing Trends'!R34 -> 0 | C28: ='Pricing Trends'!S34 -> 0 | D28: ='Pricing Trends'!U34 -> 0 | E28: FALSE | G28: Utilities Expenses | I28: =I6*0.01 -> 0.36 | J28: =I28/I$6 -> 0.01 | K28: =K6*0.01 -> 0.5 | L28: =K28/K$6 -> 0.01 | M28: =M6*0.01 -> 0.95 | N28: =M28/M$6 -> 0.01 | P28: =P6*0.01 -> 1.05 | Q28: =P28/P$6 -> 0.01 | S28: =S6*0.01 -> 1.15 | T28: =S28/S$6 -> 0.01 | V28: CANOLA (LOCAL) | W28: =$AC$11 -> 0 | X28: 0 | Y28: =W28*X28 -> 0 | AA28: OLD DATA | AE28: Wennie - Receipts | AF28: 46151 | AG28: Bottle Caps | AI28: CLIENT ACKNOWLEDGEMENT RECEIPT | AJ28: 0010686 | AK28: 1810Caps-Yellow | AL28: 4 Bags x 4000 + 1380 pcs | AM28: CP105 | AN28: 17380 | AO28: pcs | AP28: 0.7 | AQ28: =AP28*AN28 -> 12166 | AZ28: =AP28 -> 0.7 | BB28: Customs Duty | BD28: Variable | BE28: 0 | BH28: Local Trucking | BJ28: Fixed | BK28: 42000
B29: ='Pricing Trends'!R35 -> 0 | C29: ='Pricing Trends'!S35 -> 0 | D29: ='Pricing Trends'!U35 -> 0 | E29: FALSE | G29: Logistics Expenses - Delivery | J29: =I29/I$6 -> 0 | L29: =K29/K$6 -> 0 | N29: =M29/M$6 -> 0 | P29: =P6*0.03 -> 3.15 | Q29: =P29/P$6 -> 0.03 | S29: =S6*0.03 -> 3.45 | T29: =S29/S$6 -> 0.03 | V29: CANOLA (Foreign) | W29: =$AC$12 -> 84.3891 | X29: 1 | Y29: =W29*X29 -> 84.3891 | AE29: Wennie - Receipts | AF29: 46151 | AG29: Palm Oil | AI29: Finished Good Form | AK29: Mama Pina's Palm Oil 350ml x 36 BAS | AN29: 182 | AO29: box | AP29: 953.05 | AQ29: =AP29*AN29 -> 173455.1 | BB29: Brokerage Fee | BD29: Formulated | BE29: 6975.74 | BH29: Customs Handling Charges | BJ29: Fixed | BK29: 1500
B30: ='Pricing Trends'!R36 -> 0 | C30: ='Pricing Trends'!S36 -> 0 | D30: ='Pricing Trends'!U36 -> 0 | E30: FALSE | G30: Logistics Expenses - Pick Up | H30: l | I30: =M30*(35/100) -> 0.070895462 | J30: =I30/I$6 -> 0.0019693184 | K30: =M30*0.5 -> 0.10127923 | L30: =K30/K$6 -> 0.0020255846 | M30: =AZ40 -> 0.20255846 | N30: =M30/M$6 -> 0.0021321944 | P30: =((IFERROR(VLOOKUP(P2&$G$11,Validation!$E:$F,2,FALSE),0)*'Pick Up Cost'!$C$16)+(IFERROR(VLOOKUP(P2&$G$8,Validation!$E:$F,2,FALSE),0)*'Pick Up Cost'!$C$16)) -> 0 | Q30: =P30/P$6 -> 0 | S30: =((IFERROR(VLOOKUP(S2&$G$11,Validation!$E:$F,2,FALSE),0)*'Pick Up Cost'!$C$16)+(IFERROR(VLOOKUP(S2&$G$8,Validation!$E:$F,2,FALSE),0)*'Pick Up Cost'!$C$16)) -> 0 | T30: =S30/S$6 -> 0 | AE30: Wennie - Receipts | AF30: 46151 | AG30: Palm Oil | AI30: Finished Good Form | AK30: Mama Pina's Palm Oil 1L x 12 MZL BAS | AN30: 191 | AO30: box | AP30: 1486.2 | AQ30: =AP30*AN30 -> 283864.2 | BB30: Wharfage Due | BD30: Variable | BE30: 581.67 | BH30: Customs OT | BJ30: Fixed | BK30: 2000
B31: ='Pricing Trends'!R37 -> 0 | C31: ='Pricing Trends'!S37 -> 0 | D31: ='Pricing Trends'!U37 -> 0 | E31: FALSE | G31: Logistics Expenses - THC and Customs | I31: =M31*0.35 -> 0 | J31: =I31/I$6 -> 0 | K31: =M31*0.5 -> 0 | L31: =K31/K$6 -> 0 | N31: =M31/M$6 -> 0 | P31: =((IFERROR(VLOOKUP(P2&$G$7,Validation!$E:$F,2,FALSE),0)*'Shipping Cost'!$E$4)+(IFERROR(VLOOKUP(P2&$G$9,Validation!$E:$F,2,FALSE),0)*'Shipping Cost'!$C$4)+(IFERROR(VLOOKUP(P2&$G$10,Validation!$E:$F,2,FALSE),0)*'Shipping Cost'!$D$4)) -> 0 | Q31: =P31/P$6 -> 0 | S31: =((IFERROR(VLOOKUP(S2&$G$7,Validation!$E:$F,2,FALSE),0)*'Shipping Cost'!$E$4)+(IFERROR(VLOOKUP(S2&$G$9,Validation!$E:$F,2,FALSE),0)*'Shipping Cost'!$C$4)+(IFERROR(VLOOKUP(S2&$G$10,Validation!$E:$F,2,FALSE),0)*'Shipping Cost'!$D$4)) -> 0 | T31: =S31/S$6 -> 0 | AE31: Wennie - Receipts | AF31: 46151 | AG31: Palm Oil | AI31: Finished Good Form | AK31: Mama Pina's Palm Oil 1L x 12 BAS | AN31: 340 | AO31: box | AP31: 854.65 | AQ31: =AP31*AN31 -> 290581 | BB31: Arrastre Charge | BD31: Variable | BE31: 5837.44 | BH31: Xray Charges | BJ31: Fixed | BK31: 1000
B32: ='Pricing Trends'!R38 -> RBD COCONUT OIL | C32: ='Pricing Trends'!S38 -> 45468 | D32: ='Pricing Trends'!U38 -> 85.357269 | E32: FALSE | G32: Dollar Fluctuation Allowance Pricing | J32: =I32/I$6 -> 0 | K32: =K6*0.01 -> 0.5 | L32: =K32/K$6 -> 0.01 | N32: =M32/M$6 -> 0 | P32: =P10*0.05 -> 4.219455 | Q32: =P32/P$6 -> 0.040185286 | S32: =S7*0.05 -> 4.533165 | T32: =S32/S$6 -> 0.039418826 | AE32: Angie | AF32: 46151 | AG32: Bottle 1L | AH32: MCBRIDE | AK32: 1 LTER BOTTLE PALM (SWAK) | AL32: Pickup Php 7k | AN32: 17380 | AO32: pcs | AP32: 7.9 | AQ32: =AN32*AP32 -> 137302 | AZ32: =AP32 -> 7.9 | BB32: Documentary Stamp | BD32: Fixed | BE32: 280 | BH32: Custom Duties | BJ32: Formulated | BK32: =SUM(BE29:BE31) -> 13394.85
B33: ='Pricing Trends'!R39 -> 0 | C33: ='Pricing Trends'!S39 -> 0 | D33: ='Pricing Trends'!U39 -> 0 | E33: FALSE | G33: Cost of Money | J33: =I33/I$6 -> 0 | K33: =K6*0.01 -> 0.5 | L33: =K33/K$6 -> 0.01 | N33: =M33/M$6 -> 0 | P33: =P6*0.01 -> 1.05 | Q33: =P33/P$6 -> 0.01 | S33: =S6*0.01 -> 1.15 | T33: =S33/S$6 -> 0.01 | AE33: Wennie - Receipts | AF33: 46158 | AG33: Palm Oil | AH33: RMC RICOR MILLS CORP. | AI33: DELIVERY RECEIPT | AJ33: 2601-214 | AK33: Pick Up RBD Palm Oil | AN33: 30410 | AO33: KG | AP33: 85.3 | AQ33: =AN33*AP33 -> 2593973 | AR33: =AQ33/1.12*0.12 -> 277925.68 | AS33: =AQ33-AR33 -> 2316047.3 | AU33: =AN33*1.1364 -> 34557.924 | AW33: =AQ33 -> 2593973 | AX33: =AQ33/AN33 -> 85.3 | AY33: =AQ33/AU33 -> 75.061598 | BB33: Others | BD33: Fixed | BE33: 1000 | BH33: Miscellaneous | BJ33: Variable | BK33: 0
B34: ='Pricing Trends'!R40 -> RBD CANOLA OIL | C34: ='Pricing Trends'!S40 -> 0 | D34: ='Pricing Trends'!U40 -> 83.220041 | E34: TRUE | G34: Value Added Tax | J34: =I34/I$6 -> 0 | K34: =((K6/1.12)*0.12)-((K17/1.12)*0.12) -> 0.43636429 | L34: =K34/K$6 -> 0.0087272857 | N34: =M34/M$6 -> 0 | P34: =((P6/1.12)*0.12)-((P17/1.12)*0.12) -> 1.0499179 | Q34: =P34/P$6 -> 0.0099992177 | S34: =((S6/1.12)*0.12)-((S17/1.12)*0.12) -> 1.4491107 | T34: =S34/S$6 -> 0.012600963 | AE34: Angie | AF34: 46178 | AG34: Box 500mL | AH34: MCBRIDE | AK34: 500ML BOX PALM | AN34: 2000 | AO34: pcs | AP34: 20.9 | AQ34: =AN34*AP34 -> 41800 | AZ34: =AP34/24 -> 0.87083333 | BB34: TOTAL LANDED COST (TLC) | BE34: =SUM(BE25:BE33) -> 14674.85 | BF34: =SUM(BF25:BF32) -> 2114039.9 | BH34: TOTAL SHIPPING FEES | BJ34: =BK34/BF16 -> 5.3719653 | BK34: =SUM(BK23:BK33) -> 131251.08
B35: ='Pricing Trends'!R41 -> RBD SOYA BEAN OIL | C35: ='Pricing Trends'!S41 -> 0 | D35: ='Pricing Trends'!U41 -> 81.666042 | E35: TRUE | G35: Income Tax | J35: =I35/I$6 -> 0 | K35: =K6*0.01 -> 0.5 | L35: =K35/K$6 -> 0.01 | N35: =M35/M$6 -> 0 | P35: =P6*0.01 -> 1.05 | Q35: =P35/P$6 -> 0.01 | S35: =S6*0.01 -> 1.15 | T35: =S35/S$6 -> 0.01 | AE35: Angie | AF35: 46179 | AG35: Box 1L | AH35: MCBRIDE | AK35: 1 LITER BOX PALM SWAK | AN35: 7425 | AO35: pcs | AP35: 25.8 | AQ35: =AN35*AP35 -> 191565 | AZ35: =AP35/12 -> 2.15
B36: ='Pricing Trends'!R42 -> 0 | C36: ='Pricing Trends'!S42 -> 0 | D36: ='Pricing Trends'!U42 -> 0 | E36: FALSE | G36: NET PROFIT | I36: =I18-I19 -> 1.1965734 | J36: =I36/I6 -> 0.033238151 | K36: =K18-K19 -> -0.36491018 | L36: =K36/K6 -> -0.0072982037 | M36: =M18-M19 -> -0.18542513 | N36: =M36/M6 -> -0.0019518435 | P36: =P18-P19 -> -4.2201395 | Q36: =P36/P6 -> -0.040191805 | S36: =S18-S19 -> -1.9072424 | T36: =S36/S6 -> -0.016584716 | AE36: Angie | AF36: 46180 | AG36: Box 350mL | AH36: MCBRIDE | AK36: 350 LM BOX PALM | AN36: 6225 | AO36: pcs | AP36: 26 | AQ36: =AN36*AP36 -> 161850 | AZ36: =AP36/36 -> 0.72222222 | BB36: DISCREPANCY
B37: ='Pricing Trends'!R43 -> RBD PALM OLEIN (FOREIGN) | C37: ='Pricing Trends'!S43 -> 0 | D37: ='Pricing Trends'!U43 -> 64.843399 | E37: FALSE | AE37: Angie | AG37: Bottle 1L | AH37: Price Increase Chat | AK37: 1L Bottle - Price Increase Chat | AP37: 8.6 | AZ37: =AP37 -> 8.6 | BB37: DOLLAR PAYMENT | BD37: =BD16 -> 32680 | BE37: =BD37-BD16 -> 0 | BF37: =BE37*BF17 -> 0
B38: ='Pricing Trends'!R44 -> 0 | C38: ='Pricing Trends'!S44 -> 0 | D38: ='Pricing Trends'!U44 -> 0 | E38: FALSE | I38: note: Prices used @ Recent purchases -- Palm Oil @ Local Purchase + Soya and Canola @ Foreign Purchase | AE38: Angie | AG38: Bottle 350mL | AH38: Price Increase Chat | AK38: 350mL - Price Increase Chat | AP38: 4.1 | AZ38: =AP38 -> 4.1
B39: ='Pricing Trends'!R45 -> RBD PALM OLEIN (FOREIGN) | C39: ='Pricing Trends'!S45 -> 0 | D39: ='Pricing Trends'!U45 -> 82.366515 | E39: FALSE | I39: Price of boxes @ most recent purchase on May | AE39: Wennie-Receipts | AF39: 46129 | AG39: Flour | AH39: Mabuhay Interflour Inc. | AI39: DELIVERY RECEIPT | AJ39: 1012433 | AK39: CHOPSTICKS SNF PP BAG 25KG | AL39: 25kg | AM39: 1001700 | AN39: 400 | AO39: bags | AP39: =AQ39/AN39 -> 818.27675 | AQ39: 327310.7 | AT39: =AP39/25 -> 32.73107 | AX39: =AT39 -> 32.73107
B40: ='Pricing Trends'!R46 -> RBD PALM OLEIN (FOREIGN) | C40: ='Pricing Trends'!S46 -> 0 | D40: ='Pricing Trends'!U46 -> 74.65686 | E40: FALSE | I40: Prices of bottles @ most recent purchase | AE40: System | AF40: 46165 | AG40: Pickup - Palm | AH40: Angel Castro | AI40: System | AJ40: NT-005114 | AK40: PALM 5/16 Purchase Pickup | AN40: =AN33 -> 30410 | AO40: =AO33 -> KG | AQ40: 7000 | AU40: =AU33 -> 34557.924 | AZ40: =AQ40/AU40 -> 0.20255846
B41: ='Pricing Trends'!R47 -> 0 | C41: ='Pricing Trends'!S47 -> 0 | D41: ='Pricing Trends'!U47 -> 0 | E41: FALSE
B42: ='Pricing Trends'!R48 -> 0 | C42: ='Pricing Trends'!S48 -> 0 | D42: ='Pricing Trends'!U48 -> 0 | E42: FALSE
B43: ='Pricing Trends'!R49 -> 0 | C43: ='Pricing Trends'!S49 -> 0 | D43: ='Pricing Trends'!U49 -> 0 | E43: FALSE
B44: ='Pricing Trends'!R50 -> 0 | C44: ='Pricing Trends'!S50 -> 0 | D44: ='Pricing Trends'!U50 -> 0 | E44: FALSE
B45: ='Pricing Trends'!R51 -> 0 | C45: ='Pricing Trends'!S51 -> 0 | D45: ='Pricing Trends'!U51 -> 0 | E45: FALSE
B46: ='Pricing Trends'!R52 -> 0 | C46: ='Pricing Trends'!S52 -> 0 | D46: ='Pricing Trends'!U52 -> 0 | E46: FALSE
B47: ='Pricing Trends'!R53 -> 0 | C47: ='Pricing Trends'!S53 -> 0 | D47: ='Pricing Trends'!U53 -> 0 | E47: FALSE
B48: ='Pricing Trends'!R54 -> 0 | C48: ='Pricing Trends'!S54 -> 0 | D48: ='Pricing Trends'!U54 -> 0 | E48: FALSE
B49: ='Pricing Trends'!R55 -> 0 | C49: ='Pricing Trends'!S55 -> 0 | D49: ='Pricing Trends'!U55 -> 0 | E49: FALSE

Sheet Validation
B2: BLENDING PRICE COMPARISON PER CODE
B4: Type | C4: Code | D4: Oil | E4: Conca | F4: Mix | G4: T Price | H4: 350ml | I4: 500ml | J4: 1L | K4: 2L | L4: 4L | M4: 180ml | N4: 300ml | O4: 17KG | Q4: PALM OLEIN CODE
B5: PALM OLEIN | C5: BAS | D5: RBD SOYA BEAN OIL | E5: =C5&D5 -> BASRBD SOYA BEAN OIL | F5: 0.4 | G5: =SUMIFS('Pricing Trends'!U:U,'Pricing Trends'!R:R,Validation!D5,'Pricing Trends'!P:P,"TRUE")/COUNTIFS('Pricing Trends'!R:R,Validation!D5,'Pricing Trends'!P:P,"TRUE") -> 69.078872 | H5: =G5*F5*0.35 -> 9.6710421 | I5: =G5*F5*0.5 -> 13.815774 | J5: =G5*F5 -> 27.631549 | K5: =J5*2 -> 55.263098 | L5: =K5*2 -> 110.5262 | M5: =J5*0.18 -> 4.9736788 | N5: =J5*0.3 -> 8.2894646 | O5: =J5*15.66*1.1364 -> 491.7317 | Q5: =C5 -> BAS
C6: BAS | D6: RBD PALM OLEIN (LOCAL) | E6: =C6&D6 -> BASRBD PALM OLEIN (LOCAL) | F6: 0.6 | G6: =SUMIFS('Pricing Trends'!U:U,'Pricing Trends'!R:R,Validation!D6,'Pricing Trends'!P:P,"TRUE")/COUNTIFS('Pricing Trends'!R:R,Validation!D6,'Pricing Trends'!P:P,"TRUE") -> #DIV/0! | H6: =G6*F6*0.35 -> #DIV/0! | I6: =G6*F6*0.5 -> #DIV/0! | J6: =G6*F6 -> #DIV/0! | K6: =J6*2 -> #DIV/0! | L6: =K6*2 -> #DIV/0! | M6: =J6*0.18 -> #DIV/0! | N6: =J6*0.3 -> #DIV/0! | O6: =J6*15.66*1.1364 -> #DIV/0! | Q6: =C8 -> BTC
H7: =SUM(H5:H6) -> #DIV/0! | I7: =SUM(I5:I6) -> #DIV/0! | J7: =SUM(J5:J6) -> #DIV/0! | K7: =SUM(K5:K6) -> #DIV/0! | L7: =SUM(L5:L6) -> #DIV/0! | M7: =SUM(M5:M6) -> #DIV/0! | N7: =SUM(N5:N6) -> #DIV/0! | O7: =SUM(O5:O6) -> #DIV/0! | Q7: =C11 -> FD3
C8: BTC | D8: RBD SOYA BEAN OIL | E8: =C8&D8 -> BTCRBD SOYA BEAN OIL | F8: 0.3 | G8: =SUMIFS('Pricing Trends'!U:U,'Pricing Trends'!R:R,Validation!D8,'Pricing Trends'!P:P,"TRUE")/COUNTIFS('Pricing Trends'!R:R,Validation!D8,'Pricing Trends'!P:P,"TRUE") -> 69.078872 | H8: =G8*F8*0.35 -> 7.2532815 | I8: =G8*F8*0.5 -> 10.361831 | J8: =G8*F8 -> 20.723662 | K8: =J8*2 -> 41.447323 | L8: =K8*2 -> 82.894646 | M8: =J8*0.18 -> 3.7302591 | N8: =J8*0.3 -> 6.2170985 | O8: =J8*15.66*1.1364 -> 368.79878 | Q8: =C14 -> BAS.F64
C9: BTC | D9: RBD PALM OLEIN (LOCAL) | E9: =C9&D9 -> BTCRBD PALM OLEIN (LOCAL) | F9: 0.7 | G9: =SUMIFS('Pricing Trends'!U:U,'Pricing Trends'!R:R,Validation!D9,'Pricing Trends'!P:P,"TRUE")/COUNTIFS('Pricing Trends'!R:R,Validation!D9,'Pricing Trends'!P:P,"TRUE") -> #DIV/0! | H9: =G9*F9*0.35 -> #DIV/0! | I9: =G9*F9*0.5 -> #DIV/0! | J9: =G9*F9 -> #DIV/0! | K9: =J9*2 -> #DIV/0! | L9: =K9*2 -> #DIV/0! | M9: =J9*0.18 -> #DIV/0! | N9: =J9*0.3 -> #DIV/0! | O9: =J9*15.66*1.1364 -> #DIV/0! | Q9: =C17 -> BAS.F73
H10: =SUM(H8:H9) -> #DIV/0! | I10: =SUM(I8:I9) -> #DIV/0! | J10: =SUM(J8:J9) -> #DIV/0! | K10: =SUM(K8:K9) -> #DIV/0! | L10: =SUM(L8:L9) -> #DIV/0! | M10: =SUM(M8:M9) -> #DIV/0! | N10: =SUM(N8:N9) -> #DIV/0! | O10: =SUM(O8:O9) -> #DIV/0! | Q10: =C21 -> BAS.F82
C11: FD3 | D11: RBD SOYA BEAN OIL | E11: =C11&D11 -> FD3RBD SOYA BEAN OIL | F11: 0.2 | G11: =SUMIFS('Pricing Trends'!U:U,'Pricing Trends'!R:R,Validation!D11,'Pricing Trends'!P:P,"TRUE")/COUNTIFS('Pricing Trends'!R:R,Validation!D11,'Pricing Trends'!P:P,"TRUE") -> 69.078872 | H11: =G11*F11*0.35 -> 4.835521 | I11: =G11*F11*0.5 -> 6.9078872 | J11: =G11*F11 -> 13.815774 | K11: =J11*2 -> 27.631549 | L11: =K11*2 -> 55.263098 | M11: =J11*0.18 -> 2.4868394 | N11: =J11*0.3 -> 4.1447323 | O11: =J11*15.66*1.1364 -> 245.86585 | Q11: =C23 -> PALM.100
C12: FD3 | D12: RBD PALM OLEIN (LOCAL) | E12: =C12&D12 -> FD3RBD PALM OLEIN (LOCAL) | F12: 0.8 | G12: =SUMIFS('Pricing Trends'!U:U,'Pricing Trends'!R:R,Validation!D12,'Pricing Trends'!P:P,"TRUE")/COUNTIFS('Pricing Trends'!R:R,Validation!D12,'Pricing Trends'!P:P,"TRUE") -> #DIV/0! | H12: =G12*F12*0.35 -> #DIV/0! | I12: =G12*F12*0.5 -> #DIV/0! | J12: =G12*F12 -> #DIV/0! | K12: =J12*2 -> #DIV/0! | L12: =K12*2 -> #DIV/0! | M12: =J12*0.18 -> #DIV/0! | N12: =J12*0.3 -> #DIV/0! | O12: =J12*15.66*1.1364 -> #DIV/0! | Q12: =C25 -> PALMF.100
H13: =SUM(H11:H12) -> #DIV/0! | I13: =SUM(I11:I12) -> #DIV/0! | J13: =SUM(J11:J12) -> #DIV/0! | K13: =SUM(K11:K12) -> #DIV/0! | L13: =SUM(L11:L12) -> #DIV/0! | M13: =SUM(M11:M12) -> #DIV/0! | N13: =SUM(N11:N12) -> #DIV/0! | O13: =SUM(O11:O12) -> #DIV/0!
C14: BAS.F64 | D14: RBD SOYA BEAN OIL | E14: =C14&D14 -> BAS.F64RBD SOYA BEAN OIL | F14: 0.4 | G14: =SUMIFS('Pricing Trends'!U:U,'Pricing Trends'!R:R,Validation!D14,'Pricing Trends'!P:P,"TRUE")/COUNTIFS('Pricing Trends'!R:R,Validation!D14,'Pricing Trends'!P:P,"TRUE") -> 69.078872 | H14: =G14*F14*0.35 -> 9.6710421 | I14: =G14*F14*0.5 -> 13.815774 | J14: =G14*F14 -> 27.631549 | K14: =J14*2 -> 55.263098 | L14: =K14*2 -> 110.5262 | M14: =J14*0.18 -> 4.9736788 | N14: =J14*0.3 -> 8.2894646 | O14: =J14*15.66*1.1364 -> 491.7317
C15: BAS.F64 | D15: RBD PALM OLEIN (FOREIGN) | E15: =C15&D15 -> BAS.F64RBD PALM OLEIN (FOREIGN) | F15: 0.6 | G15: =SUMIFS('Pricing Trends'!U:U,'Pricing Trends'!R:R,Validation!D15,'Pricing Trends'!P:P,"TRUE")/COUNTIFS('Pricing Trends'!R:R,Validation!D15,'Pricing Trends'!P:P,"TRUE") -> 60.65316 | H15: =G15*F15*0.35 -> 12.737164 | I15: =G15*F15*0.5 -> 18.195948 | J15: =G15*F15 -> 36.391896 | K15: =J15*2 -> 72.783792 | L15: =K15*2 -> 145.56758 | M15: =J15*0.18 -> 6.5505413 | N15: =J15*0.3 -> 10.917569 | O15: =J15*15.66*1.1364 -> 647.63105
H16: =SUM(H14:H15) -> 22.408206 | I16: =SUM(I14:I15) -> 32.011722 | J16: =SUM(J14:J15) -> 64.023445 | K16: =SUM(K14:K15) -> 128.04689 | L16: =SUM(L14:L15) -> 256.09378 | M16: =SUM(M14:M15) -> 11.52422 | N16: =SUM(N14:N15) -> 19.207033 | O16: =SUM(O14:O15) -> 1139.3628
C17: BAS.F73 | D17: RBD SOYA BEAN OIL | E17: =C17&D17 -> BAS.F73RBD SOYA BEAN OIL | F17: 0.3 | G17: =SUMIFS('Pricing Trends'!U:U,'Pricing Trends'!R:R,Validation!D17,'Pricing Trends'!P:P,"TRUE")/COUNTIFS('Pricing Trends'!R:R,Validation!D17,'Pricing Trends'!P:P,"TRUE") -> 69.078872 | H17: =G17*F17*0.35 -> 7.2532815 | I17: =G17*F17*0.5 -> 10.361831 | J17: =G17*F17 -> 20.723662 | K17: =J17*2 -> 41.447323 | L17: =K17*2 -> 82.894646 | M17: =J17*0.18 -> 3.7302591 | N17: =J17*0.3 -> 6.2170985 | O17: =J17*15.66*1.1364 -> 368.79878
C18: BAS.F73 | D18: RBD PALM OLEIN (FOREIGN) | E18: =C18&D18 -> BAS.F73RBD PALM OLEIN (FOREIGN) | F18: 0.7 | G18: =SUMIFS('Pricing Trends'!U:U,'Pricing Trends'!R:R,Validation!D18,'Pricing Trends'!P:P,"TRUE")/COUNTIFS('Pricing Trends'!R:R,Validation!D18,'Pricing Trends'!P:P,"TRUE") -> 60.65316 | H18: =G18*F18*0.35 -> 14.860024 | I18: =G18*F18*0.5 -> 21.228606 | J18: =G18*F18 -> 42.457212 | K18: =J18*2 -> 84.914424 | L18: =K18*2 -> 169.82885 | M18: =J18*0.18 -> 7.6422982 | N18: =J18*0.3 -> 12.737164 | O18: =J18*15.66*1.1364 -> 755.56956
H19: =SUM(H17:H18) -> 22.113306 | I19: =SUM(I17:I18) -> 31.590437 | J19: =SUM(J17:J18) -> 63.180874 | K19: =SUM(K17:K18) -> 126.36175 | L19: =SUM(L17:L18) -> 252.72349 | M19: =SUM(M17:M18) -> 11.372557 | N19: =SUM(N17:N18) -> 18.954262 | O19: =SUM(O17:O18) -> 1124.3683
C20: BAS.F82 | D20: RBD SOYA BEAN OIL | E20: =C20&D20 -> BAS.F82RBD SOYA BEAN OIL | F20: 0.2 | G20: =SUMIFS('Pricing Trends'!U:U,'Pricing Trends'!R:R,Validation!D20,'Pricing Trends'!P:P,"TRUE")/COUNTIFS('Pricing Trends'!R:R,Validation!D20,'Pricing Trends'!P:P,"TRUE") -> 69.078872 | H20: =G20*F20*0.35 -> 4.835521 | I20: =G20*F20*0.5 -> 6.9078872 | J20: =G20*F20 -> 13.815774 | K20: =J20*2 -> 27.631549 | L20: =K20*2 -> 55.263098 | M20: =J20*0.18 -> 2.4868394 | N20: =J20*0.3 -> 4.1447323 | O20: =J20*15.66*1.1364 -> 245.86585
C21: BAS.F82 | D21: RBD PALM OLEIN (FOREIGN) | E21: =C21&D21 -> BAS.F82RBD PALM OLEIN (FOREIGN) | F21: 0.8 | G21: =SUMIFS('Pricing Trends'!U:U,'Pricing Trends'!R:R,Validation!D21,'Pricing Trends'!P:P,"TRUE")/COUNTIFS('Pricing Trends'!R:R,Validation!D21,'Pricing Trends'!P:P,"TRUE") -> 60.65316 | H21: =G21*F21*0.35 -> 16.982885 | I21: =G21*F21*0.5 -> 24.261264 | J21: =G21*F21 -> 48.522528 | K21: =J21*2 -> 97.045056 | L21: =K21*2 -> 194.09011 | M21: =J21*0.18 -> 8.734055 | N21: =J21*0.3 -> 14.556758 | O21: =J21*15.66*1.1364 -> 863.50807
H22: =SUM(H20:H21) -> 21.818406 | I22: =SUM(I20:I21) -> 31.169151 | J22: =SUM(J20:J21) -> 62.338302 | K22: =SUM(K20:K21) -> 124.6766 | L22: =SUM(L20:L21) -> 249.35321 | M22: =SUM(M20:M21) -> 11.220894 | N22: =SUM(N20:N21) -> 18.701491 | O22: =SUM(O20:O21) -> 1109.3739
C23: PALM.100 | D23: RBD PALM OLEIN (LOCAL) | E23: =C23&D23 -> PALM.100RBD PALM OLEIN (LOCAL) | F23: 1 | G23: =SUMIFS('Pricing Trends'!U:U,'Pricing Trends'!R:R,Validation!D23,'Pricing Trends'!P:P,"TRUE")/COUNTIFS('Pricing Trends'!R:R,Validation!D23,'Pricing Trends'!P:P,"TRUE") -> #DIV/0! | H23: =G23*F23*0.35 -> #DIV/0! | I23: =G23*F23*0.5 -> #DIV/0! | J23: =G23*F23 -> #DIV/0! | K23: =J23*2 -> #DIV/0! | L23: =K23*2 -> #DIV/0! | M23: =J23*0.18 -> #DIV/0! | N23: =J23*0.3 -> #DIV/0! | O23: =J23*15.66*1.1364 -> #DIV/0!
H24: =SUM(H23) -> #DIV/0! | I24: =SUM(I23) -> #DIV/0! | J24: =SUM(J23) -> #DIV/0! | K24: =SUM(K23) -> #DIV/0! | L24: =SUM(L23) -> #DIV/0! | M24: =SUM(M23) -> #DIV/0! | N24: =SUM(N23) -> #DIV/0! | O24: =SUM(O23) -> #DIV/0!
C25: PALMF.100 | D25: RBD PALM OLEIN (FOREIGN) | E25: =C25&D25 -> PALMF.100RBD PALM OLEIN (FOREIGN) | F25: 1 | G25: =SUMIFS('Pricing Trends'!U:U,'Pricing Trends'!R:R,Validation!D25,'Pricing Trends'!P:P,"TRUE")/COUNTIFS('Pricing Trends'!R:R,Validation!D25,'Pricing Trends'!P:P,"TRUE") -> 60.65316 | H25: =G25*F25*0.35 -> 21.228606 | I25: =G25*F25*0.5 -> 30.32658 | J25: =G25*F25 -> 60.65316 | K25: =J25*2 -> 121.30632 | L25: =K25*2 -> 242.61264 | M25: =J25*0.18 -> 10.917569 | N25: =J25*0.3 -> 18.195948 | O25: =J25*15.66*1.1364 -> 1079.3851
H26: =SUM(H25:H25) -> 21.228606 | I26: =SUM(I25:I25) -> 30.32658 | J26: =SUM(J25:J25) -> 60.65316 | K26: =SUM(K25:K25) -> 121.30632 | L26: =SUM(L25:L25) -> 242.61264 | M26: =SUM(M25:M25) -> 10.917569 | N26: =SUM(N25:N25) -> 18.195948 | O26: =SUM(O25:O25) -> 1079.3851
B27: CANOLEIN | C27: CANF.82 | D27: RBD CANOLA OIL | E27: =C27&D27 -> CANF.82RBD CANOLA OIL | F27: 0.8 | G27: =SUMIFS('Pricing Trends'!U:U,'Pricing Trends'!R:R,Validation!D27,'Pricing Trends'!P:P,"TRUE")/COUNTIFS('Pricing Trends'!R:R,Validation!D27,'Pricing Trends'!P:P,"TRUE") -> 83.220041 | J27: =G27*F27 -> 66.576033 | K27: =J27*2 -> 133.15207 | L27: =K27*2 -> 266.30413 | M27: =J27*0.18 -> 11.983686 | N27: =J27*0.3 -> 19.97281 | O27: =J27*15.66*1.1364 -> 1184.7887 | Q27: CANOLEIN CODE
C28: CANF.82 | D28: RBD PALM OLEIN (FOREIGN) | E28: =C28&D28 -> CANF.82RBD PALM OLEIN (FOREIGN) | F28: 0.2 | G28: =SUMIFS('Pricing Trends'!U:U,'Pricing Trends'!R:R,Validation!D28,'Pricing Trends'!P:P,"TRUE")/COUNTIFS('Pricing Trends'!R:R,Validation!D28,'Pricing Trends'!P:P,"TRUE") -> 60.65316 | J28: =G28*F28 -> 12.130632 | K28: =J28*2 -> 24.261264 | L28: =K28*2 -> 48.522528 | M28: =J28*0.18 -> 2.1835138 | N28: =J28*0.3 -> 3.6391896 | O28: =J28*15.66*1.1364 -> 215.87702 | Q28: =C27 -> CANF.82
J29: =SUM(J27:J28) -> 78.706665 | K29: =SUM(K27:K28) -> 157.41333 | L29: =SUM(L27:L28) -> 314.82666 | M29: =SUM(M27:M28) -> 14.1672 | N29: =SUM(N27:N28) -> 23.612 | O29: =SUM(O27:O28) -> 1400.6657 | Q29: =C30 -> CAN.100
C30: CAN.100 | D30: RBD CANOLA OIL | E30: =C30&D30 -> CAN.100RBD CANOLA OIL | F30: 1 | G30: =SUMIFS('Pricing Trends'!U:U,'Pricing Trends'!R:R,Validation!D30,'Pricing Trends'!P:P,"TRUE")/COUNTIFS('Pricing Trends'!R:R,Validation!D30,'Pricing Trends'!P:P,"TRUE") -> 83.220041 | J30: =G30*F30 -> 83.220041 | K30: =J30*2 -> 166.44008 | L30: =K30*2 -> 332.88017 | M30: =J30*0.18 -> 14.979607 | N30: =J30*0.3 -> 24.966012 | O30: =J30*15.66*1.1364 -> 1480.9859
J31: =SUM(J30) -> 83.220041 | K31: =SUM(K30) -> 166.44008 | L31: =SUM(L30) -> 332.88017 | M31: =SUM(M30) -> 14.979607 | N31: =SUM(N30) -> 24.966012 | O31: =SUM(O30) -> 1480.9859
B32: SOYA OIL | C32: SOYF.73 | D32: RBD SOYA BEAN OIL | E32: =C32&D32 -> SOYF.73RBD SOYA BEAN OIL | F32: 0.7 | G32: =SUMIFS('Pricing Trends'!U:U,'Pricing Trends'!R:R,Validation!D32,'Pricing Trends'!P:P,"TRUE")/COUNTIFS('Pricing Trends'!R:R,Validation!D32,'Pricing Trends'!P:P,"TRUE") -> 69.078872 | J32: =G32*F32 -> 48.35521 | K32: =J32*2 -> 96.710421 | L32: =K32*2 -> 193.42084 | M32: =J32*0.18 -> 8.7039379 | N32: =J32*0.3 -> 14.506563 | O32: =J32*15.66*1.1364 -> 860.53048 | Q32: SOYA OIL CODE
C33: SOYF.73 | D33: RBD PALM OLEIN (FOREIGN) | E33: =C33&D33 -> SOYF.73RBD PALM OLEIN (FOREIGN) | F33: 0.3 | G33: =SUMIFS('Pricing Trends'!U:U,'Pricing Trends'!R:R,Validation!D33,'Pricing Trends'!P:P,"TRUE")/COUNTIFS('Pricing Trends'!R:R,Validation!D33,'Pricing Trends'!P:P,"TRUE") -> 60.65316 | J33: =G33*F33 -> 18.195948 | K33: =J33*2 -> 36.391896 | L33: =K33*2 -> 72.783792 | M33: =J33*0.18 -> 3.2752706 | N33: =J33*0.3 -> 5.4587844 | O33: =J33*15.66*1.1364 -> 323.81553 | Q33: =C32 -> SOYF.73
J34: =SUM(J32:J33) -> 66.551158 | K34: =SUM(K32:K33) -> 133.10232 | L34: =SUM(L32:L33) -> 266.20463 | M34: =SUM(M32:M33) -> 11.979208 | N34: =SUM(N32:N33) -> 19.965347 | O34: =SUM(O32:O33) -> 1184.346 | Q34: =C35 -> SOYF.82
C35: SOYF.82 | D35: RBD SOYA BEAN OIL | E35: =C35&D35 -> SOYF.82RBD SOYA BEAN OIL | F35: 0.8 | G35: =SUMIFS('Pricing Trends'!U:U,'Pricing Trends'!R:R,Validation!D35,'Pricing Trends'!P:P,"TRUE")/COUNTIFS('Pricing Trends'!R:R,Validation!D35,'Pricing Trends'!P:P,"TRUE") -> 69.078872 | J35: =G35*F35 -> 55.263098 | K35: =J35*2 -> 110.5262 | L35: =K35*2 -> 221.05239 | M35: =J35*0.18 -> 9.9473576 | N35: =J35*0.3 -> 16.578929 | O35: =J35*15.66*1.1364 -> 983.46341 | Q35: =C38 -> SOY.100
C36: SOYF.82 | D36: RBD PALM OLEIN (FOREIGN) | E36: =C36&D36 -> SOYF.82RBD PALM OLEIN (FOREIGN) | F36: 0.2 | G36: =SUMIFS('Pricing Trends'!U:U,'Pricing Trends'!R:R,Validation!D36,'Pricing Trends'!P:P,"TRUE")/COUNTIFS('Pricing Trends'!R:R,Validation!D36,'Pricing Trends'!P:P,"TRUE") -> 60.65316 | J36: =G36*F36 -> 12.130632 | K36: =J36*2 -> 24.261264 | L36: =K36*2 -> 48.522528 | M36: =J36*0.18 -> 2.1835138 | N36: =J36*0.3 -> 3.6391896 | O36: =J36*15.66*1.1364 -> 215.87702
J37: =SUM(J35:J36) -> 67.39373 | K37: =SUM(K35:K36) -> 134.78746 | L37: =SUM(L35:L36) -> 269.57492 | M37: =SUM(M35:M36) -> 12.130871 | N37: =SUM(N35:N36) -> 20.218119 | O37: =SUM(O35:O36) -> 1199.3404
C38: SOY.100 | D38: RBD SOYA BEAN OIL | E38: =C38&D38 -> SOY.100RBD SOYA BEAN OIL | F38: 1 | G38: =SUMIFS('Pricing Trends'!U:U,'Pricing Trends'!R:R,Validation!D38,'Pricing Trends'!P:P,"TRUE")/COUNTIFS('Pricing Trends'!R:R,Validation!D38,'Pricing Trends'!P:P,"TRUE") -> 69.078872 | J38: =G38*F38 -> 69.078872 | K38: =J38*2 -> 138.15774 | L38: =K38*2 -> 276.31549 | M38: =J38*0.18 -> 12.434197 | N38: =J38*0.3 -> 20.723662 | O38: =J38*15.66*1.1364 -> 1229.3293
J39: =SUM(J38:J38) -> 69.078872 | K39: =SUM(K38:K38) -> 138.15774 | L39: =SUM(L38:L38) -> 276.31549 | M39: =SUM(M38:M38) -> 12.434197 | N39: =SUM(N38:N38) -> 20.723662 | O39: =SUM(O38:O38) -> 1229.3293
B40: VEGETABLE OIL | C40: VG100 | D40: RBD COCONUT OIL | E40: =C40&D40 -> VG100RBD COCONUT OIL | F40: 1 | G40: =SUMIFS('Pricing Trends'!U:U,'Pricing Trends'!R:R,Validation!D40,'Pricing Trends'!P:P,"TRUE")/COUNTIFS('Pricing Trends'!R:R,Validation!D40,'Pricing Trends'!P:P,"TRUE") -> 85.357269 | J40: =G40*F40 -> 85.357269 | K40: =J40*2 -> 170.71454 | L40: =K40*2 -> 341.42907 | M40: =J40*0.18 -> 15.364308 | N40: =J40*0.3 -> 25.607181 | O40: =J40*1.1364*15.66 -> 1519.02
J41: =SUM(J40:J40) -> 85.357269 | K41: =SUM(K40:K40) -> 170.71454 | L41: =SUM(L40:L40) -> 341.42907 | M41: =SUM(M40:M40) -> 15.364308 | N41: =SUM(N40:N40) -> 25.607181 | O41: =SUM(O40:O40) -> 1519.02

Sheet PALM
B2: 1ST ORDER | M2: 2ND ORDER | X2: 3RD ORDER | AI2: 4TH ORDER | AT2: 5TH ORDER | BE2: 6TH ORDER | BP2: 7TH ORDER | CA2: 8TH ORDER | CL2: CP10 | CW2: FOR OSAVE | DI2: PENDING 01022025
B4: SUPPLIER INFORMATION | H4: PAYMENT SUMMARY AND COST PER UNIT (Formulated Table) | M4: SUPPLIER INFORMATION | S4: PAYMENT SUMMARY AND COST PER UNIT (Formulated Table) | X4: SUPPLIER INFORMATION | AD4: PAYMENT SUMMARY AND COST PER UNIT (Formulated Table) | AI4: SUPPLIER INFORMATION | AO4: PAYMENT SUMMARY AND COST PER UNIT (Formulated Table) | AT4: SUPPLIER INFORMATION | AZ4: PAYMENT SUMMARY AND COST PER UNIT (Formulated Table) | BE4: SUPPLIER INFORMATION | BK4: PAYMENT SUMMARY AND COST PER UNIT (Formulated Table) | BP4: SUPPLIER INFORMATION | BV4: PAYMENT SUMMARY AND COST PER UNIT (Formulated Table) | CA4: SUPPLIER INFORMATION | CG4: PAYMENT SUMMARY AND COST PER UNIT (Formulated Table) | CL4: SUPPLIER INFORMATION | CR4: PAYMENT SUMMARY AND COST PER UNIT (Formulated Table) | CW4: SUPPLIER INFORMATION | DC4: PAYMENT SUMMARY AND COST PER UNIT (Formulated Table) | DI4: SUPPLIER INFORMATION | DO4: PAYMENT SUMMARY AND COST PER UNIT (Formulated Table)
B5: Supplier: | C5: Cornerstone APAC (S) PTE LTD | H5: Description | I5: Amount | J5: CPU (KG) | K5: CPU (LTR) | M5: Supplier: | N5: MAC World Globality Reliable | S5: Description | T5: Amount | U5: CPU (KG) | V5: CPU (LTR) | X5: Supplier: | Y5: Cornerstone APAC (S) PTE LTD | AD5: Description | AE5: Amount | AF5: CPU (KG) | AG5: CPU (LTR) | AI5: Supplier: | AJ5: Cornerstone APAC (S) PTE LTD | AO5: Description | AP5: Amount | AQ5: CPU (KG) | AR5: CPU (LTR) | AT5: Supplier: | AU5: MOI INTERNATIONAL (SINGAPORE) PTE. LTD. | AZ5: Description | BA5: Amount | BB5: CPU (KG) | BC5: CPU (LTR) | BE5: Supplier: | BF5: MOI INTERNATIONAL (SINGAPORE) PTE. LTD. | BK5: Description | BL5: Amount | BM5: CPU (KG) | BN5: CPU (LTR) | BP5: Supplier: | BQ5: MOI INTERNATIONAL (SINGAPORE) PTE. LTD. | BV5: Description | BW5: Amount | BX5: CPU (KG) | BY5: CPU (LTR) | CA5: Supplier: | CB5: MOI INTERNATIONAL (SINGAPORE) PTE. LTD. | CG5: Description | CH5: Amount | CI5: CPU (KG) | CJ5: CPU (LTR) | CL5: Supplier: | CM5: MOI INTERNATIONAL (SINGAPORE) PTE. LTD. | CR5: Description | CS5: Amount | CT5: CPU (KG) | CU5: CPU (LTR) | CW5: Supplier: | CX5: MOI INTERNATIONAL (SINGAPORE) PTE. LTD. | DC5: Description | DD5: Amount | DE5: CPU (KG) | DF5: CPU (LTR) | DI5: Supplier: | DJ5: MOI INTERNATIONAL (SINGAPORE) PTE. LTD. | DO5: Description | DP5: Amount | DQ5: CPU (KG) | DR5: CPU (LTR)
B6: Address: | C6: 190 Middle Road #19-05 Fortune Centre Singapore | H6: As per Foreign Cost | I6: =F22+F38 -> 1802264.5 | J6: =I6/D16 -> 87.108 | K6: =I6/F17 -> 76.652587 | M6: Address: | S6: As per Foreign Cost | T6: =Q22+Q38 -> 1270386 | U6: =T6/O16 -> 59.475 | V6: =T6/Q17 -> 52.336325 | X6: Address: | Y6: 190 Middle Road #19-05 Fortune Centre Singapore | AD6: As per Foreign Cost | AE6: =AB22+AB38 -> 1434720 | AF6: =AE6/Z16 -> 67.803403 | AG6: =AE6/AB17 -> 59.665085 | AI6: Address: | AJ6: 190 Middle Road #19-05 Fortune Centre Singapore | AO6: As per Foreign Cost | AP6: =AM22+AM38 -> 1413467.6 | AQ6: =AP6/AK16 -> 66.673 | AR6: =AP6/AM17 -> 58.670363 | AT6: Address: | AU6: 5, International Business Park, #04-00 Mewah Building, Singapore | AZ6: As per Foreign Cost | BA6: =AX22+AX38 -> 1320930.6 | BB6: =BA6/AV16 -> 62.22 | BC6: =BA6/AX17 -> 54.751848 | BE6: Address: | BF6: 5, International Business Park, #04-00 Mewah Building, Singapore | BK6: As per Foreign Cost | BL6: =BI22+BI38 -> 1337730 | BM6: =BL6/BG16 -> 62.22 | BN6: =BL6/BI17 -> 54.751848 | BP6: Address: | BQ6: 5, International Business Park, #04-00 Mewah Building, Singapore | BV6: As per Foreign Cost | BW6: =BT22+BT38 -> 1350845 | BX6: =BW6/BR16 -> 62.83 | BY6: =BW6/BT17 -> 55.288631 | CA6: Address: | CB6: 5, International Business Park, #04-00 Mewah Building, Singapore | CG6: As per Foreign Cost | CH6: =CE22+CE38 -> 1381558.5 | CI6: =CH6/CC16 -> 64.05 | CJ6: =CH6/CE17 -> 56.362196 | CL6: Address: | CM6: 5, International Business Park, #04-00 Mewah Building, Singapore | CR6: As per Foreign Cost | CS6: =CP22+CP38 -> 1390190 | CT6: =CS6/CN16 -> 64.66 | CU6: =CS6/CP17 -> 56.898979 | CW6: Address: | CX6: 5, International Business Park, #04-00 Mewah Building, Singapore | DC6: As per Foreign Cost | DD6: =DA22+DA38 -> 1578924 | DE6: =DD6/CY16 -> 73.2 | DF6: =DD6/DA17 -> 64.413939 | DI6: Address: | DJ6: 5, International Business Park, #04-00 Mewah Building, Singapore | DO6: As per Foreign Cost | DP6: =DM22+DM38 -> 1830000 | DQ6: =DP6/DK16 -> 84.840056 | DR6: =DP6/DM17 -> 74.65686
B7: Shippine Line: | C7: Save and Best Cargo Logistic Corp | H7: As per Local Cost | I7: =K35+J21 -> 335246.54 | J7: =I7/D16 -> 16.203313 | K7: =I7/F17 -> 14.258459 | M7: Shippine Line: | N7: Save and Best Cargo Logistic Corp | S7: As per Local Cost | T7: =V35+U21 -> 306172.07 | U7: =T7/O16 -> 14.333898 | V7: =T7/Q17 -> 12.613427 | X7: Shippine Line: | Y7: Save and Best Cargo Logistic Corp | AD7: As per Local Cost | AE7: =AG35+AF21 -> 311309 | AF7: =AE7/Z16 -> 14.712146 | AG7: =AE7/AB17 -> 12.946274 | AI7: Shippine Line: | AJ7: Save and Best Cargo Logistic Corp | AO7: As per Local Cost | AP7: =AR35+AQ21 -> 308737.46 | AQ7: =AP7/AK16 -> 14.563088 | AR7: =AP7/AM17 -> 12.815107 | AT7: Shippine Line: | AU7: Save and Best Cargo Logistic Corp | AZ7: As per Local Cost | BA7: =BC35+BB21 -> 307159.74 | BB7: =BA7/AV16 -> 14.468193 | BC7: =BA7/AX17 -> 12.731603 | BE7: Shippine Line: | BF7: Save and Best Cargo Logistic Corp | BK7: As per Local Cost | BL7: =BN35+BM21 -> 309938.19 | BM7: =BL7/BG16 -> 14.41573 | BN7: =BL7/BI17 -> 12.685436 | BP7: Shippine Line: | BQ7: Save and Best Cargo Logistic Corp | BV7: As per Local Cost | BW7: =BY35+BX21 -> 316450.67 | BX7: =BW7/BR16 -> 14.718636 | BY7: =BW7/BT17 -> 12.951985 | CA7: Shippine Line: | CB7: Save and Best Cargo Logistic Corp | CG7: As per Local Cost | CH7: =CJ35+CI21 -> 320231.29 | CI7: =CH7/CC16 -> 14.846142 | CJ7: =CH7/CE17 -> 13.064187 | CL7: Shippine Line: | CM7: Save and Best Cargo Logistic Corp | CR7: As per Local Cost | CS7: =CU35+CT21 -> 316450.67 | CT7: =CS7/CN16 -> 14.718636 | CU7: =CS7/CP17 -> 12.951985 | CW7: Shippine Line: | CX7: Save and Best Cargo Logistic Corp | DC7: As per Local Cost | DD7: =DF35+DE21 -> 320231.29 | DE7: =DD7/CY16 -> 14.846142 | DF7: =DD7/DA17 -> 13.064187 | DI7: Shippine Line: | DJ7: Save and Best Cargo Logistic Corp | DO7: As per Local Cost | DP7: =DR35+DQ21 -> 320231.29 | DQ7: =DP7/DK16 -> 14.846142 | DR7: =DP7/DM17 -> 13.064187
B8: Date: | C8: 44788 | E8: Date Received: | F8: 44838 | H8: As per Gross of BOC | I8: =I6+I7 -> 2137511.1 | J8: =I8/D16 -> 103.31131 | K8: =I8/F17 -> 90.911046 | M8: Date: | N8: 45202 | P8: Date Received: | Q8: 45234 | S8: As per Gross of BOC | T8: =T6+T7 -> 1576558.1 | U8: =T8/O16 -> 73.808898 | V8: =T8/Q17 -> 64.949752 | X8: Date: | Y8: 45161 | AA8: Date Received: | AB8: 45244 | AD8: As per Gross of BOC | AE8: =AE6+AE7 -> 1746029 | AF8: =AE8/Z16 -> 82.515548 | AG8: =AE8/AB17 -> 72.611359 | AI8: Date: | AJ8: 45217 | AL8: Date Received: | AM8: 45244 | AO8: As per Gross of BOC | AP8: =AP6+AP7 -> 1722205.1 | AQ8: =AP8/AK16 -> 81.236088 | AR8: =AP8/AM17 -> 71.48547 | AT8: Date: | AU8: 45279 | AW8: Date Received: | AX8: 45314 | AZ8: As per Gross of BOC | BA8: =BA6+BA7 -> 1628090.3 | BB8: =BA8/AV16 -> 76.688193 | BC8: =BA8/AX17 -> 67.48345 | BE8: Date: | BF8: 45420 | BH8: Date Received: | BI8: 45494 | BK8: As per Gross of BOC | BL8: =BL6+BL7 -> 1647668.2 | BM8: =BL8/BG16 -> 76.63573 | BN8: =BL8/BI17 -> 67.437284 | BP8: Date: | BQ8: 45433 | BS8: Date Received: | BT8: 45517 | BV8: As per Gross of BOC | BW8: =BW6+BW7 -> 1667295.7 | BX8: =BW8/BR16 -> 77.548636 | BY8: =BW8/BT17 -> 68.240616 | CA8: Date: | CB8: 45515 | CD8: Date Received: | CE8: 45547 | CG8: As per Gross of BOC | CH8: =CH6+CH7 -> 1701789.8 | CI8: =CH8/CC16 -> 78.896142 | CJ8: =CH8/CE17 -> 69.426384 | CL8: Date: | CM8: 45433 | CO8: Date Received: | CP8: 45314 | CR8: As per Gross of BOC | CS8: =CS6+CS7 -> 1706640.7 | CT8: =CS8/CN16 -> 79.378636 | CU8: =CS8/CP17 -> 69.850964 | CW8: Date: | CX8: 45515 | CZ8: Date Received: | DA8: 45547 | DC8: As per Gross of BOC | DD8: =DD6+DD7 -> 1899155.3 | DE8: =DD8/CY16 -> 88.046142 | DF8: =DD8/DA17 -> 77.478126 | DI8: Date: | DJ8: 45515 | DL8: Date Received: | DM8: 45547 | DO8: As per Gross of BOC | DP8: =DP6+DP7 -> 2150231.3 | DQ8: =DP8/DK16 -> 99.686198 | DR8: =DP8/DM17 -> 87.721047
B9: Type of Oil: | C9: RBD PALM OLEIN | H9: As per Net of BOC | I9: =I8-J21 -> 1949168.1 | J9: =I9/D16 -> 94.208221 | K9: =I9/F17 -> 82.900582 | M9: Type of Oil: | N9: RBD PALM OLEIN | S9: As per Net of BOC | T9: =T8-U21 -> 1387954.8 | U9: =T9/O16 -> 64.979157 | V9: =T9/Q17 -> 57.179828 | X9: Type of Oil: | Y9: RBD PALM OLEIN | AD9: As per Net of BOC | AE9: =AE8-AF21 -> 1558761.5 | AF9: =AE9/Z16 -> 73.665477 | AG9: =AE9/AB17 -> 64.823545 | AI9: Type of Oil: | AJ9: RBD PALM OLEIN | AO9: As per Net of BOC | AP9: =AP8-AQ21 -> 1537491.8 | AQ9: =AP9/AK16 -> 72.523197 | AR9: =AP9/AM17 -> 63.818371 | AT9: Type of Oil: | AU9: RBD PALM OLEIN | AZ9: As per Net of BOC | BA9: =BA8-BB21 -> 1444938.5 | BB9: =BA9/AV16 -> 68.061165 | BC9: =BA9/AX17 -> 59.891909 | BE9: Type of Oil: | BF9: RBD PALM OLEIN | BK9: As per Net of BOC | BL9: =BL8-BM21 -> 1452477.4 | BM9: =BL9/BG16 -> 67.557091 | BN9: =BL9/BI17 -> 59.448337 | BP9: Type of Oil: | BQ9: RBD PALM OLEIN | BV9: As per Net of BOC | BW9: =BW8-BX21 -> 1473192.8 | BX9: =BW9/BR16 -> 68.520597 | BY9: =BW9/BT17 -> 60.296196 | CA9: Type of Oil: | CB9: RBD PALM OLEIN | CG9: As per Net of BOC | CH9: =CH8-CI21 -> 1512809.6 | CI9: =CH9/CC16 -> 70.13489 | CJ9: =CH9/CE17 -> 61.716728 | CL9: Type of Oil: | CM9: RBD PALM OLEIN | CR9: As per Net of BOC | CS9: =CS8-CT21 -> 1512537.8 | CT9: =CS9/CN16 -> 70.350597 | CU9: =CS9/CP17 -> 61.906545 | CW9: Type of Oil: | CX9: RBD PALM OLEIN | DC9: As per Net of BOC | DD9: =DD8-DE21 -> 1710175.1 | DE9: =DD9/CY16 -> 79.28489 | DF9: =DD9/DA17 -> 69.768471 | DI9: Type of Oil: | DJ9: RBD PALM OLEIN | DO9: As per Net of BOC | DP9: =DP8-DQ21 -> 1961251.1 | DQ9: =DP9/DK16 -> 90.924946 | DR9: =DP9/DM17 -> 80.011392
H10: For COGS | I10: =F22+J21+F38 -> 1990607.5 | J10: =I10/D16 -> 96.211092 | K10: =I10/F17 -> 84.663052 | S10: For COGS | T10: =Q22+U21+Q38 -> 1458989.3 | U10: =T10/O16 -> 68.304742 | V10: =T10/Q17 -> 60.106249 | AD10: For COGS | AE10: =AB22+AF21+AB38 -> 1621987.5 | AF10: =AE10/Z16 -> 76.653474 | AG10: =AE10/AB17 -> 67.452899 | AO10: For COGS | AP10: =AM22+AQ21+AM38 -> 1598180.9 | AQ10: =AP10/AK16 -> 75.385891 | AR10: =AP10/AM17 -> 66.337461 | AZ10: For COGS | BA10: =AX22+BB21+AX38 -> 1504082.4 | BB10: =BA10/AV16 -> 70.847028 | BC10: =BA10/AX17 -> 62.343389 | BF10: MSE240659 | BK10: For COGS | BL10: =BI22+BM21+BI38 -> 1532920.7 | BM10: =BL10/BG16 -> 71.298639 | BN10: =BL10/BI17 -> 62.740795 | BQ10: MSE240731 | BV10: For COGS | BW10: =BT22+BX21+BT38 -> 1544947.8 | BX10: =BW10/BR16 -> 71.858039 | BY10: =BW10/BT17 -> 63.233051 | CB10: MSE240978 | CG10: For COGS | CH10: =CE22+CI21+CE38 -> 1570538.7 | CI10: =CH10/CC16 -> 72.811252 | CJ10: =CH10/CE17 -> 64.071852 | CM10: MSE240731 | CR10: For COGS | CS10: =CP22+CT21+CP38 -> 1584292.8 | CT10: =CS10/CN16 -> 73.688039 | CU10: =CS10/CP17 -> 64.843399 | CX10: MSE240978 | DC10: For COGS | DD10: =DA22+DE21+DA38 -> 1767904.2 | DE10: =DD10/CY16 -> 81.961252 | DF10: =DD10/DA17 -> 72.123594 | DJ10: MSE240978 | DO10: For COGS | DP10: =DM22+DQ21+DM38 -> 2018980.2 | DQ10: =DP10/DK16 -> 93.601308 | DR10: =DP10/DM17 -> 82.366515
B12: DETAILS OF PAYMENT | M12: DETAILS OF PAYMENT | X12: DETAILS OF PAYMENT | AI12: DETAILS OF PAYMENT | AT12: DETAILS OF PAYMENT | BE12: DETAILS OF PAYMENT | BP12: DETAILS OF PAYMENT | CA12: DETAILS OF PAYMENT | CL12: DETAILS OF PAYMENT | CW12: DETAILS OF PAYMENT | DI12: DETAILS OF PAYMENT
B15: ORDER DETAILS (FOREIGN) | H15: COMPUTATION OF TAXES AND DUTIES | M15: ORDER DETAILS (FOREIGN) | S15: COMPUTATION OF TAXES AND DUTIES | X15: ORDER DETAILS (FOREIGN) | AD15: COMPUTATION OF TAXES AND DUTIES | AI15: ORDER DETAILS (FOREIGN) | AO15: COMPUTATION OF TAXES AND DUTIES | AT15: ORDER DETAILS (FOREIGN) | AZ15: COMPUTATION OF TAXES AND DUTIES | BE15: ORDER DETAILS (FOREIGN) | BK15: COMPUTATION OF TAXES AND DUTIES | BP15: ORDER DETAILS (FOREIGN) | BV15: COMPUTATION OF TAXES AND DUTIES | CA15: ORDER DETAILS (FOREIGN) | CG15: COMPUTATION OF TAXES AND DUTIES | CL15: ORDER DETAILS (FOREIGN) | CR15: COMPUTATION OF TAXES AND DUTIES | CW15: ORDER DETAILS (FOREIGN) | DC15: COMPUTATION OF TAXES AND DUTIES | DI15: ORDER DETAILS (FOREIGN) | DO15: COMPUTATION OF TAXES AND DUTIES
B16: ITEM NET WEIGHT (KG) | D16: 20690 | E16: PRICE PER KG | F16: 1.428 | H16: VAT PH (12%) | J16: Formulated | K16: =F35*0.12 -> 229176.49 | M16: ITEM NET WEIGHT (KG) | O16: 21360 | P16: PRICE PER KG | Q16: =20826/O16 -> 0.975 | S16: VAT PH (12%) | U16: Formulated | V16: =Q35*0.12 -> 163938.59 | X16: ITEM NET WEIGHT (KG) | Z16: 21160 | AA16: PRICE PER KG | AB16: 1.12 | AD16: VAT PH (12%) | AF16: Formulated | AG16: =AB35*0.12 -> 185728.58 | AI16: ITEM NET WEIGHT (KG) | AK16: 21200 | AL16: PRICE PER KG | AM16: 1.093 | AO16: VAT PH (12%) | AQ16: Formulated | AR16: =AM35*0.12 -> 181624.65 | AT16: ITEM NET WEIGHT (KG) | AV16: 21230 | AW16: PRICE PER KG | AX16: 1.02 | AZ16: VAT PH (12%) | BB16: Formulated | BC16: =AX35*0.12 -> 169057.27 | BE16: ITEM NET WEIGHT (KG) | BG16: =21930/1.02 -> 21500 | BH16: PRICE PER KG | BI16: 1.02 | BK16: VAT PH (12%) | BM16: Formulated | BN16: =BI35*0.12 -> 171477.16 | BP16: ITEM NET WEIGHT (KG) | BR16: 21500 | BS16: PRICE PER KG | BT16: 1.03 | BV16: VAT PH (12%) | BX16: Formulated | BY16: =BT35*0.12 -> 172653.36 | CA16: ITEM NET WEIGHT (KG) | CC16: 21570 | CD16: PRICE PER KG | CE16: 1.05 | CG16: VAT PH (12%) | CI16: Formulated | CJ16: =CE35*0.12 -> 176332.6 | CL16: ITEM NET WEIGHT (KG) | CN16: 21500 | CO16: PRICE PER KG | CP16: 1.06 | CR16: VAT PH (12%) | CT16: Formulated | CU16: =CP35*0.12 -> 177374.76 | CW16: ITEM NET WEIGHT (KG) | CY16: 21570 | CZ16: PRICE PER KG | DA16: 1.2 | DC16: VAT PH (12%) | DE16: Formulated | DF16: =DA35*0.12 -> 200016.46 | DI16: ITEM NET WEIGHT (KG) | DK16: 21570 | DL16: PRICE PER KG | DM16: 1.2 | DO16: VAT PH (12%) | DQ16: Formulated | DR16: =DM35*0.12 -> 230145.58
B17: DOLLAR PAYMENT | D17: =D16*F16 -> 29545.32 | E17: NET WEIGHT (LTR) | F17: =D16*1.1364 -> 23512.116 | H17: Minimum VAT | J17: 186770.97 | K17: =J17-K16 -> -42405.521 | M17: DOLLAR PAYMENT | O17: =O16*Q16 -> 20826 | P17: NET WEIGHT (LTR) | Q17: =O16*1.1364 -> 24273.504 | S17: Minimum VAT | U17: 187039.28 | V17: =U17-V16 -> 23100.688 | X17: DOLLAR PAYMENT | Z17: =Z16*AB16 -> 23699.2 | AA17: NET WEIGHT (LTR) | AB17: =Z16*1.1364 -> 24046.224 | AD17: Minimum VAT | AF17: 185703.51 | AG17: =AF17-AG16 -> -25.0656 | AI17: DOLLAR PAYMENT | AK17: =AK16*AM16 -> 23171.6 | AL17: NET WEIGHT (LTR) | AM17: =AK16*1.1364 -> 24091.68 | AO17: Minimum VAT | AQ17: 183154.29 | AR17: =AQ17-AR16 -> 1529.6352 | AT17: DOLLAR PAYMENT | AV17: =AV16*AX16 -> 21654.6 | AW17: NET WEIGHT (LTR) | AX17: =AV16*1.1364 -> 24125.772 | AZ17: Minimum VAT | BB17: 181593.8 | BC17: =BB17-BC16 -> 12536.533 | BE17: DOLLAR PAYMENT | BG17: =BG16*BI16 -> 21930 | BH17: NET WEIGHT (LTR) | BI17: =BG16*1.1364 -> 24432.6 | BK17: Minimum VAT | BM17: 192769.74 | BN17: =BM17-BN16 -> 21292.584 | BP17: DOLLAR PAYMENT | BR17: =BR16*BT16 -> 22145 | BS17: NET WEIGHT (LTR) | BT17: =BR16*1.1364 -> 24432.6 | BV17: Minimum VAT | BX17: 191681.83 | BY17: =BX17-BY16 -> 19028.465 | CA17: DOLLAR PAYMENT | CC17: =CC16*CE16 -> 22648.5 | CD17: NET WEIGHT (LTR) | CE17: =CC16*1.1364 -> 24512.148 | CG17: Minimum VAT | CI17: 186569.21 | CJ17: =CI17-CJ16 -> 10236.608 | CL17: DOLLAR PAYMENT | CN17: =CN16*CP16 -> 22790 | CO17: NET WEIGHT (LTR) | CP17: =CN16*1.1364 -> 24432.6 | CR17: Minimum VAT | CT17: 191681.83 | CU17: =CT17-CU16 -> 14307.065 | CW17: DOLLAR PAYMENT | CY17: =CY16*DA16 -> 25884 | CZ17: NET WEIGHT (LTR) | DA17: =CY16*1.1364 -> 24512.148 | DC17: Minimum VAT | DE17: 186569.21 | DF17: =DE17-DF16 -> -13447.252 | DI17: DOLLAR PAYMENT | DK17: 30000 | DL17: NET WEIGHT (LTR) | DM17: =DK16*1.1364 -> 24512.148 | DO17: Minimum VAT | DQ17: 186569.21 | DR17: =DQ17-DR16 -> -43576.372
B18: FOREIGN EXCHANGE RATE | F18: 61 | H18: Import Processing Fee (IPF) | J18: Formulated | K18: =IF(E24+F22+E25>750000,1000,IF(E24+F22+E25>750000,750,IF(E24+F22+E25>P31500000,750,IF(E24+F22+E25>500000,750,IF(E24+F22+E25>250000,500,IF(E24+F22+E25>250000,500,250)))))) -> 1000 | M18: FOREIGN EXCHANGE RATE | Q18: 61 | S18: Import Processing Fee (IPF) | U18: Formulated | V18: =IF(P24+Q22+P25>750000,1000,IF(P24+Q22+P25>750000,750,IF(P24+Q22+P25>P31500000,750,IF(P24+Q22+P25>500000,750,IF(P24+Q22+P25>250000,500,IF(P24+Q22+P25>250000,500,250)))))) -> 1000 | X18: FOREIGN EXCHANGE RATE | AB18: 61 | AD18: Import Processing Fee (IPF) | AF18: Formulated | AG18: =IF(AA24+AB22+AA25>750000,1000,IF(AA24+AB22+AA25>750000,750,IF(AA24+AB22+AA25>P31500000,750,IF(AA24+AB22+AA25>500000,750,IF(AA24+AB22+AA25>250000,500,IF(AA24+AB22+AA25>250000,500,250)))))) -> 1000 | AI18: FOREIGN EXCHANGE RATE | AM18: 61 | AO18: Import Processing Fee (IPF) | AQ18: Formulated | AR18: =IF(AL24+AM22+AL25>750000,1000,IF(AL24+AM22+AL25>750000,750,IF(AL24+AM22+AL25>P31500000,750,IF(AL24+AM22+AL25>500000,750,IF(AL24+AM22+AL25>250000,500,IF(AL24+AM22+AL25>250000,500,250)))))) -> 1000 | AT18: FOREIGN EXCHANGE RATE | AX18: 61 | AZ18: Import Processing Fee (IPF) | BB18: Formulated | BC18: =IF(AW24+AX22+AW25>750000,1000,IF(AW24+AX22+AW25>750000,750,IF(AW24+AX22+AW25>P31500000,750,IF(AW24+AX22+AW25>500000,750,IF(AW24+AX22+AW25>250000,500,IF(AW24+AX22+AW25>250000,500,250)))))) -> 1000 | BE18: FOREIGN EXCHANGE RATE | BI18: 61 | BK18: Import Processing Fee (IPF) | BM18: Formulated | BN18: 2000 | BP18: FOREIGN EXCHANGE RATE | BT18: 61 | BV18: Import Processing Fee (IPF) | BX18: Formulated | BY18: 2000 | CA18: FOREIGN EXCHANGE RATE | CE18: 61 | CG18: Import Processing Fee (IPF) | CI18: Formulated | CJ18: 2000 | CL18: FOREIGN EXCHANGE RATE | CP18: 61 | CR18: Import Processing Fee (IPF) | CT18: Formulated | CU18: 2000 | CW18: FOREIGN EXCHANGE RATE | DA18: 61 | DC18: Import Processing Fee (IPF) | DE18: Formulated | DF18: 2000 | DI18: FOREIGN EXCHANGE RATE | DM18: 61 | DO18: Import Processing Fee (IPF) | DQ18: Formulated | DR18: 2000
H19: Customs Documentary Stamp (CDS) | J19: Fixed | K19: 280 | S19: Customs Documentary Stamp (CDS) | U19: Fixed | V19: 280 | AD19: Customs Documentary Stamp (CDS) | AF19: Fixed | AG19: 280 | AO19: Customs Documentary Stamp (CDS) | AQ19: Fixed | AR19: 280 | AZ19: Customs Documentary Stamp (CDS) | BB19: Fixed | BC19: 280 | BK19: Customs Documentary Stamp (CDS) | BM19: Fixed | BN19: 130 | BV19: Customs Documentary Stamp (CDS) | BX19: Fixed | BY19: 130 | CG19: Customs Documentary Stamp (CDS) | CI19: Fixed | CJ19: 130 | CR19: Customs Documentary Stamp (CDS) | CT19: Fixed | CU19: 130 | DC19: Customs Documentary Stamp (CDS) | DE19: Fixed | DF19: 130 | DO19: Customs Documentary Stamp (CDS) | DQ19: Fixed | DR19: 130
B20: BOC COMPUTATION | H20: Container Security Fees (CSF) | J20: Fixed | K20: 292 | M20: BOC COMPUTATION | S20: Container Security Fees (CSF) | U20: Fixed | V20: 284 | X20: BOC COMPUTATION | AD20: Container Security Fees (CSF) | AF20: Fixed | AG20: 284 | AI20: BOC COMPUTATION | AO20: Container Security Fees (CSF) | AQ20: Fixed | AR20: 279 | AT20: BOC COMPUTATION | AZ20: Container Security Fees (CSF) | BB20: Fixed | BC20: 278 | BE20: BOC COMPUTATION | BK20: Container Security Fees (CSF) | BM20: Fixed | BN20: 291 | BP20: BOC COMPUTATION | BV20: Container Security Fees (CSF) | BX20: Fixed | BY20: 291 | CA20: BOC COMPUTATION | CG20: Container Security Fees (CSF) | CI20: Fixed | CJ20: 281 | CL20: BOC COMPUTATION | CR20: Container Security Fees (CSF) | CT20: Fixed | CU20: 291 | CW20: BOC COMPUTATION | DC20: Container Security Fees (CSF) | DE20: Fixed | DF20: 281 | DI20: BOC COMPUTATION | DO20: Container Security Fees (CSF) | DQ20: Fixed | DR20: 281
B21: MEN2 PAYMENT IN PESO VALUE | H21: TOTAL DUTIES AND TAXES | J21: =SUM(K16:K20) -> 188342.97 | M21: MEN2 PAYMENT IN PESO VALUE | S21: TOTAL DUTIES AND TAXES | U21: =SUM(V16:V20) -> 188603.28 | X21: MEN2 PAYMENT IN PESO VALUE | AD21: TOTAL DUTIES AND TAXES | AF21: =SUM(AG16:AG20) -> 187267.51 | AI21: MEN2 PAYMENT IN PESO VALUE | AO21: TOTAL DUTIES AND TAXES | AQ21: =SUM(AR16:AR20) -> 184713.29 | AT21: MEN2 PAYMENT IN PESO VALUE | AZ21: TOTAL DUTIES AND TAXES | BB21: =SUM(BC16:BC20) -> 183151.8 | BE21: MEN2 PAYMENT IN PESO VALUE | BK21: TOTAL DUTIES AND TAXES | BM21: =SUM(BN16:BN20) -> 195190.74 | BP21: MEN2 PAYMENT IN PESO VALUE | BV21: TOTAL DUTIES AND TAXES | BX21: =SUM(BY16:BY20) -> 194102.83 | CA21: MEN2 PAYMENT IN PESO VALUE | CG21: TOTAL DUTIES AND TAXES | CI21: =SUM(CJ16:CJ20) -> 188980.21 | CL21: MEN2 PAYMENT IN PESO VALUE | CR21: TOTAL DUTIES AND TAXES | CT21: =SUM(CU16:CU20) -> 194102.83 | CW21: MEN2 PAYMENT IN PESO VALUE | DC21: TOTAL DUTIES AND TAXES | DE21: =SUM(DF16:DF20) -> 188980.21 | DI21: MEN2 PAYMENT IN PESO VALUE | DO21: TOTAL DUTIES AND TAXES | DQ21: =SUM(DR16:DR20) -> 188980.21
B22: Item Custom Value (Oil) | E22: Formulated | F22: =D17*F18 -> 1802264.5 | M22: Item Custom Value (Oil) | P22: Formulated | Q22: =O17*Q18 -> 1270386 | X22: Item Custom Value (Oil) | AA22: Formulated | AB22: =Z17*AB18 -> 1445651.2 | AI22: Item Custom Value (Oil) | AL22: Formulated | AM22: =AK17*AM18 -> 1413467.6 | AT22: Item Custom Value (Oil) | AW22: Formulated | AX22: =AV17*AX18 -> 1320930.6 | BE22: Item Custom Value (Oil) | BH22: Formulated | BI22: =BG17*BI18 -> 1337730 | BP22: Item Custom Value (Oil) | BS22: Formulated | BT22: =BR17*BT18 -> 1350845 | CA22: Item Custom Value (Oil) | CD22: Formulated | CE22: =CC17*CE18 -> 1381558.5 | CL22: Item Custom Value (Oil) | CO22: Formulated | CP22: =CN17*CP18 -> 1390190 | CW22: Item Custom Value (Oil) | CZ22: Formulated | DA22: =CY17*DA18 -> 1578924 | DI22: Item Custom Value (Oil) | DL22: Formulated | DM22: =DK17*DM18 -> 1830000
B23: SUPPLIER DUTIES | H23: COMPUTATION OF SHIPPING FEE | M23: SUPPLIER DUTIES | S23: COMPUTATION OF SHIPPING FEE | X23: SUPPLIER DUTIES | AD23: COMPUTATION OF SHIPPING FEE | AI23: SUPPLIER DUTIES | AO23: COMPUTATION OF SHIPPING FEE | AT23: SUPPLIER DUTIES | AZ23: COMPUTATION OF SHIPPING FEE | BE23: SUPPLIER DUTIES | BK23: COMPUTATION OF SHIPPING FEE | BP23: SUPPLIER DUTIES | BV23: COMPUTATION OF SHIPPING FEE | CA23: SUPPLIER DUTIES | CG23: COMPUTATION OF SHIPPING FEE | CL23: SUPPLIER DUTIES | CR23: COMPUTATION OF SHIPPING FEE | CW23: SUPPLIER DUTIES | DC23: COMPUTATION OF SHIPPING FEE | DI23: SUPPLIER DUTIES | DO23: COMPUTATION OF SHIPPING FEE
A24: =F24/F22 -> 0.051628381 | B24: InsuranceInFreight | D24: Formulated | E24: 35044 | F24: =SUM(E24:E25) -> 93048 | H24: Shippine Lines THC Fee | J24: Variable | K24: 52192 | L24: =Q24/Q22 -> 0.064247402 | M24: InsuranceInFreight | O24: Formulated | P24: 34173 | Q24: =SUM(P24:P25) -> 81619 | S24: Shippine Lines THC Fee | U24: Variable | V24: 26659.8 | W24: =AB24/AB22 -> 0.060828642 | X24: InsuranceInFreight | Z24: Formulated | AA24: 34085 | AB24: =SUM(AA24:AA25) -> 87937 | AD24: Shippine Lines THC Fee | AF24: Variable | AG24: 38671.56 | AH24: =AM24/AM22 -> 0.060404639 | AI24: InsuranceInFreight | AK24: Formulated | AL24: 33551 | AM24: =SUM(AL24:AL25) -> 85380 | AO24: Shippine Lines THC Fee | AQ24: Variable | AR24: 38112.98 | AS24: =AX24/AX22 -> 0.055419263 | AT24: InsuranceInFreight | AV24: Formulated | AW24: 25029 | AX24: =SUM(AW24:AW25) -> 73205 | AZ24: Shippine Lines THC Fee | BB24: Variable | BC24: 38112.98 | BD24: =BI24/BI22 -> 0.05760729 | BE24: InsuranceInFreight | BG24: Formulated | BH24: 26234 | BI24: =SUM(BH24:BH25) -> 77063 | BK24: Shippine Lines THC Fee | BM24: Variable | BN24: 29344.15 | BO24: =#REF!/#REF! -> #REF! | BP24: InsuranceInFreight | BR24: Formulated | BS24: 25029 | BT24: =SUM(BS24:BS25) -> 73205 | BV24: Shippine Lines THC Fee | BX24: Variable | BY24: 36399.8 | CA24: InsuranceInFreight | CC24: Formulated | CD24: 25029 | CE24: =SUM(CD24:CD25) -> 73205 | CG24: Shippine Lines THC Fee | CI24: Variable | CJ24: 42510 | CL24: InsuranceInFreight | CN24: Formulated | CO24: 25029 | CP24: =SUM(CO24:CO25) -> 73205 | CR24: Shippine Lines THC Fee | CT24: Variable | CU24: 36399.8 | CW24: InsuranceInFreight | CY24: Formulated | CZ24: 25029 | DA24: =SUM(CZ24:CZ25) -> 73205 | DC24: Shippine Lines THC Fee | DE24: Variable | DF24: 42510 | DI24: InsuranceInFreight | DK24: Formulated | DL24: 25029 | DM24: =SUM(DL24:DL25) -> 73205 | DO24: Shippine Lines THC Fee | DQ24: Variable | DR24: 42510
B25: OTHinEV | D25: Formulated | E25: 58004 | H25: Storage Fee | J25: Variable | M25: OTHinEV | O25: Formulated | P25: 47446 | S25: Storage Fee | U25: Variable | V25: 539.06 | X25: OTHinEV | Z25: Formulated | AA25: 53852 | AD25: Storage Fee | AF25: Variable | AG25: 0 | AI25: OTHinEV | AK25: Formulated | AL25: 51829 | AO25: Storage Fee | AQ25: Variable | AR25: 0 | AT25: OTHinEV | AV25: Formulated | AW25: 48176 | AZ25: Storage Fee | BB25: Variable | BC25: 0 | BE25: OTHinEV | BG25: Formulated | BH25: 50829 | BK25: Storage Fee | BM25: Variable | BN25: 0 | BP25: OTHinEV | BR25: Formulated | BS25: 48176 | BV25: Storage Fee | BX25: Variable | BY25: 0 | CA25: OTHinEV | CC25: Formulated | CD25: 48176 | CG25: Storage Fee | CI25: Variable | CJ25: 2846.23 | CL25: OTHinEV | CN25: Formulated | CO25: 48176 | CR25: Storage Fee | CT25: Variable | CU25: 0 | CW25: OTHinEV | CY25: Formulated | CZ25: 48176 | DC25: Storage Fee | DE25: Variable | DF25: 2846.23 | DI25: OTHinEV | DK25: Formulated | DL25: 48176 | DO25: Storage Fee | DQ25: Variable | DR25: 2846.23
B26: CUSTOMS DUTIABLE VALUE (CUD) | F26: =SUM(F22:F24) -> 1895312.5 | H26: Custom SOP | J26: Variable | K26: 30000 | M26: CUSTOMS DUTIABLE VALUE (CUD) | Q26: =SUM(Q22:Q24) -> 1352005 | S26: Custom SOP | U26: Variable | V26: 23000 | X26: CUSTOMS DUTIABLE VALUE (CUD) | AB26: =SUM(AB22:AB24) -> 1533588.2 | AD26: Custom SOP | AF26: Variable | AG26: 18000 | AI26: CUSTOMS DUTIABLE VALUE (CUD) | AM26: =SUM(AM22:AM24) -> 1498847.6 | AO26: Custom SOP | AQ26: Variable | AR26: 18000 | AT26: CUSTOMS DUTIABLE VALUE (CUD) | AX26: =SUM(AX22:AX24) -> 1394135.6 | AZ26: Custom SOP | BB26: Variable | BC26: 18000 | BE26: CUSTOMS DUTIABLE VALUE (CUD) | BI26: =SUM(BI22:BI24) -> 1414793 | BK26: Custom SOP | BM26: Variable | BN26: 18000 | BP26: CUSTOMS DUTIABLE VALUE (CUD) | BT26: =SUM(BT22:BT24) -> 1424050 | BV26: Custom SOP | BX26: Variable | BY26: 18000 | CA26: CUSTOMS DUTIABLE VALUE (CUD) | CE26: =SUM(CE22:CE24) -> 1454763.5 | CG26: Custom SOP | CI26: Variable | CJ26: 18000 | CL26: CUSTOMS DUTIABLE VALUE (CUD) | CP26: =SUM(CP22:CP24) -> 1463395 | CR26: Custom SOP | CT26: Variable | CU26: 18000 | CW26: CUSTOMS DUTIABLE VALUE (CUD) | DA26: =SUM(DA22:DA24) -> 1652129 | DC26: Custom SOP | DE26: Variable | DF26: 18000 | DI26: CUSTOMS DUTIABLE VALUE (CUD) | DM26: =SUM(DM22:DM24) -> 1903205 | DO26: Custom SOP | DQ26: Variable | DR26: 18000
B27: CUSTOM DUTIES | H27: Processing Fee | J27: Fixed | K27: 6000 | M27: CUSTOM DUTIES | S27: Processing Fee | U27: Fixed | V27: 6000 | X27: CUSTOM DUTIES | AD27: Processing Fee | AF27: Fixed | AG27: 6000 | AI27: CUSTOM DUTIES | AO27: Processing Fee | AQ27: Fixed | AR27: 6000 | AT27: CUSTOM DUTIES | AZ27: Processing Fee | BB27: Fixed | BC27: 6000 | BE27: CUSTOM DUTIES | BK27: Processing Fee | BM27: Fixed | BN27: 6000 | BP27: CUSTOM DUTIES | BV27: Processing Fee | BX27: Fixed | BY27: 6000 | CA27: CUSTOM DUTIES | CG27: Processing Fee | CI27: Fixed | CJ27: 6000 | CL27: CUSTOM DUTIES | CR27: Processing Fee | CT27: Fixed | CU27: 6000 | CW27: CUSTOM DUTIES | DC27: Processing Fee | DE27: Fixed | DF27: 6000 | DI27: CUSTOM DUTIES | DO27: Processing Fee | DQ27: Fixed | DR27: 6000
B28: Bank Charges | D28: Variable | E28: 0 | F28: =SUM(E28:E34) -> 14491.57 | H28: Documentation | J28: Fixed | K28: 2000 | M28: Bank Charges | O28: Variable | P28: 0 | Q28: =SUM(P28:P34) -> 14149.93 | S28: Documentation | U28: Fixed | V28: 2000 | X28: Bank Charges | Z28: Variable | AA28: 0 | AB28: =SUM(AA28:AA34) -> 14149.93 | AD28: Documentation | AF28: Fixed | AG28: 2000 | AI28: Bank Charges | AK28: Variable | AL28: 0 | AM28: =SUM(AL28:AL34) -> 14691.19 | AO28: Documentation | AQ28: Fixed | AR28: 2000 | AT28: Bank Charges | AV28: Variable | AW28: 0 | AX28: =SUM(AW28:AW34) -> 14674.96 | AZ28: Documentation | BB28: Fixed | BC28: 2000 | BE28: Bank Charges | BG28: Variable | BH28: 0 | BI28: =SUM(BH28:BH34) -> 14183.3 | BK28: Documentation | BM28: Fixed | BN28: 2000 | BP28: Bank Charges | BR28: Variable | BS28: 0 | BT28: =SUM(BS28:BS34) -> 14728.04 | BV28: Documentation | BX28: Fixed | BY28: 2000 | CA28: Bank Charges | CC28: Variable | CD28: 0 | CE28: =SUM(CD28:CD34) -> 14674.85 | CG28: Documentation | CI28: Fixed | CJ28: 2000 | CL28: Bank Charges | CN28: Variable | CO28: 0 | CP28: =SUM(CO28:CO34) -> 14728.04 | CR28: Documentation | CT28: Fixed | CU28: 2000 | CW28: Bank Charges | CY28: Variable | CZ28: 0 | DA28: =SUM(CZ28:CZ34) -> 14674.85 | DC28: Documentation | DE28: Fixed | DF28: 2000 | DI28: Bank Charges | DK28: Variable | DL28: 0 | DM28: =SUM(DL28:DL34) -> 14674.85 | DO28: Documentation | DQ28: Fixed | DR28: 2000
B29: Customs Duty | D29: Variable | E29: 0 | H29: Local Trucking | J29: Fixed | K29: 40000 | M29: Customs Duty | O29: Variable | P29: 0 | S29: Local Trucking | U29: Fixed | V29: 42000 | X29: Customs Duty | Z29: Variable | AA29: 0 | AD29: Local Trucking | AF29: Fixed | AG29: 42000 | AI29: Customs Duty | AK29: Variable | AL29: 0 | AO29: Local Trucking | AQ29: Fixed | AR29: 42000 | AT29: Customs Duty | AV29: Variable | AW29: 0 | AZ29: Local Trucking | BB29: Fixed | BC29: 42000 | BE29: Customs Duty | BG29: Variable | BH29: 0 | BK29: Local Trucking | BM29: Fixed | BN29: 42000 | BP29: Customs Duty | BR29: Variable | BS29: 0 | BV29: Local Trucking | BX29: Fixed | BY29: 42000 | CA29: Customs Duty | CC29: Variable | CD29: 0 | CG29: Local Trucking | CI29: Fixed | CJ29: 42000 | CL29: Customs Duty | CN29: Variable | CO29: 0 | CR29: Local Trucking | CT29: Fixed | CU29: 42000 | CW29: Customs Duty | CY29: Variable | CZ29: 0 | DC29: Local Trucking | DE29: Fixed | DF29: 42000 | DI29: Customs Duty | DK29: Variable | DL29: 0 | DO29: Local Trucking | DQ29: Fixed | DR29: 42000
B30: Brokerage Fee | D30: Formulated | E30: 7323.34 | H30: Customs Handling Charges | J30: Fixed | K30: 1500 | M30: Brokerage Fee | O30: Formulated | P30: 6981.7 | S30: Customs Handling Charges | U30: Fixed | V30: 1500 | X30: Brokerage Fee | Z30: Formulated | AA30: 6981.7 | AD30: Customs Handling Charges | AF30: Fixed | AG30: 1500 | AI30: Brokerage Fee | AK30: Formulated | AL30: 6941.29 | AO30: Customs Handling Charges | AQ30: Fixed | AR30: 1500 | AT30: Brokerage Fee | AV30: Formulated | AW30: 6925.06 | AZ30: Customs Handling Charges | BB30: Fixed | BC30: 1500 | BE30: Brokerage Fee | BG30: Formulated | BH30: 7015.07 | BK30: Customs Handling Charges | BM30: Fixed | BN30: 1500 | BP30: Brokerage Fee | BR30: Formulated | BS30: 7028.93 | BV30: Customs Handling Charges | BX30: Fixed | BY30: 1500 | CA30: Brokerage Fee | CC30: Formulated | CD30: 6975.74 | CG30: Customs Handling Charges | CI30: Fixed | CJ30: 1500 | CL30: Brokerage Fee | CN30: Formulated | CO30: 7028.93 | CR30: Customs Handling Charges | CT30: Fixed | CU30: 1500 | CW30: Brokerage Fee | CY30: Formulated | CZ30: 6975.74 | DC30: Customs Handling Charges | DE30: Fixed | DF30: 1500 | DI30: Brokerage Fee | DK30: Formulated | DL30: 6975.74 | DO30: Customs Handling Charges | DQ30: Fixed | DR30: 1500
B31: Wharfage Due | D31: Variable | E31: 581.67 | H31: Customs OT | J31: Fixed | K31: 1000 | M31: Wharfage Due | O31: Variable | P31: 581.67 | S31: Customs OT | U31: Fixed | V31: 2000 | X31: Wharfage Due | Z31: Variable | AA31: 581.67 | AD31: Customs OT | AF31: Fixed | AG31: 2000 | AI31: Wharfage Due | AK31: Variable | AL31: 581.67 | AO31: Customs OT | AQ31: Fixed | AR31: 2000 | AT31: Wharfage Due | AV31: Variable | AW31: 581.67 | AZ31: Customs OT | BB31: Fixed | BC31: 2000 | BE31: Wharfage Due | BG31: Variable | BH31: 581.67 | BK31: Customs OT | BM31: Fixed | BN31: 2000 | BP31: Wharfage Due | BR31: Variable | BS31: 581.67 | BV31: Customs OT | BX31: Fixed | BY31: 2000 | CA31: Wharfage Due | CC31: Variable | CD31: 581.67 | CG31: Customs OT | CI31: Fixed | CJ31: 2000 | CL31: Wharfage Due | CN31: Variable | CO31: 581.67 | CR31: Customs OT | CT31: Fixed | CU31: 2000 | CW31: Wharfage Due | CY31: Variable | CZ31: 581.67 | DC31: Customs OT | DE31: Fixed | DF31: 2000 | DI31: Wharfage Due | DK31: Variable | DL31: 581.67 | DO31: Customs OT | DQ31: Fixed | DR31: 2000
B32: Arrastre Charge | D32: Variable | E32: 5306.56 | H32: Xray Charges | J32: Fixed | K32: 1000 | M32: Arrastre Charge | O32: Variable | P32: 5306.56 | S32: Xray Charges | U32: Fixed | V32: 1000 | X32: Arrastre Charge | Z32: Variable | AA32: 5306.56 | AD32: Xray Charges | AF32: Fixed | AG32: 1000 | AI32: Arrastre Charge | AK32: Variable | AL32: 5888.23 | AO32: Xray Charges | AQ32: Fixed | AR32: 1000 | AT32: Arrastre Charge | AV32: Variable | AW32: 5888.23 | AZ32: Xray Charges | BB32: Fixed | BC32: 1000 | BE32: Arrastre Charge | BG32: Variable | BH32: 5306.56 | BK32: Xray Charges | BM32: Fixed | BN32: 1000 | BP32: Arrastre Charge | BR32: Variable | BS32: 5837.44 | BV32: Xray Charges | BX32: Fixed | BY32: 1000 | CA32: Arrastre Charge | CC32: Variable | CD32: 5837.44 | CG32: Xray Charges | CI32: Fixed | CJ32: 1000 | CL32: Arrastre Charge | CN32: Variable | CO32: 5837.44 | CR32: Xray Charges | CT32: Fixed | CU32: 1000 | CW32: Arrastre Charge | CY32: Variable | CZ32: 5837.44 | DC32: Xray Charges | DE32: Fixed | DF32: 1000 | DI32: Arrastre Charge | DK32: Variable | DL32: 5837.44 | DO32: Xray Charges | DQ32: Fixed | DR32: 1000
B33: Documentary Stamp | D33: Fixed | E33: 280 | H33: Custom Duties | J33: Formulated | K33: =SUM(E30:E32) -> 13211.57 | M33: Documentary Stamp | O33: Fixed | P33: 280 | S33: Custom Duties | U33: Formulated | V33: =SUM(P30:P32) -> 12869.93 | X33: Documentary Stamp | Z33: Fixed | AA33: 280 | AD33: Custom Duties | AF33: Formulated | AG33: =SUM(AA30:AA32) -> 12869.93 | AI33: Documentary Stamp | AK33: Fixed | AL33: 280 | AO33: Custom Duties | AQ33: Formulated | AR33: =SUM(AL30:AL32) -> 13411.19 | AT33: Documentary Stamp | AV33: Fixed | AW33: 280 | AZ33: Custom Duties | BB33: Formulated | BC33: =SUM(AW30:AW32) -> 13394.96 | BE33: Documentary Stamp | BG33: Fixed | BH33: 280 | BK33: Custom Duties | BM33: Formulated | BN33: =SUM(BH30:BH32) -> 12903.3 | BP33: Documentary Stamp | BR33: Fixed | BS33: 280 | BV33: Custom Duties | BX33: Formulated | BY33: =SUM(BS30:BS32) -> 13448.04 | CA33: Documentary Stamp | CC33: Fixed | CD33: 280 | CG33: Custom Duties | CI33: Formulated | CJ33: =SUM(CD30:CD32) -> 13394.85 | CL33: Documentary Stamp | CN33: Fixed | CO33: 280 | CR33: Custom Duties | CT33: Formulated | CU33: =SUM(CO30:CO32) -> 13448.04 | CW33: Documentary Stamp | CY33: Fixed | CZ33: 280 | DC33: Custom Duties | DE33: Formulated | DF33: =SUM(CZ30:CZ32) -> 13394.85 | DI33: Documentary Stamp | DK33: Fixed | DL33: 280 | DO33: Custom Duties | DQ33: Formulated | DR33: =SUM(DL30:DL32) -> 13394.85
B34: Others | D34: Fixed | E34: 1000 | H34: Miscellaneous | J34: Variable | K34: 0 | M34: Others | O34: Fixed | P34: 1000 | S34: Miscellaneous | U34: Variable | V34: 0 | X34: Others | Z34: Fixed | AA34: 1000 | AD34: Miscellaneous | AF34: Variable | AG34: 0 | AI34: Others | AK34: Fixed | AL34: 1000 | AO34: Miscellaneous | AQ34: Variable | AR34: 0 | AT34: Others | AV34: Fixed | AW34: 1000 | AZ34: Miscellaneous | BB34: Variable | BC34: 0 | BE34: Others | BG34: Fixed | BH34: 1000 | BK34: Miscellaneous | BM34: Variable | BN34: 0 | BP34: Others | BR34: Fixed | BS34: 1000 | BV34: Miscellaneous | BX34: Variable | BY34: 0 | CA34: Others | CC34: Fixed | CD34: 1000 | CG34: Miscellaneous | CI34: Variable | CJ34: 0 | CL34: Others | CN34: Fixed | CO34: 1000 | CR34: Miscellaneous | CT34: Variable | CU34: 0 | CW34: Others | CY34: Fixed | CZ34: 1000 | DC34: Miscellaneous | DE34: Variable | DF34: 0 | DI34: Others | DK34: Fixed | DL34: 1000 | DO34: Miscellaneous | DQ34: Variable | DR34: 0
B35: TOTAL LANDED COST (TLC) | E35: =SUM(E26:E34) -> 14491.57 | F35: =SUM(F26:F33) -> 1909804.1 | H35: TOTAL SHIPPING FEES | J35: =K35/F17 -> 6.2479944 | K35: =SUM(K24:K34) -> 146903.57 | M35: TOTAL LANDED COST (TLC) | P35: =SUM(P26:P34) -> 14149.93 | Q35: =SUM(Q26:Q33) -> 1366154.9 | S35: TOTAL SHIPPING FEES | U35: =V35/Q17 -> 4.843503 | V35: =SUM(V24:V34) -> 117568.79 | X35: TOTAL LANDED COST (TLC) | AA35: =SUM(AA26:AA34) -> 14149.93 | AB35: =SUM(AB26:AB33) -> 1547738.1 | AD35: TOTAL SHIPPING FEES | AF35: =AG35/AB17 -> 5.1584602 | AG35: =SUM(AG24:AG34) -> 124041.49 | AI35: TOTAL LANDED COST (TLC) | AL35: =SUM(AL26:AL34) -> 14691.19 | AM35: =SUM(AM26:AM33) -> 1513538.8 | AO35: TOTAL SHIPPING FEES | AQ35: =AR35/AM17 -> 5.1480084 | AR35: =SUM(AR24:AR34) -> 124024.17 | AT35: TOTAL LANDED COST (TLC) | AW35: =SUM(AW26:AW34) -> 14674.96 | AX35: =SUM(AX26:AX33) -> 1408810.6 | AZ35: TOTAL SHIPPING FEES | BB35: =BC35/AX17 -> 5.140061 | BC35: =SUM(BC24:BC34) -> 124007.94 | BE35: TOTAL LANDED COST (TLC) | BH35: =SUM(BH26:BH34) -> 14183.3 | BI35: =SUM(BI26:BI33) -> 1428976.3 | BK35: TOTAL SHIPPING FEES | BM35: =BN35/BI17 -> 4.6964895 | BN35: =SUM(BN24:BN34) -> 114747.45 | BP35: TOTAL LANDED COST (TLC) | BS35: =SUM(BS26:BS34) -> 14728.04 | BT35: =SUM(BT26:BT33) -> 1438778 | BV35: TOTAL SHIPPING FEES | BX35: =BY35/BT17 -> 5.0075653 | BY35: =SUM(BY24:BY34) -> 122347.84 | CA35: TOTAL LANDED COST (TLC) | CD35: =SUM(CD26:CD34) -> 14674.85 | CE35: =SUM(CE26:CE33) -> 1469438.4 | CG35: TOTAL SHIPPING FEES | CI35: =CJ35/CE17 -> 5.354532 | CJ35: =SUM(CJ24:CJ34) -> 131251.08 | CL35: TOTAL LANDED COST (TLC) | CO35: =SUM(CO26:CO34) -> 14728.04 | CP35: =SUM(CP26:CP33) -> 1478123 | CR35: TOTAL SHIPPING FEES | CT35: =CU35/CP17 -> 5.0075653 | CU35: =SUM(CU24:CU34) -> 122347.84 | CW35: TOTAL LANDED COST (TLC) | CZ35: =SUM(CZ26:CZ34) -> 14674.85 | DA35: =SUM(DA26:DA33) -> 1666803.9 | DC35: TOTAL SHIPPING FEES | DE35: =DF35/DA17 -> 5.354532 | DF35: =SUM(DF24:DF34) -> 131251.08 | DI35: TOTAL LANDED COST (TLC) | DL35: =SUM(DL26:DL34) -> 14674.85 | DM35: =SUM(DM26:DM33) -> 1917879.9 | DO35: TOTAL SHIPPING FEES | DQ35: =DR35/DM17 -> 5.354532 | DR35: =SUM(DR24:DR34) -> 131251.08
K36: =K35/F22 -> 0.081510549 | V36: =V35/Q22 -> 0.092545722 | AG36: =AG35/AB22 -> 0.085803194 | AR36: =AR35/AM22 -> 0.087744615 | BC36: =BC35/AX22 -> 0.093879224 | BM36: =116.86*BI17 -> 2855193.6 | BN36: =BN35/BI22 -> 0.085777735 | BY36: =BY35/BT22 -> 0.090571339 | CU36: =CU35/CP22 -> 0.088007999
B37: DISCREPANCY | M37: DISCREPANCY | X37: DISCREPANCY | AI37: DISCREPANCY | AT37: DISCREPANCY | BE37: DISCREPANCY | BM37: =BN35/BM36 -> 0.040189026 | BP37: DISCREPANCY | CA37: DISCREPANCY | CL37: DISCREPANCY | CW37: DISCREPANCY | DI37: DISCREPANCY
B38: DOLLAR PAYMENT | D38: 29545.32 | E38: =D38-D17 -> 0 | F38: =E38*F18 -> 0 | M38: DOLLAR PAYMENT | O38: =O17 -> 20826 | P38: =O38-O17 -> 0 | Q38: =P38*Q18 -> 0 | X38: DOLLAR PAYMENT | Z38: 23520 | AA38: =Z38-Z17 -> -179.2 | AB38: =AA38*AB18 -> -10931.2 | AI38: DOLLAR PAYMENT | AK38: =AK17 -> 23171.6 | AL38: =AK38-AK17 -> 0 | AM38: =AL38*AM18 -> 0 | AT38: DOLLAR PAYMENT | AV38: =AV17 -> 21654.6 | AW38: =AV38-AV17 -> 0 | AX38: =AW38*AX18 -> 0 | BE38: DOLLAR PAYMENT | BG38: =BG17 -> 21930 | BH38: =BG38-BG17 -> 0 | BI38: =BH38*BI18 -> 0 | BP38: DOLLAR PAYMENT | BR38: =BR17 -> 22145 | BS38: =BR38-BR17 -> 0 | BT38: =BS38*BT18 -> 0 | CA38: DOLLAR PAYMENT | CC38: =CC17 -> 22648.5 | CD38: =CC38-CC17 -> 0 | CE38: =CD38*CE18 -> 0 | CL38: DOLLAR PAYMENT | CN38: =CN17 -> 22790 | CO38: =CN38-CN17 -> 0 | CP38: =CO38*CP18 -> 0 | CW38: DOLLAR PAYMENT | CY38: =CY17 -> 25884 | CZ38: =CY38-CY17 -> 0 | DA38: =CZ38*DA18 -> 0 | DI38: DOLLAR PAYMENT | DK38: =DK17 -> 30000 | DL38: =DK38-DK17 -> 0 | DM38: =DL38*DM18 -> 0

Sheet Pricing Trends
A3: 180ML POUCH PALM [SUP] | D3: 2.1 | E3: 1.5 | F3: 300ML BOX PALM SUP | I3: 25 | K3: 1LITER LABEL SOYA | N3: 0.72
A4: 300ML POUCH PALM [SUP] | D4: 2.6 | E4: 1.95 | F4: 180ML BOX PALM SUP | I4: 25
A5: 500ML POUCH PALM [SUP] | E5: 2.5 | F5: 500ML BOX PALM SUP | I5: 22
A6: 1LITER POUCH PALM [SUP] | D6: 4.7 | E6: 4 | F6: 1LITER BOX PALM SUP | I6: 31
A7: 2LITERS POUCH PALM [SUP] | D7: 6.17 | E7: 4.5 | F7: 2LITERS BOX PALM SUP | I7: 27
A9: CatName | B9: BOTTLE | F9: CatName | G9: BOX | K9: CatName | L9: LABEL | R9: CatName | S9: REFINED OIL | W9: CatName | X9: TAPE
A11: Average of UnitPrice | F11: Average of UnitPrice | K11: Average of UnitPrice | R11: Average of UnitPrice | W11: Average of UnitPrice
A12: SubDescription | B12: dDate | C12: SupplierName | D12: Total | F12: SubDescription | G12: dDate | H12: SupplierName | I12: Total | K12: SubDescription | L12: dDate | M12: SupplierName | N12: Total | P12: isUsed? | Q12: Conca | R12: SubDescription | S12: dDate | T12: InvcRemarks | U12: Total | W12: SubDescription | X12: dDate | Y12: SupplierName | Z12: Total
A13: 1LITER BOTTLE PALM [SWAK] | B13: 45399 | C13: MC BRIDE CORPORATION | D13: 6.55 | F13: 1G BOX PAMINTA CRACKED | G13: 45540 | H13: SUPERIOR PACKAGING CORPORATION | I13: 6.4 | K13: 1LITER LABEL PALM | L13: 44718 | M13: MACHINEWORLD PHILIPPINES, INC. | N13: 0.55 | P13: ='Profitability - New'!E7 -> TRUE | Q13: =P13&R13 -> TRUERBD SOYA BEAN OIL | R13: RBD SOYA BEAN OIL | S13: 45314 | T13: SOYA - MOI INTERNATIONAL (SINGAPORE) PTE. LTD. | U13: 69.078872 | W13: DOUBLE SIDED TAPE | X13: 45482 | Y13: MULTI-LINE | Z13: 35
B14: 45334 | C14: MC BRIDE CORPORATION | D14: 6.55 | G14: 45075 | H14: SUPERIOR PACKAGING CORPORATION | I14: 6.4 | L14: 44849 | M14: MACHINEWORLD PHILIPPINES, INC. | N14: 0.29 | P14: ='Profitability - New'!E8 -> FALSE | Q14: =P14&R14 -> FALSERBD SOYA BEAN OIL | R14: RBD SOYA BEAN OIL | S14: 45256 | T14: SOYA - CORNERSTONE APAC (S) PTE. LTD. | U14: 68.75434 | W14: DOUBLE SIDED TAPE | X14: 44965 | Y14: CONNAN PACKAGING SUPPLIES TRADING | Z14: 40
B15: 45280 | C15: MC BRIDE CORPORATION | D15: 6.55 | L15: 44868 | M15: MACHINEWORLD PHILIPPINES, INC. | N15: 0.55 | P15: ='Profitability - New'!E9 -> FALSE | Q15: =P15&R15 -> FALSERBD SOYA BEAN OIL | R15: RBD SOYA BEAN OIL | S15: 45132 | T15: SOYA - CORNERSTONE APAC (S) PTE. LTD. | U15: 64.59293 | W15: DOUBLE SIDED TAPE | X15: 44772 | Y15: CONNAN PACKAGING SUPPLIES TRADING | Z15: 40
B16: 45254 | C16: MC BRIDE CORPORATION | D16: 6.55 | F16: 1G BOX PAMINTA FINE | G16: 45540 | H16: SUPERIOR PACKAGING CORPORATION | I16: 6.4 | L16: 44882 | M16: MACHINEWORLD PHILIPPINES, INC. | N16: 0.55 | P16: ='Profitability - New'!E10 -> FALSE | Q16: =P16&R16 -> FALSERBD SOYA BEAN OIL | R16: RBD SOYA BEAN OIL | S16: 44961 | T16: SOYA - CORNERSTONE APAC (S) PTE. LTD. | U16: 81.901482
B17: 45204 | C17: MC BRIDE CORPORATION | D17: 6.6 | G17: 45075 | H17: SUPERIOR PACKAGING CORPORATION | I17: 6.4 | P17: ='Profitability - New'!E11 -> FALSE | Q17: =P17&R17 -> FALSE | W17: PACKAGING TAPE CLEAR | X17: 45482 | Y17: MULTI-LINE | Z17: 25
B18: 45182 | C18: MC BRIDE CORPORATION | D18: 6.55 | K18: 350ML LABEL PALM | L18: 44718 | M18: MACHINEWORLD PHILIPPINES, INC. | N18: 0.3 | P18: ='Profitability - New'!E12 -> FALSE | Q18: =P18&R18 -> FALSERBD COCONUT OIL | R18: RBD COCONUT OIL | S18: 45468 | T18: EMPIRE OIL INTEGRATED MANUFACTURING CORPORATION | U18: 64.678486 | W18: PACKAGING TAPE CLEAR | X18: 45371 | Y18: MULTI-LINE | Z18: 25.5
B19: 45177 | C19: MC BRIDE CORPORATION | D19: 6.55 | F19: 1G BOX PAMINTA WHOLE | G19: 45540 | H19: SUPERIOR PACKAGING CORPORATION | I19: 6.4 | L19: 44849 | M19: MACHINEWORLD PHILIPPINES, INC. | N19: 0.16 | P19: ='Profitability - New'!E13 -> FALSE | Q19: =P19&R19 -> FALSERBD COCONUT OIL | R19: RBD COCONUT OIL | S19: 45222 | T19: COCO - GOLDEN SELECTION COOKING OIL TRADING | U19: 51.4783 | W19: PACKAGING TAPE CLEAR | X19: 45366 | Y19: MULTI-LINE | Z19: 30
B20: 45155 | C20: MC BRIDE CORPORATION | D20: 6.55 | G20: 45075 | H20: SUPERIOR PACKAGING CORPORATION | I20: 6.4 | P20: ='Profitability - New'!E14 -> FALSE | Q20: =P20&R20 -> FALSERBD COCONUT OIL | R20: RBD COCONUT OIL | S20: 45133 | T20: COCO - SME COMMODITIES, INC. | U20: 54.559 | W20: PACKAGING TAPE CLEAR | X20: 45363 | Y20: MULTI-LINE | Z20: 30
B21: 45128 | C21: MC BRIDE CORPORATION | D21: 6.55 | K21: 500ML LABEL PALM | L21: 44718 | M21: MACHINEWORLD PHILIPPINES, INC. | N21: 0.45 | P21: ='Profitability - New'!E15 -> FALSE | Q21: =P21&R21 -> FALSERBD COCONUT OIL | R21: RBD COCONUT OIL | S21: 44965 | T21: COCO - SME COMMODITIES, INC. | U21: 52.7983 | W21: PACKAGING TAPE CLEAR | X21: 45335 | Y21: MULTI-LINE | Z21: 30
B22: 45118 | C22: MC BRIDE CORPORATION | D22: 6.55 | F22: 1LITER BOX CANOLEIN | G22: 45168 | H22: WELL-PACK CONTAINER CORPORATION | I22: 15 | L22: 44849 | M22: MACHINEWORLD PHILIPPINES, INC. | N22: 0.16 | P22: ='Profitability - New'!E16 -> FALSE | Q22: =P22&R22 -> FALSE | W22: PACKAGING TAPE CLEAR | X22: 45334 | Y22: MULTI-LINE | Z22: 30
B23: 45034 | C23: MC BRIDE CORPORATION | D23: 6.55 | G23: 45065 | H23: SUPERIOR PACKAGING CORPORATION | I23: 15.9 | P23: ='Profitability - New'!E17 -> TRUE | Q23: =P23&R23 -> TRUERBD PALM OLEIN (FOREIGN) | R23: RBD PALM OLEIN (FOREIGN) | S23: 45547 | T23: PALM - MOI INTERNATIONAL (SINGAPORE) | U23: 60.65316 | W23: PACKAGING TAPE CLEAR | X23: 45203 | Y23: MULTI-LINE | Z23: 25.5
B24: 44985 | C24: MC BRIDE CORPORATION | D24: 6.55 | G24: 44748 | H24: EXACT BOX & PACKAGING CORP. | I24: 16 | K24: 2LITERS LABEL CANOLEIN | L24: 44868 | M24: MACHINEWORLD PHILIPPINES, INC. | N24: 1.05 | P24: ='Profitability - New'!E18 -> FALSE | Q24: =P24&R24 -> FALSERBD PALM OLEIN (FOREIGN) | R24: RBD PALM OLEIN (FOREIGN) | S24: 45517 | T24: PALM - MOI INTERNATIONAL (SINGAPORE) | U24: 60.97 | W24: PACKAGING TAPE CLEAR | X24: 45074 | Y24: MULTI-LINE | Z24: 27
P25: ='Profitability - New'!E19 -> FALSE | Q25: =P25&R25 -> FALSERBD PALM OLEIN (FOREIGN) | R25: RBD PALM OLEIN (FOREIGN) | S25: 45494 | T25: PALM - MOI INTERNATIONAL (SINGAPORE) | U25: 60.49687 | W25: PACKAGING TAPE CLEAR | X25: 45072 | Y25: MULTI-LINE | Z25: 48
A26: 350ML BOTTLE PALM [SWAK] | B26: 45504 | C26: MC BRIDE CORPORATION | D26: 3.35 | F26: 1LITER BOX PALM | G26: 45346 | H26: EXACT BOX & PACKAGING CORP. | I26: 31 | K26: 2LITERS LABEL PALM | L26: 44868 | M26: MACHINEWORLD PHILIPPINES, INC. | N26: 1.02 | P26: ='Profitability - New'!E20 -> FALSE | Q26: =P26&R26 -> FALSERBD PALM OLEIN (FOREIGN) | R26: RBD PALM OLEIN (FOREIGN) | S26: 45314 | T26: PALM - MOI INTERNATIONAL (SINGAPORE) PTE. LTD. | U26: 57.51356 | W26: PACKAGING TAPE CLEAR | X26: 45071 | Y26: MULTI-LINE | Z26: 48
B27: 45458 | C27: MC BRIDE CORPORATION | D27: 3.35 | G27: 45345 | H27: EXACT BOX & PACKAGING CORP. | I27: 31 | P27: ='Profitability - New'!E21 -> FALSE | Q27: =P27&R27 -> FALSERBD PALM OLEIN (FOREIGN) | R27: RBD PALM OLEIN (FOREIGN) | S27: 45248 | T27: PALM - CORNERSTONE APAC (S) PTE. LTD. | U27: 61.45051 | W27: PACKAGING TAPE CLEAR | X27: 45068 | Y27: MULTI-LINE | Z27: 48
B28: 45442 | C28: MC BRIDE CORPORATION | D28: 3.35 | G28: 45227 | H28: EXACT BOX & PACKAGING CORP. | I28: 31 | K28: 2LITERS LABEL SOYA | L28: 44868 | M28: MACHINEWORLD PHILIPPINES, INC. | N28: 1.05 | P28: ='Profitability - New'!E22 -> FALSE | Q28: =P28&R28 -> FALSERBD PALM OLEIN (FOREIGN) | R28: RBD PALM OLEIN (FOREIGN) | S28: 45244 | T28: PALM - CORNERSTONE APAC (S) PTE. LTD. | U28: 63.35264 | W28: PACKAGING TAPE CLEAR | X28: 45064 | Y28: MULTI-LINE | Z28: 48
B29: 45409 | C29: MC BRIDE CORPORATION | D29: 3.35 | G29: 45198 | H29: EXACT BOX & PACKAGING CORP. | I29: 31 | P29: ='Profitability - New'!E23 -> FALSE | Q29: =P29&R29 -> FALSERBD PALM OLEIN (FOREIGN) | R29: RBD PALM OLEIN (FOREIGN) | S29: 45234 | T29: PALM - MAC WORLD GLOBALLY RELIABLE | U29: 56.63575 | W29: PACKAGING TAPE CLEAR | X29: 44886 | Y29: LIM PAN | Z29: 35
B30: 45378 | C30: MC BRIDE CORPORATION | D30: 3.35 | G30: 45171 | H30: EXACT BOX & PACKAGING CORP. | I30: 31 | K30: 1LITER LABEL CANOLEIN | L30: 44868 | M30: MACHINEWORLD PHILIPPINES, INC. | N30: 0.72 | P30: ='Profitability - New'!E24 -> FALSE | Q30: =P30&R30 -> FALSE
B31: 45334 | C31: MC BRIDE CORPORATION | D31: 3.35 | G31: 44968 | H31: SUPERIOR PACKAGING CORPORATION | I31: 32 | P31: ='Profitability - New'!E25 -> FALSE | Q31: =P31&R31 -> FALSERBD CANOLA OIL | R31: RBD CANOLA OIL | S31: 45269 | T31: CANOLA - MOI INTERNATIONAL (SINGAPORE) PTE. LTD. | U31: 73.180847
B32: 45280 | C32: MC BRIDE CORPORATION | D32: 3.65 | G32: 44888 | H32: EXACT BOX & PACKAGING CORP. | I32: 34 | K32: 1LITER LABEL PALM MZL | L32: 45094 | M32: MACHINEWORLD PHILIPPINES, INC. | N32: 0.7 | P32: ='Profitability - New'!E26 -> FALSE | Q32: =P32&R32 -> FALSERBD CANOLA OIL | R32: RBD CANOLA OIL | S32: 45118 | T32: CANOLA - CORNERSTONE APAC (S) PTE. LTD. | U32: 80.463781
B33: 45204 | C33: MC BRIDE CORPORATION | D33: 3.5 | G33: 44846 | H33: SUPERIOR PACKAGING CORPORATION | I33: 32 | P33: ='Profitability - New'!E27 -> FALSE | Q33: =P33&R33 -> FALSE
B34: 44985 | C34: MC BRIDE CORPORATION | D34: 3.35 | G34: 44842 | H34: EXACT BOX & PACKAGING CORP. | I34: 32 | K34: 4LITERS LABEL SOYA | L34: 45168 | M34: RED AMBER ENTERPRISE | N34: 7 | P34: ='Profitability - New'!E28 -> FALSE | Q34: =P34&R34 -> FALSE
G35: 44825 | H35: EXACT BOX & PACKAGING CORP. | I35: 32 | P35: ='Profitability - New'!E29 -> FALSE | Q35: =P35&R35 -> FALSE
A36: 500ML BOTTLE PALM [SWAK] | B36: 45504 | C36: MC BRIDE CORPORATION | D36: 3.65 | G36: 44800 | H36: EXACT BOX & PACKAGING CORP. | I36: 32 | K36: 4LITERS LABEL PALM | L36: 45168 | M36: RED AMBER ENTERPRISE | N36: 7 | P36: ='Profitability - New'!E30 -> FALSE | Q36: =P36&R36 -> FALSE
B37: 45442 | C37: MC BRIDE CORPORATION | D37: 3.65 | G37: 44782 | H37: EXACT BOX & PACKAGING CORP. | I37: 32 | P37: ='Profitability - New'!E31 -> FALSE | Q37: =P37&R37 -> FALSE
B38: 45334 | C38: MC BRIDE CORPORATION | D38: 3.65 | G38: 44746 | H38: SUPERIOR PACKAGING CORPORATION | I38: 35.86 | K38: 4LITERS LABEL CANOLA | L38: 45168 | M38: RED AMBER ENTERPRISE | N38: 7 | P38: ='Profitability - New'!E32 -> TRUE | Q38: =P38&R38 -> TRUERBD COCONUT OIL | R38: RBD COCONUT OIL | S38: 45468 | T38: EMPIRE OIL INTEGRATED MANUFACTURING CORPORATION | U38: =97/1.1364 -> 85.357269
B39: 45280 | C39: MC BRIDE CORPORATION | D39: 3.35 | G39: 44727 | H39: SUPERIOR PACKAGING CORPORATION | I39: 35.86 | P39: ='Profitability - New'!E33 -> FALSE | Q39: =P39&R39 -> FALSE
B40: 45225 | C40: MC BRIDE CORPORATION | D40: 3.65 | G40: 44707 | H40: SUPERIOR PACKAGING CORPORATION | I40: 35.86 | P40: ='Profitability - New'!E34 -> TRUE | Q40: =P40&R40 -> TRUERBD CANOLA OIL | R40: RBD CANOLA OIL | U40: =CANOLA!AG10 -> 83.220041
B41: 44985 | C41: MC BRIDE CORPORATION | D41: 3.65 | G41: 44583 | H41: SUPERIOR PACKAGING CORPORATION | I41: 32.6 | P41: ='Profitability - New'!E35 -> FALSE | Q41: =P41&R41 -> FALSERBD SOYA BEAN OIL | R41: RBD SOYA BEAN OIL | U41: =SOYA!CW10 -> 81.666042
P42: ='Profitability - New'!E36 -> FALSE | Q42: =P42&R42 -> FALSE
A43: 1LITER BOTTLE CANSOY [NUTRI] | B43: 45504 | C43: MC BRIDE CORPORATION | D43: 6.6 | F43: 1LITER BOX PALM [TIE-UP] | G43: 44824 | H43: EXACT BOX & PACKAGING CORP. | I43: 33 | P43: ='Profitability - New'!E37 -> FALSE | Q43: =P43&R43 -> FALSERBD PALM OLEIN (FOREIGN) | R43: RBD PALM OLEIN (FOREIGN) | U43: =PALM!CU10 -> 64.843399
B44: 45498 | C44: MC BRIDE CORPORATION | D44: 6.6 | P44: ='Profitability - New'!E38 -> FALSE | Q44: =P44&R44 -> FALSE
B45: 45399 | C45: MC BRIDE CORPORATION | D45: 6.6 | F45: 1LITER BOX PALM MZL | G45: 45511 | H45: WELL-PACK CONTAINER CORPORATION | I45: 16.5 | P45: ='Profitability - New'!E39 -> FALSE | Q45: =P45&R45 -> FALSERBD PALM OLEIN (FOREIGN) | R45: RBD PALM OLEIN (FOREIGN) | U45: =PALM!DR10 -> 82.366515
B46: 45173 | C46: MC BRIDE CORPORATION | D46: 6.55 | G46: 45268 | H46: WELL-PACK CONTAINER CORPORATION | I46: 16.5 | P46: ='Profitability - New'!E40 -> FALSE | Q46: =P46&R46 -> FALSERBD PALM OLEIN (FOREIGN) | R46: RBD PALM OLEIN (FOREIGN) | U46: =PALM!DR6 -> 74.65686 | V46: NVAT
P47: ='Profitability - New'!E41 -> FALSE | Q47: =P47&R47 -> FALSE
A48: 2LITERS BOTTLE CANOLEIN [ROUND] | B48: 45378 | C48: MC BRIDE CORPORATION | D48: 18.1 | F48: 1LITER BOX SOYA | G48: 45168 | H48: WELL-PACK CONTAINER CORPORATION | I48: 15 | P48: ='Profitability - New'!E42 -> FALSE | Q48: =P48&R48 -> FALSE
B49: 45187 | C49: MC BRIDE CORPORATION | D49: 19 | P49: ='Profitability - New'!E43 -> FALSE | Q49: =P49&R49 -> FALSE
F50: 2LITERS BOX CANOLEIN | G50: 45168 | H50: WELL-PACK CONTAINER CORPORATION | I50: 16.4 | P50: ='Profitability - New'!E44 -> FALSE | Q50: =P50&R50 -> FALSE
A51: 2LITERS BOTTLE SOYA [ROUND] | B51: 45194 | C51: MC BRIDE CORPORATION | D51: 19 | G51: 44888 | H51: EXACT BOX & PACKAGING CORP. | I51: 27.5 | P51: ='Profitability - New'!E45 -> FALSE | Q51: =P51&R51 -> FALSE
P52: ='Profitability - New'!E46 -> FALSE | Q52: =P52&R52 -> FALSE
A53: 2LITERS BOTTLE PALM [NUTRI] | B53: 45254 | C53: MC BRIDE CORPORATION | D53: 15.75 | F53: 2LITERS BOX PALM | G53: 45346 | H53: EXACT BOX & PACKAGING CORP. | I53: 27 | P53: ='Profitability - New'!E47 -> FALSE | Q53: =P53&R53 -> FALSE
B54: 45182 | C54: MC BRIDE CORPORATION | D54: 15.75 | G54: 45345 | H54: EXACT BOX & PACKAGING CORP. | I54: 27 | P54: ='Profitability - New'!E48 -> FALSE | Q54: =P54&R54 -> FALSE
B55: 45034 | C55: MC BRIDE CORPORATION | D55: 15.75 | G55: 45198 | H55: EXACT BOX & PACKAGING CORP. | I55: 27 | P55: ='Profitability - New'!E49 -> FALSE | Q55: =P55&R55 -> FALSE
G56: 45074 | H56: EXACT BOX & PACKAGING CORP. | I56: 27 | P56: ='Profitability - New'!E50 -> 0 | Q56: =P56&R56 -> 0
A57: 4LITERS BOTTLE GODZILLA | B57: 45101 | C57: BESTPAK PACKAGING SOLUTIONS, INC. | D57: 32.48 | G57: 44888 | H57: EXACT BOX & PACKAGING CORP. | I57: 31 | P57: ='Profitability - New'!E51 -> 0 | Q57: =P57&R57 -> 0
P58: ='Profitability - New'!E52 -> 0 | Q58: =P58&R58 -> 0
A59: 900ML BOTTLE PALM MAZOLA | B59: 45525 | C59: MC BRIDE CORPORATION | D59: 6.9 | F59: 2LITERS BOX PALM MZL | G59: 45268 | H59: WELL-PACK CONTAINER CORPORATION | I59: 17 | P59: ='Profitability - New'!E53 -> 0 | Q59: =P59&R59 -> 0
B60: 45521 | C60: MC BRIDE CORPORATION | D60: 6.9 | P60: ='Profitability - New'!E54 -> 0 | Q60: =P60&R60 -> 0
B61: 45498 | C61: MC BRIDE CORPORATION | D61: 6.9 | F61: 2LITERS BOX SOYA | G61: 45168 | H61: WELL-PACK CONTAINER CORPORATION | I61: 16.4 | P61: ='Profitability - New'!E55 -> 0 | Q61: =P61&R61 -> 0
B62: 45458 | C62: MC BRIDE CORPORATION | D62: 6.9 | P62: ='Profitability - New'!E56 -> 0 | Q62: =P62&R62 -> 0
B63: 45425 | C63: MC BRIDE CORPORATION | D63: 6.9 | F63: 300G BOX CANTON | G63: 45500 | H63: SUPERIOR PACKAGING CORPORATION | I63: 32.75 | P63: ='Profitability - New'!E57 -> 0 | Q63: =P63&R63 -> 0
B64: 45409 | C64: MC BRIDE CORPORATION | D64: 6.9 | G64: 45344 | H64: SUPERIOR PACKAGING CORPORATION | I64: 32.75 | P64: ='Profitability - New'!E58 -> 0 | Q64: =P64&R64 -> 0
B65: 45399 | C65: MC BRIDE CORPORATION | D65: 6.9 | G65: 45152 | H65: SUPERIOR PACKAGING CORPORATION | I65: 32.75 | P65: ='Profitability - New'!E59 -> 0 | Q65: =P65&R65 -> 0
G66: 45094 | H66: SUPERIOR PACKAGING CORPORATION | I66: 30.75 | P66: ='Profitability - New'!E60 -> 0 | Q66: =P66&R66 -> 0
A67: 2LITERS BOTTLE PALM MAZOLA | B67: 45539 | C67: MC BRIDE CORPORATION | D67: 21.95 | P67: ='Profitability - New'!E61 -> 0 | Q67: =P67&R67 -> 0
B68: 45425 | C68: MC BRIDE CORPORATION | D68: 21.95 | F68: 350ML BOX PALM | G68: 45526 | H68: WELL-PACK CONTAINER CORPORATION | I68: 29 | P68: ='Profitability - New'!E62 -> 0 | Q68: =P68&R68 -> 0
G69: 45464 | H69: WELL-PACK CONTAINER CORPORATION | I69: 29 | P69: ='Profitability - New'!E63 -> 0 | Q69: =P69&R69 -> 0
G70: 45394 | H70: WELL-PACK CONTAINER CORPORATION | I70: 29 | P70: ='Profitability - New'!E64 -> 0 | Q70: =P70&R70 -> 0
P71: ='Profitability - New'!E65 -> 0 | Q71: =P71&R71 -> 0
F72: 4LITERS BOX CHECK | G72: 45168 | H72: WELL-PACK CONTAINER CORPORATION | I72: 16 | P72: ='Profitability - New'!E66 -> 0 | Q72: =P72&R72 -> 0
P73: ='Profitability - New'!E67 -> 0 | Q73: =P73&R73 -> 0
F74: 500ML BOX PALM | G74: 45461 | H74: EXACT BOX & PACKAGING CORP. | I74: 20.7 | P74: ='Profitability - New'!E68 -> 0 | Q74: =P74&R74 -> 0
G75: 45346 | H75: EXACT BOX & PACKAGING CORP. | I75: 20.7 | P75: ='Profitability - New'!E69 -> 0 | Q75: =P75&R75 -> 0
G76: 45345 | H76: EXACT BOX & PACKAGING CORP. | I76: 20.7 | P76: ='Profitability - New'!E70 -> 0 | Q76: =P76&R76 -> 0
G77: 44800 | H77: EXACT BOX & PACKAGING CORP. | I77: 22 | P77: ='Profitability - New'!E71 -> 0 | Q77: =P77&R77 -> 0
P78: ='Profitability - New'!E72 -> 0 | Q78: =P78&R78 -> 0
P79: ='Profitability - New'!E73 -> 0 | Q79: =P79&R79 -> 0
P80: ='Profitability - New'!E74 -> 0 | Q80: =P80&R80 -> 0
P81: ='Profitability - New'!E75 -> 0 | Q81: =P81&R81 -> 0
P82: ='Profitability - New'!E76 -> 0 | Q82: =P82&R82 -> 0
P83: ='Profitability - New'!E77 -> 0 | Q83: =P83&R83 -> 0
P84: ='Profitability - New'!E78 -> 0 | Q84: =P84&R84 -> 0
P85: ='Profitability - New'!E79 -> 0 | Q85: =P85&R85 -> 0
P86: ='Profitability - New'!E80 -> 0 | Q86: =P86&R86 -> 0
P87: ='Profitability - New'!E81 -> 0 | Q87: =P87&R87 -> 0
P88: ='Profitability - New'!E82 -> 0 | Q88: =P88&R88 -> 0
P89: ='Profitability - New'!E83 -> 0 | Q89: =P89&R89 -> 0
... P104: ='Profitability - New'!E98 -> 0 | Q104: =P104&R104 -> 0

Sheet Profitability - OSave
G1: NOTE: THAT THE DIFFERENCE OF DECLARED VAT IMPORTATION IS 2-3% ONLY | I1: 29.5 | J1: 1200 @ 57.30 | M1: 79 | N1: 1200 @ 57.30 | U1: PET | AF1: SUP | AK1: PPR | AL1: 115 | AM1: 1500 @ 57.30 | AN1: 236.17 | AO1: =(AN6-AN1)/AN1 -> -0.038827963 | AP1: CNE | AQ1: 535.95 | AR1: =(AQ6-AQ1)/AQ1 -> 0 | AU1: CNL | AW1: 1500 @ 57.30 | AZ1: SYA | BE1: SYP | BH1: VEG
B2: OIL COSTING | G2: PROFITABILITY | I2: PALMF.100 | V2: PALMF.100 | AG2: PALMF.100 | AL2: CAN.100 | AQ2: CAN.100 | AV2: SOY.100 | BA2: SOY.100 | BF2: VG100
I3: PALM OIL PET | V3: PALM OIL SUP | AG3: PALM | AL3: CANOLEIN | AQ3: CANOLA | AV3: SOYA | BA3: SOYA | BF3: VEGE
G5: DESCRIPTION | I5: 350ML | J5: 36 | K5: 500ML | L5: 24 | M5: 1LSWAK | N5: 12 | O5: 1LMZL | P5: 12 | Q5: 2LNUTRI | R5: 6 | S5: 2LMZL | T5: 6 | V5: 180ML | W5: 48 | X5: 300ML | Y5: 36 | Z5: 500ML | AA5: 24 | AB5: 1LITER | AC5: 12 | AD5: 2LITERS | AE5: 6 | AG5: 4LITER | AH5: 4 | AI5: 17KG | AJ5: 1 | AL5: 1LITER | AM5: 12 | AN5: 2LITER | AO5: 6 | AQ5: 4LITER | AR5: 4 | AS5: 17KG | AT5: 1 | AV5: 1LITER | AW5: 12 | AX5: 2LITER | AY5: 6 | BA5: 4LITER | BB5: 4 | BC5: 17KG | BD5: 1 | BF5: 17KG | BG5: 1
B6: Description | C6: Date | D6: Price | E6: isUsed | G6: SALES | I6: 35 | J6: =I6/I6 -> 1 | K6: 51 | L6: =K6/K6 -> 1 | M6: 91 | N6: =M6/M6 -> 1 | O6: 116.86029 | P6: =O6/O6 -> 1 | Q6: 226.22058 | R6: =Q6/Q6 -> 1 | S6: 226.22058 | T6: =S6/S6 -> 1 | V6: 20 | W6: =V6/V6 -> 1 | X6: 31 | Y6: =X6/X6 -> 1 | Z6: =AB6*0.5+2 -> 49.5 | AA6: =Z6/Z6 -> 1 | AB6: 95 | AC6: =AB6/AB6 -> 1 | AD6: 180 | AE6: =AD6/AD6 -> 1 | AG6: 447.44116 | AH6: =AG6/AG6 -> 1 | AI6: 1600 | AJ6: =AI6/AI6 -> 1 | AL6: 108.5 | AM6: =AL6/AL6 -> 1 | AN6: 227 | AO6: =AN6/AN6 -> 1 | AQ6: 535.95 | AR6: =AQ6/AQ6 -> 1 | AS6: 1977.79 | AT6: =AS6/AS6 -> 1 | AV6: 115 | AW6: =AV6/AV6 -> 1 | AX6: 240 | AY6: =AX6/AX6 -> 1 | BA6: 551.432 | BB6: =BA6/BA6 -> 1 | BC6: 2150 | BD6: =BC6/BC6 -> 1 | BF6: 1450 | BG6: =BF6/BF6 -> 1
B7: ='Pricing Trends'!R13 -> RBD SOYA BEAN OIL | C7: ='Pricing Trends'!S13 -> 45314 | D7: ='Pricing Trends'!U13 -> 69.078872 | E7: FALSE | G7: RBD SOYA BEAN OIL | I7: =IFERROR(VLOOKUP($I$2&$G7,Validation!$E:$O,4,FALSE),0) -> 0 | J7: =I7/I$6 -> 0 | K7: =IFERROR(VLOOKUP($I$2&$G7,Validation!$E:$O,5,FALSE),0) -> 0 | L7: =K7/K$6 -> 0 | M7: =IFERROR(VLOOKUP($I$2&$G7,Validation!$E:$O,6,FALSE),0) -> 0 | N7: =M7/M$6 -> 0 | O7: =IFERROR(VLOOKUP($I$2&$G7,Validation!$E:$O,6,FALSE),0) -> 0 | P7: =O7/O$6 -> 0 | Q7: =IFERROR(VLOOKUP($I$2&$G7,Validation!$E:$O,7,FALSE),0) -> 0 | R7: =Q7/Q$6 -> 0 | S7: =IFERROR(VLOOKUP($I$2&$G7,Validation!$E:$O,7,FALSE),0) -> 0 | T7: =S7/S$6 -> 0 | V7: =IFERROR(VLOOKUP($V$2&$G7,Validation!$E:$O,9,FALSE),0) -> 0 | W7: =V7/V$6 -> 0 | X7: =IFERROR(VLOOKUP($V$2&$G7,Validation!$E:$O,10,FALSE),0) -> 0 | Y7: =X7/X$6 -> 0 | Z7: =IFERROR(VLOOKUP($V$2&$G7,Validation!$E:$O,5,FALSE),0) -> 0 | AA7: =Z7/Z$6 -> 0 | AB7: =IFERROR(VLOOKUP($V$2&$G7,Validation!$E:$O,6,FALSE),0) -> 0 | AC7: =AB7/AB$6 -> 0 | AD7: =IFERROR(VLOOKUP($V$2&$G7,Validation!$E:$O,7,FALSE),0) -> 0 | AE7: =AD7/AD$6 -> 0 | AG7: =IFERROR(VLOOKUP($AG$2&$G7,Validation!E:O,8,FALSE),0) -> 0 | AH7: =AG7/AG$6 -> 0 | AI7: =IFERROR(VLOOKUP($AG$2&$G7,Validation!E:O,11,FALSE),0) -> 0 | AJ7: =AI7/AI$6 -> 0 | AL7: =IFERROR(VLOOKUP($AL$2&$G7,Validation!$E:$O,6,FALSE),0) -> 0 | AM7: =AL7/AL$6 -> 0 | AN7: =IFERROR(VLOOKUP($AL$2&$G7,Validation!$E:$O,7,FALSE),0) -> 0 | AO7: =AN7/AN$6 -> 0 | AQ7: =IFERROR(VLOOKUP($AQ$2&$G7,Validation!$E:$O,8,FALSE),0) -> 0 | AR7: =AQ7/AQ$6 -> 0 | AS7: =IFERROR(VLOOKUP($AQ$2&$G7,Validation!$E:$O,11,FALSE),0) -> 0 | AT7: =AS7/AS$6 -> 0 | AV7: 75.63 | AW7: =AV7/AV$6 -> 0.65765217 | AX7: =IFERROR(VLOOKUP($AV$2&$G7,Validation!$E:$O,7,FALSE),0) -> 138.15774 | AY7: =AX7/AX$6 -> 0.57565727 | BA7: =IFERROR(VLOOKUP($BA$2&$G7,Validation!$E:$L,8,FALSE),0) -> 276.31549 | BB7: =BA7/BA$6 -> 0.50108715 | BC7: =IFERROR(VLOOKUP($BA$2&$G7,Validation!$E:$O,11,FALSE),0) -> 1229.3293 | BD7: =BC7/BC$6 -> 0.57178105 | BF7: =IFERROR(VLOOKUP($BF$2&$G7,Validation!E:O,11,FALSE),0) -> 0 | BG7: =BF7/BF$6 -> 0
B8: ='Pricing Trends'!R14 -> RBD SOYA BEAN OIL | C8: ='Pricing Trends'!S14 -> 45256 | D8: ='Pricing Trends'!U14 -> 68.75434 | E8: FALSE | G8: RBD PALM OLEIN (LOCAL) | I8: =IFERROR(VLOOKUP($I$2&$G8,Validation!$E:$O,4,FALSE),0) -> 0 | J8: =I8/I$6 -> 0 | K8: =IFERROR(VLOOKUP($I$2&$G8,Validation!$E:$O,5,FALSE),0) -> 0 | L8: =K8/K$6 -> 0 | M8: =IFERROR(VLOOKUP($I$2&$G8,Validation!$E:$O,6,FALSE),0) -> 0 | N8: =M8/M$6 -> 0 | O8: =IFERROR(VLOOKUP($I$2&$G8,Validation!$E:$O,6,FALSE),0) -> 0 | P8: =O8/O$6 -> 0 | Q8: =IFERROR(VLOOKUP($I$2&$G8,Validation!$E:$O,7,FALSE),0) -> 0 | R8: =Q8/Q$6 -> 0 | S8: =IFERROR(VLOOKUP($I$2&$G8,Validation!$E:$O,7,FALSE),0) -> 0 | T8: =S8/S$6 -> 0 | V8: =IFERROR(VLOOKUP($V$2&$G8,Validation!$E:$O,9,FALSE),0) -> 0 | W8: =V8/V$6 -> 0 | X8: =IFERROR(VLOOKUP($V$2&$G8,Validation!$E:$O,10,FALSE),0) -> 0 | Y8: =X8/X$6 -> 0 | Z8: =IFERROR(VLOOKUP($V$2&$G8,Validation!$E:$O,5,FALSE),0) -> 0 | AA8: =Z8/Z$6 -> 0 | AB8: =IFERROR(VLOOKUP($V$2&$G8,Validation!$E:$O,6,FALSE),0) -> 0 | AC8: =AB8/AB$6 -> 0 | AD8: =IFERROR(VLOOKUP($V$2&$G8,Validation!$E:$O,7,FALSE),0) -> 0 | AE8: =AD8/AD$6 -> 0 | AG8: =IFERROR(VLOOKUP($AG$2&$G8,Validation!E:O,8,FALSE),0) -> 0 | AH8: =AG8/AG$6 -> 0 | AI8: =IFERROR(VLOOKUP($AG$2&$G8,Validation!E:O,11,FALSE),0) -> 0 | AJ8: =AI8/AI$6 -> 0 | AL8: =IFERROR(VLOOKUP($AL$2&$G8,Validation!$E:$O,6,FALSE),0) -> 0 | AM8: =AL8/AL$6 -> 0 | AN8: =IFERROR(VLOOKUP($AL$2&$G8,Validation!$E:$O,7,FALSE),0) -> 0 | AO8: =AN8/AN$6 -> 0 | AQ8: =IFERROR(VLOOKUP($AQ$2&$G8,Validation!$E:$O,8,FALSE),0) -> 0 | AR8: =AQ8/AQ$6 -> 0 | AS8: =IFERROR(VLOOKUP($AQ$2&$G8,Validation!$E:$O,11,FALSE),0) -> 0 | AT8: =AS8/AS$6 -> 0 | AV8: =IFERROR(VLOOKUP($AV$2&$G8,Validation!$E:$O,6,FALSE),0) -> 0 | AW8: =AV8/AV$6 -> 0 | AX8: =IFERROR(VLOOKUP($AV$2&$G8,Validation!$E:$O,7,FALSE),0) -> 0 | AY8: =AX8/AX$6 -> 0 | BA8: =IFERROR(VLOOKUP($BA$2&$G8,Validation!$E:$L,8,FALSE),0) -> 0 | BB8: =BA8/BA$6 -> 0 | BC8: =IFERROR(VLOOKUP($BA$2&$G8,Validation!$E:$O,11,FALSE),0) -> 0 | BD8: =BC8/BC$6 -> 0 | BF8: =IFERROR(VLOOKUP($BF$2&$G8,Validation!E:O,11,FALSE),0) -> 0 | BG8: =BF8/BF$6 -> 0
B9: ='Pricing Trends'!R15 -> RBD SOYA BEAN OIL | C9: ='Pricing Trends'!S15 -> 45132 | D9: ='Pricing Trends'!U15 -> 64.59293 | E9: FALSE | G9: RBD PALM OLEIN (FOREIGN) | I9: =M9*(350/1000) -> 28.82828 | J9: =I9/I$6 -> 0.82366515 | K9: =M9/2 -> 41.183258 | L9: =K9/K$6 -> 0.80751485 | M9: =PALM!DR10 -> 82.366515 | N9: =M9/M$6 -> 0.90512654 | O9: =IFERROR(VLOOKUP($I$2&$G9,Validation!$E:$O,6,FALSE),0) -> 60.65316 | P9: =O9/O$6 -> 0.51902284 | Q9: =IFERROR(VLOOKUP($I$2&$G9,Validation!$E:$O,7,FALSE),0) -> 121.30632 | R9: =Q9/Q$6 -> 0.53623026 | S9: =IFERROR(VLOOKUP($I$2&$G9,Validation!$E:$O,7,FALSE),0) -> 121.30632 | T9: =S9/S$6 -> 0.53623026 | V9: =IFERROR(VLOOKUP($V$2&$G9,Validation!$E:$O,9,FALSE),0) -> 10.917569 | W9: =V9/V$6 -> 0.54587844 | X9: =IFERROR(VLOOKUP($V$2&$G9,Validation!$E:$O,10,FALSE),0) -> 18.195948 | Y9: =X9/X$6 -> 0.58696606 | Z9: =IFERROR(VLOOKUP($V$2&$G9,Validation!$E:$O,5,FALSE),0) -> 30.32658 | AA9: =Z9/Z$6 -> 0.61265818 | AB9: =IFERROR(VLOOKUP($V$2&$G9,Validation!$E:$O,6,FALSE),0) -> 60.65316 | AC9: =AB9/AB$6 -> 0.63845432 | AD9: =IFERROR(VLOOKUP($V$2&$G9,Validation!$E:$O,7,FALSE),0) -> 121.30632 | AE9: =AD9/AD$6 -> 0.673924 | AG9: =IFERROR(VLOOKUP($AG$2&$G9,Validation!E:O,8,FALSE),0) -> 242.61264 | AH9: =AG9/AG$6 -> 0.54222245 | AI9: =IFERROR(VLOOKUP($AG$2&$G9,Validation!E:O,11,FALSE),0) -> 1079.3851 | AJ9: =AI9/AI$6 -> 0.67461568 | AL9: =IFERROR(VLOOKUP($AL$2&$G9,Validation!$E:$O,6,FALSE),0) -> 0 | AM9: =AL9/AL$6 -> 0 | AN9: =IFERROR(VLOOKUP($AL$2&$G9,Validation!$E:$O,7,FALSE),0) -> 0 | AO9: =AN9/AN$6 -> 0 | AQ9: =IFERROR(VLOOKUP($AQ$2&$G9,Validation!$E:$O,8,FALSE),0) -> 0 | AR9: =AQ9/AQ$6 -> 0 | AS9: =IFERROR(VLOOKUP($AQ$2&$G9,Validation!$E:$O,11,FALSE),0) -> 0 | AT9: =AS9/AS$6 -> 0 | AV9: =IFERROR(VLOOKUP($AV$2&$G9,Validation!$E:$O,6,FALSE),0) -> 0 | AW9: =AV9/AV$6 -> 0 | AX9: =IFERROR(VLOOKUP($AV$2&$G9,Validation!$E:$O,7,FALSE),0) -> 0 | AY9: =AX9/AX$6 -> 0 | BA9: =IFERROR(VLOOKUP($BA$2&$G9,Validation!$E:$L,8,FALSE),0) -> 0 | BB9: =BA9/BA$6 -> 0 | BC9: =IFERROR(VLOOKUP($BA$2&$G9,Validation!$E:$O,11,FALSE),0) -> 0 | BD9: =BC9/BC$6 -> 0 | BF9: =IFERROR(VLOOKUP($BF$2&$G9,Validation!E:O,11,FALSE),0) -> 0 | BG9: =BF9/BF$6 -> 0
B10: ='Pricing Trends'!R16 -> RBD SOYA BEAN OIL | C10: ='Pricing Trends'!S16 -> 44961 | D10: ='Pricing Trends'!U16 -> 81.901482 | E10: FALSE | G10: RBD CANOLA OIL | I10: =IFERROR(VLOOKUP($I$2&$G10,Validation!$E:$O,4,FALSE),0) -> 0 | J10: =I10/I$6 -> 0 | K10: =IFERROR(VLOOKUP($I$2&$G10,Validation!$E:$O,5,FALSE),0) -> 0 | L10: =K10/K$6 -> 0 | M10: =IFERROR(VLOOKUP($I$2&$G10,Validation!$E:$O,6,FALSE),0) -> 0 | N10: =M10/M$6 -> 0 | O10: =IFERROR(VLOOKUP($I$2&$G10,Validation!$E:$O,6,FALSE),0) -> 0 | P10: =O10/O$6 -> 0 | Q10: =IFERROR(VLOOKUP($I$2&$G10,Validation!$E:$O,7,FALSE),0) -> 0 | R10: =Q10/Q$6 -> 0 | S10: =IFERROR(VLOOKUP($I$2&$G10,Validation!$E:$O,7,FALSE),0) -> 0 | T10: =S10/S$6 -> 0 | V10: =IFERROR(VLOOKUP($V$2&$G10,Validation!$E:$O,9,FALSE),0) -> 0 | W10: =V10/V$6 -> 0 | X10: =IFERROR(VLOOKUP($V$2&$G10,Validation!$E:$O,10,FALSE),0) -> 0 | Y10: =X10/X$6 -> 0 | Z10: =IFERROR(VLOOKUP($V$2&$G10,Validation!$E:$O,5,FALSE),0) -> 0 | AA10: =Z10/Z$6 -> 0 | AB10: =IFERROR(VLOOKUP($V$2&$G10,Validation!$E:$O,6,FALSE),0) -> 0 | AC10: =AB10/AB$6 -> 0 | AD10: =IFERROR(VLOOKUP($V$2&$G10,Validation!$E:$O,7,FALSE),0) -> 0 | AE10: =AD10/AD$6 -> 0 | AG10: =IFERROR(VLOOKUP($AG$2&$G10,Validation!E:O,8,FALSE),0) -> 0 | AH10: =AG10/AG$6 -> 0 | AI10: =IFERROR(VLOOKUP($AG$2&$G10,Validation!E:O,11,FALSE),0) -> 0 | AJ10: =AI10/AI$6 -> 0 | AL10: 75.24 | AM10: =AL10/AL$6 -> 0.69345622 | AN10: =IFERROR(VLOOKUP($AL$2&$G10,Validation!$E:$O,7,FALSE),0) -> 166.44008 | AO10: =AN10/AN$6 -> 0.73321622 | AQ10: =IFERROR(VLOOKUP($AQ$2&$G10,Validation!$E:$O,8,FALSE),0) -> 332.88017 | AR10: =AQ10/AQ$6 -> 0.62110302 | AS10: =IFERROR(VLOOKUP($AQ$2&$G10,Validation!$E:$O,11,FALSE),0) -> 1480.9859 | AT10: =AS10/AS$6 -> 0.74880844 | AV10: =IFERROR(VLOOKUP($AV$2&$G10,Validation!$E:$O,6,FALSE),0) -> 0 | AW10: =AV10/AV$6 -> 0 | AX10: =IFERROR(VLOOKUP($AV$2&$G10,Validation!$E:$O,7,FALSE),0) -> 0 | AY10: =AX10/AX$6 -> 0 | BA10: =IFERROR(VLOOKUP($BA$2&$G10,Validation!$E:$L,8,FALSE),0) -> 0 | BB10: =BA10/BA$6 -> 0 | BC10: =IFERROR(VLOOKUP($BA$2&$G10,Validation!$E:$O,11,FALSE),0) -> 0 | BD10: =BC10/BC$6 -> 0 | BF10: =IFERROR(VLOOKUP($BF$2&$G10,Validation!E:O,11,FALSE),0) -> 0 | BG10: =BF10/BF$6 -> 0
B11: ='Pricing Trends'!R17 -> 0 | C11: ='Pricing Trends'!S17 -> 0 | D11: ='Pricing Trends'!U17 -> 0 | E11: FALSE | G11: RBD COCONUT OIL | I11: =IFERROR(VLOOKUP($I$2&$G11,Validation!$E:$O,4,FALSE),0) -> 0 | J11: =I11/I$6 -> 0 | K11: =IFERROR(VLOOKUP($I$2&$G11,Validation!$E:$O,5,FALSE),0) -> 0 | L11: =K11/K$6 -> 0 | M11: =IFERROR(VLOOKUP($I$2&$G11,Validation!$E:$O,6,FALSE),0) -> 0 | N11: =M11/M$6 -> 0 | O11: =IFERROR(VLOOKUP($I$2&$G11,Validation!$E:$O,6,FALSE),0) -> 0 | P11: =O11/O$6 -> 0 | Q11: =IFERROR(VLOOKUP($I$2&$G11,Validation!$E:$O,7,FALSE),0) -> 0 | R11: =Q11/Q$6 -> 0 | S11: =IFERROR(VLOOKUP($I$2&$G11,Validation!$E:$O,7,FALSE),0) -> 0 | T11: =S11/S$6 -> 0 | V11: =IFERROR(VLOOKUP($V$2&$G11,Validation!$E:$O,9,FALSE),0) -> 0 | W11: =V11/V$6 -> 0 | X11: =IFERROR(VLOOKUP($V$2&$G11,Validation!$E:$O,10,FALSE),0) -> 0 | Y11: =X11/X$6 -> 0 | Z11: =IFERROR(VLOOKUP($V$2&$G11,Validation!$E:$O,5,FALSE),0) -> 0 | AA11: =Z11/Z$6 -> 0 | AB11: =IFERROR(VLOOKUP($V$2&$G11,Validation!$E:$O,6,FALSE),0) -> 0 | AC11: =AB11/AB$6 -> 0 | AD11: =IFERROR(VLOOKUP($V$2&$G11,Validation!$E:$O,7,FALSE),0) -> 0 | AE11: =AD11/AD$6 -> 0 | AG11: =IFERROR(VLOOKUP($AG$2&$G11,Validation!E:O,8,FALSE),0) -> 0 | AH11: =AG11/AG$6 -> 0 | AI11: =IFERROR(VLOOKUP($AG$2&$G11,Validation!E:O,11,FALSE),0) -> 0 | AJ11: =AI11/AI$6 -> 0 | AL11: =IFERROR(VLOOKUP($AL$2&$G11,Validation!$E:$O,6,FALSE),0) -> 0 | AM11: =AL11/AL$6 -> 0 | AN11: =IFERROR(VLOOKUP($AL$2&$G11,Validation!$E:$O,7,FALSE),0) -> 0 | AO11: =AN11/AN$6 -> 0 | AQ11: =IFERROR(VLOOKUP($AQ$2&$G11,Validation!$E:$O,8,FALSE),0) -> 0 | AR11: =AQ11/AQ$6 -> 0 | AS11: =IFERROR(VLOOKUP($AQ$2&$G11,Validation!$E:$O,11,FALSE),0) -> 0 | AT11: =AS11/AS$6 -> 0 | AV11: =IFERROR(VLOOKUP($AV$2&$G11,Validation!$E:$O,6,FALSE),0) -> 0 | AW11: =AV11/AV$6 -> 0 | AX11: =IFERROR(VLOOKUP($AV$2&$G11,Validation!$E:$O,7,FALSE),0) -> 0 | AY11: =AX11/AX$6 -> 0 | BA11: =IFERROR(VLOOKUP($I$2&$G11,Validation!$E:$K,4,FALSE),0) -> 0 | BB11: =BA11/BA$6 -> 0 | BC11: =IFERROR(VLOOKUP($BA$2&$G11,Validation!$E:$O,11,FALSE),0) -> 0 | BD11: =BC11/BC$6 -> 0 | BF11: =IFERROR(VLOOKUP($BF$2&$G11,Validation!E:O,11,FALSE),0) -> 1519.02 | BG11: =BF11/BF$6 -> 1.0476
B12: ='Pricing Trends'!R18 -> RBD COCONUT OIL | C12: ='Pricing Trends'!S18 -> 45468 | D12: ='Pricing Trends'!U18 -> 64.678486 | E12: FALSE | G12: LABEL | I12: =IFERROR(VLOOKUP("350ML LABEL PALM",'Pricing Trends'!$K:$N,4,FALSE),0) -> 0.3 | J12: =I12/I$6 -> 0.0085714286 | K12: =IFERROR(VLOOKUP("500ML LABEL PALM",'Pricing Trends'!$K:$N,4,FALSE),0) -> 0.45 | L12: =K12/K$6 -> 0.0088235294 | M12: =IFERROR(VLOOKUP("1LITER LABEL PALM",'Pricing Trends'!$K:$N,4,FALSE),0) -> 0.55 | N12: =M12/M$6 -> 0.006043956 | O12: =IFERROR(VLOOKUP("1LITER LABEL PALM MZL",'Pricing Trends'!$K:$N,4,FALSE),0) -> 0.7 | P12: =O12/O$6 -> 0.0059900587 | Q12: =IFERROR(VLOOKUP("2LITERS LABEL PALM",'Pricing Trends'!$K:$N,4,FALSE),0) -> 1.02 | R12: =Q12/Q$6 -> 0.0045088736 | S12: =IFERROR(VLOOKUP("2LITERS LABEL PALM",'Pricing Trends'!$K:$N,4,FALSE),0) -> 1.02 | T12: =S12/S$6 -> 0.0045088736 | W12: =V12/V$6 -> 0 | Y12: =X12/X$6 -> 0 | AA12: =Z12/Z$6 -> 0 | AC12: =AB12/AB$6 -> 0 | AE12: =AD12/AD$6 -> 0 | AG12: =IFERROR(VLOOKUP("4LITERS LABEL PALM",'Pricing Trends'!$K:$N,4,FALSE),0) -> 7 | AH12: =AG12/AG$6 -> 0.015644515 | AJ12: =AI12/AI$6 -> 0 | AL12: =IFERROR(VLOOKUP("1LITER LABEL CANOLEIN",'Pricing Trends'!$K:$N,4,FALSE),0) -> 0.72 | AM12: =AL12/AL$6 -> 0.0066359447 | AN12: =IFERROR(VLOOKUP("2LITERS LABEL CANOLEIN",'Pricing Trends'!$K:$N,4,FALSE),0) -> 1.05 | AO12: =AN12/AN$6 -> 0.0046255507 | AQ12: =IFERROR(VLOOKUP("4LITERS LABEL CANOLA",'Pricing Trends'!$K:$N,4,FALSE),0) -> 7 | AR12: =AQ12/AQ$6 -> 0.01306092 | AT12: =AS12/AS$6 -> 0 | AV12: =IFERROR(VLOOKUP("1LITER LABEL SOYA",'Pricing Trends'!$K:$N,4,FALSE),0) -> 0.72 | AW12: =AV12/AV$6 -> 0.0062608696 | AX12: =IFERROR(VLOOKUP("2LITERS LABEL SOYA",'Pricing Trends'!$K:$N,4,FALSE),0) -> 1.05 | AY12: =AX12/AX$6 -> 0.004375 | BA12: =IFERROR(VLOOKUP("4LITERS LABEL SOYA",'Pricing Trends'!$K:$N,4,FALSE),0) -> 7 | BB12: =BA12/BA$6 -> 0.012694222 | BD12: =BC12/BC$6 -> 0 | BG12: =BF12/BF$6 -> 0
B13: ='Pricing Trends'!R19 -> RBD COCONUT OIL | C13: ='Pricing Trends'!S19 -> 45222 | D13: ='Pricing Trends'!U19 -> 51.4783 | E13: FALSE | G13: BOTTLE / POUCH | I13: 3.9 | J13: =I13/I$6 -> 0.11142857 | K13: =IFERROR(VLOOKUP("500ML BOTTLE PALM [SWAK]",'Pricing Trends'!$A:$D,4,FALSE),0) -> 3.65 | L13: =K13/K$6 -> 0.071568627 | M13: 9 | N13: =M13/M$6 -> 0.098901099 | O13: =IFERROR(VLOOKUP("900ML BOTTLE PALM MAZOLA",'Pricing Trends'!$A:$D,4,FALSE),0) -> 6.9 | P13: =O13/O$6 -> 0.059044865 | Q13: =IFERROR(VLOOKUP("2LITERS BOTTLE PALM [NUTRI]",'Pricing Trends'!$A:$D,4,FALSE),0) -> 15.75 | R13: =Q13/Q$6 -> 0.069622313 | S13: =IFERROR(VLOOKUP("2LITERS BOTTLE PALM MAZOLA",'Pricing Trends'!$A:$D,4,FALSE),0) -> 21.95 | T13: =S13/S$6 -> 0.097029192 | V13: =IFERROR(VLOOKUP("180ML POUCH PALM [SUP]",'Pricing Trends'!$A:$D,4,FALSE),0) -> 2.1 | W13: =V13/V$6 -> 0.105 | X13: =IFERROR(VLOOKUP("300ML POUCH PALM [SUP]",'Pricing Trends'!$A:$D,4,FALSE),0) -> 2.6 | Y13: =X13/X$6 -> 0.083870968 | Z13: =IFERROR(VLOOKUP("500ML POUCH PALM [SUP]",'Pricing Trends'!$A:$D,4,FALSE),0) -> 0 | AA13: =Z13/Z$6 -> 0 | AB13: =IFERROR(VLOOKUP("1LITER POUCH PALM [SUP]",'Pricing Trends'!$A:$D,4,FALSE),0) -> 4.7 | AC13: =AB13/AB$6 -> 0.049473684 | AD13: =IFERROR(VLOOKUP("2LITERS POUCH PALM [SUP]",'Pricing Trends'!$A:$D,4,FALSE),0) -> 6.17 | AE13: =AD13/AD$6 -> 0.034277778 | AG13: =IFERROR(VLOOKUP("4LITERS BOTTLE GODZILLA",'Pricing Trends'!$A:$D,4,FALSE),0) -> 32.48 | AH13: =AG13/AG$6 -> 0.07259055 | AJ13: =AI13/AI$6 -> 0 | AL13: =IFERROR(VLOOKUP("1LITER BOTTLE CANSOY [NUTRI]",'Pricing Trends'!$A:$D,4,FALSE),0) -> 6.6 | AM13: =AL13/AL$6 -> 0.060829493 | AN13: =IFERROR(VLOOKUP("2LITERS BOTTLE CANOLEIN [ROUND]",'Pricing Trends'!$A:$D,4,FALSE),0) -> 18.1 | AO13: =AN13/AN$6 -> 0.079735683 | AQ13: =IFERROR(VLOOKUP("4LITERS BOTTLE GODZILLA",'Pricing Trends'!$A:$D,4,FALSE),0) -> 32.48 | AR13: =AQ13/AQ$6 -> 0.060602668 | AT13: =AS13/AS$6 -> 0 | AV13: =IFERROR(VLOOKUP("1LITER BOTTLE CANSOY [NUTRI]",'Pricing Trends'!$A:$D,4,FALSE),0) -> 6.6 | AW13: =AV13/AV$6 -> 0.057391304 | AX13: =IFERROR(VLOOKUP("2LITERS BOTTLE SOYA [ROUND]",'Pricing Trends'!$A:$D,4,FALSE),0) -> 19 | AY13: =AX13/AX$6 -> 0.079166667 | BA13: =IFERROR(VLOOKUP("4LITERS BOTTLE GODZILLA",'Pricing Trends'!$A:$D,4,FALSE),0) -> 32.48 | BB13: =BA13/BA$6 -> 0.058901188 | BD13: =BC13/BC$6 -> 0 | BG13: =BF13/BF$6 -> 0
B14: ='Pricing Trends'!R20 -> RBD COCONUT OIL | C14: ='Pricing Trends'!S20 -> 45133 | D14: ='Pricing Trends'!U20 -> 54.559 | E14: FALSE | G14: BOX | I14: =IFERROR(VLOOKUP("350ML BOX PALM",'Pricing Trends'!$F:$I,4,FALSE),0)/J5 -> 0.80555556 | J14: =I14/I$6 -> 0.023015873 | K14: =IFERROR(VLOOKUP("500ML BOX PALM",'Pricing Trends'!$F:$I,4,FALSE),0)/L5 -> 0.8625 | L14: =K14/K$6 -> 0.016911765 | N14: =M14/M$6 -> 0 | O14: =IFERROR(VLOOKUP("1LITER BOX PALM MZL",'Pricing Trends'!$F:$I,4,FALSE),0)/P5 -> 1.375 | P14: =O14/O$6 -> 0.011766187 | Q14: =IFERROR(VLOOKUP("2LITERS BOX PALM",'Pricing Trends'!$F:$I,4,FALSE),0)/R5 -> 4.5 | R14: =Q14/Q$6 -> 0.019892089 | S14: =IFERROR(VLOOKUP("2LITERS BOX PALM MZL",'Pricing Trends'!$F:$I,4,FALSE),0)/T5 -> 2.8333333 | T14: =S14/S$6 -> 0.012524649 | V14: =IFERROR(VLOOKUP("180ML BOX PALM SUP",'Pricing Trends'!$F:$I,4,FALSE),0)/W5 -> 0.52083333 | W14: =V14/V$6 -> 0.026041667 | X14: =IFERROR(VLOOKUP("300ML BOX PALM SUP",'Pricing Trends'!$F:$I,4,FALSE),0)/Y5 -> 0.69444444 | Y14: =X14/X$6 -> 0.022401434 | Z14: =IFERROR(VLOOKUP("500ML BOX PALM SUP",'Pricing Trends'!$F:$I,4,FALSE),0)/AA5 -> 0.91666667 | AA14: =Z14/Z$6 -> 0.018518519 | AB14: =IFERROR(VLOOKUP("1LITER BOX PALM SUP",'Pricing Trends'!$F:$I,4,FALSE),0)/AC5 -> 2.5833333 | AC14: =AB14/AB$6 -> 0.027192982 | AD14: =IFERROR(VLOOKUP("2LITERS BOX PALM SUP",'Pricing Trends'!$F:$I,4,FALSE),0)/AE5 -> 4.5 | AE14: =AD14/AD$6 -> 0.025 | AG14: =IFERROR(VLOOKUP("4LITERS BOX CHECK",'Pricing Trends'!$F:$I,4,FALSE),0)/AH5 -> 4 | AH14: =AG14/AG$6 -> 0.0089397229 | AJ14: =AI14/AI$6 -> 0 | AL14: =IFERROR(VLOOKUP("1LITER BOX CANOLEIN",'Pricing Trends'!$F:$I,4,FALSE),0)/AM5 -> 1.25 | AM14: =AL14/AL$6 -> 0.011520737 | AN14: =IFERROR(VLOOKUP("2LITERS BOX CANOLEIN",'Pricing Trends'!$F:$I,4,FALSE),0)/AO5 -> 2.7333333 | AO14: =AN14/AN$6 -> 0.012041116 | AQ14: =IFERROR(VLOOKUP("4LITERS BOX CHECK",'Pricing Trends'!$F:$I,4,FALSE),0)/AR5 -> 4 | AR14: =AQ14/AQ$6 -> 0.0074633828 | AT14: =AS14/AS$6 -> 0 | AV14: =IFERROR(VLOOKUP("1LITER BOX SOYA",'Pricing Trends'!$F:$I,4,FALSE),0)/AW5 -> 1.25 | AW14: =AV14/AV$6 -> 0.010869565 | AX14: =IFERROR(VLOOKUP("2LITERS BOX CANOLEIN",'Pricing Trends'!$F:$I,4,FALSE),0)/AY5 -> 2.7333333 | AY14: =AX14/AX$6 -> 0.011388889 | BA14: =IFERROR(VLOOKUP("4LITERS BOX CHECK",'Pricing Trends'!$F:$I,4,FALSE),0)/BB5 -> 4 | BB14: =BA14/BA$6 -> 0.0072538409 | BD14: =BC14/BC$6 -> 0 | BG14: =BF14/BF$6 -> 0
B15: ='Pricing Trends'!R21 -> RBD COCONUT OIL | C15: ='Pricing Trends'!S21 -> 44965 | D15: ='Pricing Trends'!U21 -> 52.7983 | E15: FALSE | G15: PACKAGING TAPE CLEAR | I15: =((IFERROR(VLOOKUP($G$15,'Pricing Trends'!$W:$Z,4,FALSE),0)/10000)*200)/J5 -> 0.013888889 | J15: =I15/I$6 -> 0.0003968254 | K15: =((IFERROR(VLOOKUP($G$15,'Pricing Trends'!$W:$Z,4,FALSE),0)/10000)*200)/L5 -> 0.020833333 | L15: =K15/K$6 -> 0.00040849673 | M15: =((IFERROR(VLOOKUP($G$15,'Pricing Trends'!$W:$Z,4,FALSE),0)/10000)*200)/N5 -> 0.041666667 | N15: =M15/M$6 -> 0.00045787546 | O15: =((IFERROR(VLOOKUP($G$15,'Pricing Trends'!$W:$Z,4,FALSE),0)/10000)*200)/P5 -> 0.041666667 | P15: =O15/O$6 -> 0.00035655111 | Q15: =((IFERROR(VLOOKUP($G$15,'Pricing Trends'!$W:$Z,4,FALSE),0)/10000)*200)/R5 -> 0.083333333 | R15: =Q15/Q$6 -> 0.00036837203 | S15: =((IFERROR(VLOOKUP($G$15,'Pricing Trends'!$W:$Z,4,FALSE),0)/10000)*200)/T5 -> 0.083333333 | T15: =S15/S$6 -> 0.00036837203 | V15: =((IFERROR(VLOOKUP($G$15,'Pricing Trends'!$W:$Z,4,FALSE),0)/10000)*200)/W5 -> 0.010416667 | W15: =V15/V$6 -> 0.00052083333 | X15: =((IFERROR(VLOOKUP($G$15,'Pricing Trends'!$W:$Z,4,FALSE),0)/10000)*200)/Y5 -> 0.013888889 | Y15: =X15/X$6 -> 0.00044802867 | Z15: =((IFERROR(VLOOKUP($G$15,'Pricing Trends'!$W:$Z,4,FALSE),0)/10000)*200)/AA5 -> 0.020833333 | AA15: =Z15/Z$6 -> 0.00042087542 | AB15: =((IFERROR(VLOOKUP($G$15,'Pricing Trends'!$W:$Z,4,FALSE),0)/10000)*200)/AC5 -> 0.041666667 | AC15: =AB15/AB$6 -> 0.00043859649 | AD15: =((IFERROR(VLOOKUP($G$15,'Pricing Trends'!$W:$Z,4,FALSE),0)/10000)*200)/AE5 -> 0.083333333 | AE15: =AD15/AD$6 -> 0.00046296296 | AG15: =((IFERROR(VLOOKUP($G$15,'Pricing Trends'!$W:$Z,4,FALSE),0)/10000)*200)/AH5 -> 0.125 | AH15: =AG15/AG$6 -> 0.00027936634 | AJ15: =AI15/AI$6 -> 0 | AL15: =((IFERROR(VLOOKUP($G$15,'Pricing Trends'!$W:$Z,4,FALSE),0)/10000)*200)/AM5 -> 0.041666667 | AM15: =AL15/AL$6 -> 0.00038402458 | AN15: =((IFERROR(VLOOKUP($G$15,'Pricing Trends'!$W:$Z,4,FALSE),0)/10000)*200)/AO5 -> 0.083333333 | AO15: =AN15/AN$6 -> 0.0003671072 | AQ15: =((IFERROR(VLOOKUP($G$15,'Pricing Trends'!$W:$Z,4,FALSE),0)/10000)*200)/AR5 -> 0.125 | AR15: =AQ15/AQ$6 -> 0.00023323071 | AT15: =AS15/AS$6 -> 0 | AV15: =((IFERROR(VLOOKUP($G$15,'Pricing Trends'!$W:$Z,4,FALSE),0)/10000)*200)/AW5 -> 0.041666667 | AW15: =AV15/AV$6 -> 0.00036231884 | AX15: =((IFERROR(VLOOKUP($G$15,'Pricing Trends'!$W:$Z,4,FALSE),0)/10000)*200)/AY5 -> 0.083333333 | AY15: =AX15/AX$6 -> 0.00034722222 | BA15: =((IFERROR(VLOOKUP($G$15,'Pricing Trends'!$W:$Z,4,FALSE),0)/10000)*200)/BB5 -> 0.125 | BB15: =BA15/BA$6 -> 0.00022668253 | BD15: =BC15/BC$6 -> 0 | BG15: =BF15/BF$6 -> 0
B16: ='Pricing Trends'!R22 -> 0 | C16: ='Pricing Trends'!S22 -> 0 | D16: ='Pricing Trends'!U22 -> 0 | E16: FALSE | G16: DOUBLE SIDED TAPE 3/4"X30M | I16: =((45/3000)*7) -> 0.105 | J16: =I16/I$6 -> 0.003 | K16: =((45/3000)*7) -> 0.105 | L16: =K16/K$6 -> 0.0020588235 | M16: =((45/3000)*12) -> 0.18 | N16: =M16/M$6 -> 0.001978022 | P16: =O16/O$6 -> 0 | R16: =Q16/Q$6 -> 0 | T16: =S16/S$6 -> 0 | W16: =V16/V$6 -> 0 | Y16: =X16/X$6 -> 0 | AA16: =Z16/Z$6 -> 0 | AC16: =AB16/AB$6 -> 0 | AE16: =AD16/AD$6 -> 0 | AH16: =AG16/AG$6 -> 0 | AJ16: =AI16/AI$6 -> 0 | AM16: =AL16/AL$6 -> 0 | AO16: =AN16/AN$6 -> 0 | AR16: =AQ16/AQ$6 -> 0 | AT16: =AS16/AS$6 -> 0 | AW16: =AV16/AV$6 -> 0 | AY16: =AX16/AX$6 -> 0 | BB16: =BA16/BA$6 -> 0 | BD16: =BC16/BC$6 -> 0 | BG16: =BF16/BF$6 -> 0
B17: ='Pricing Trends'!R23 -> RBD PALM OLEIN (FOREIGN) | C17: ='Pricing Trends'!S23 -> 45547 | D17: ='Pricing Trends'!U23 -> 60.65316 | E17: FALSE | G17: COST OF GOODS SOLD | I17: =SUM(I7:I16) -> 33.952725 | J17: =I17/I6 -> 0.97007785 | K17: =SUM(K7:K16) -> 46.271591 | L17: =K17/K6 -> 0.9072861 | M17: =SUM(M7:M16) -> 92.138182 | N17: =M17/M6 -> 1.0125075 | O17: =SUM(O7:O16) -> 69.669827 | P17: =O17/O6 -> 0.59618051 | Q17: =SUM(Q7:Q16) -> 142.65965 | R17: =Q17/Q6 -> 0.63062191 | S17: =SUM(S7:S16) -> 147.19299 | T17: =S17/S6 -> 0.65066134 | V17: =SUM(V7:V16) -> 13.548819 | W17: =V17/V6 -> 0.67744094 | X17: =SUM(X7:X16) -> 21.504281 | Y17: =X17/X6 -> 0.69368649 | Z17: =SUM(Z7:Z16) -> 31.26408 | AA17: =Z17/Z6 -> 0.63159758 | AB17: =SUM(AB7:AB16) -> 67.97816 | AC17: =AB17/AB6 -> 0.71555958 | AD17: =SUM(AD7:AD16) -> 132.05965 | AE17: =AD17/AD6 -> 0.73366474 | AG17: =SUM(AG7:AG16) -> 286.21764 | AH17: =AG17/AG6 -> 0.6396766 | AI17: =SUM(AI7:AI16) -> 1079.3851 | AJ17: =AI17/AI6 -> 0.67461568 | AL17: =SUM(AL7:AL16) -> 83.851667 | AM17: =AL17/AL6 -> 0.77282642 | AN17: =SUM(AN7:AN16) -> 188.40675 | AO17: =AN17/AN6 -> 0.82998568 | AQ17: =SUM(AQ7:AQ16) -> 376.48517 | AR17: =AQ17/AQ6 -> 0.70246322 | AS17: =SUM(AS7:AS16) -> 1480.9859 | AT17: =AS17/AS6 -> 0.74880844 | AV17: =SUM(AV7:AV16) -> 84.241667 | AW17: =AV17/AV6 -> 0.73253623 | AX17: =SUM(AX7:AX16) -> 161.02441 | AY17: =AX17/AX6 -> 0.67093504 | BA17: =SUM(BA7:BA16) -> 319.92049 | BB17: =BA17/BA6 -> 0.58016308 | BC17: =SUM(BC7:BC16) -> 1229.3293 | BD17: =BC17/BC6 -> 0.57178105 | BF17: =SUM(BF7:BF16) -> 1519.02 | BG17: =BF17/BF6 -> 1.0476
B18: ='Pricing Trends'!R24 -> RBD PALM OLEIN (FOREIGN) | C18: ='Pricing Trends'!S24 -> 45517 | D18: ='Pricing Trends'!U24 -> 60.97 | E18: FALSE | G18: GROSS PROFIT | I18: =I6-I17 -> 1.0472752 | J18: =I18/I6 -> 0.02992215 | K18: =K6-K17 -> 4.7284091 | L18: =K18/K6 -> 0.092713904 | M18: =M6-M17 -> -1.1381818 | N18: =M18/M6 -> -0.012507493 | O18: =O6-O17 -> 47.190463 | P18: =O18/O6 -> 0.40381949 | Q18: =Q6-Q17 -> 83.560926 | R18: =Q18/Q6 -> 0.36937809 | S18: =S6-S17 -> 79.027593 | T18: =S18/S6 -> 0.34933866 | V18: =V6-V17 -> 6.4511812 | W18: =V18/V6 -> 0.32255906 | X18: =X6-X17 -> 9.4957187 | Y18: =X18/X6 -> 0.30631351 | Z18: =Z6-Z17 -> 18.23592 | AA18: =Z18/Z6 -> 0.36840242 | AB18: =AB6-AB17 -> 27.02184 | AC18: =AB18/AB6 -> 0.28444042 | AD18: =AD6-AD17 -> 47.940347 | AE18: =AD18/AD6 -> 0.26633526 | AG18: =AG6-AG17 -> 161.22352 | AH18: =AG18/AG6 -> 0.3603234 | AI18: =AI6-AI17 -> 520.61491 | AJ18: =AI18/AI6 -> 0.32538432 | AL18: =AL6-AL17 -> 24.648333 | AM18: =AL18/AL6 -> 0.22717358 | AN18: =AN6-AN17 -> 38.593251 | AO18: =AN18/AN6 -> 0.17001432 | AQ18: =AQ6-AQ17 -> 159.46483 | AR18: =AQ18/AQ6 -> 0.29753678 | AS18: =AS6-AS17 -> 496.80415 | AT18: =AS18/AS6 -> 0.25119156 | AV18: =AV6-AV17 -> 30.758333 | AW18: =AV18/AV6 -> 0.26746377 | AX18: =AX6-AX17 -> 78.97559 | AY18: =AX18/AX6 -> 0.32906496 | BA18: =BA6-BA17 -> 231.51151 | BB18: =BA18/BA6 -> 0.41983692 | BC18: =BC6-BC17 -> 920.67074 | BD18: =BC18/BC6 -> 0.42821895 | BF18: =BF6-BF17 -> -69.02 | BG18: =BF18/BF6 -> -0.0476
B19: ='Pricing Trends'!R25 -> RBD PALM OLEIN (FOREIGN) | C19: ='Pricing Trends'!S25 -> 45494 | D19: ='Pricing Trends'!U25 -> 60.49687 | E19: FALSE | G19: EXPENSES | I19: =SUM(I20:I35) -> 2.09 | J19: =I19/I6 -> 0.059714286 | K19: =SUM(K20:K35) -> 5.9866153 | L19: =K19/K6 -> 0.11738461 | M19: =SUM(M20:M35) -> 5.15 | N19: =M19/M6 -> 0.056593407 | O19: =SUM(O20:O35) -> 20.963404 | P19: =O19/O6 -> 0.17938861 | Q19: =SUM(Q20:Q35) -> 28.850603 | R19: =Q19/Q6 -> 0.12753306 | S19: =SUM(S20:S35) -> 28.364889 | T19: =S19/S6 -> 0.12538598 | V19: =SUM(V20:V35) -> 4.0005228 | W19: =V19/V6 -> 0.20002614 | X19: =SUM(X20:X35) -> 5.7675381 | Y19: =X19/X6 -> 0.18604962 | Z19: =SUM(Z20:Z35) -> 7.7292301 | AA19: =Z19/Z6 -> 0.15614606 | AB19: =SUM(AB20:AB35) -> 16.05846 | AC19: =AB19/AB6 -> 0.16903642 | AD19: =SUM(AD20:AD35) -> 30.11692 | AE19: =AD19/AD6 -> 0.16731622 | AG19: =SUM(AG20:AG35) -> 76.503082 | AH19: =AG19/AG6 -> 0.17097909 | AI19: =SUM(AI20:AI35) -> 283.69866 | AJ19: =AI19/AI6 -> 0.17731166 | AL19: =SUM(AL20:AL35) -> 20.653813 | AM19: =AL19/AL6 -> 0.19035772 | AN19: =SUM(AN20:AN35) -> 34.606831 | AO19: =AN19/AN6 -> 0.152453 | AQ19: =SUM(AQ20:AQ35) -> 83.785198 | AR19: =AQ19/AQ6 -> 0.15633025 | AS19: =SUM(AS20:AS35) -> 307.4523 | AT19: =AS19/AS6 -> 0.15545245 | AV19: =SUM(AV20:AV35) -> 21.813844 | AW19: =AV19/AV6 -> 0.1896856 | AX19: =SUM(AX20:AX35) -> 40.035286 | AY19: =AX19/AX6 -> 0.16681369 | BA19: =SUM(BA20:BA35) -> 92.866597 | BB19: =BA19/BA6 -> 0.16840988 | BC19: =SUM(BC20:BC35) -> 372.84586 | BD19: =BC19/BC6 -> 0.17341668 | BF19: =SUM(BF20:BF35) -> 140.76145 | BG19: =BF19/BF6 -> 0.097076863
B20: ='Pricing Trends'!R26 -> RBD PALM OLEIN (FOREIGN) | C20: ='Pricing Trends'!S26 -> 45314 | D20: ='Pricing Trends'!U26 -> 57.51356 | E20: FALSE | G20: Production Expenses - Labelling | I20: 0.2 | J20: =I20/I$6 -> 0.0057142857 | K20: 0.2 | L20: =K20/K$6 -> 0.0039215686 | M20: 0.2 | N20: =M20/M$6 -> 0.0021978022 | P20: =O20/O$6 -> 0 | R20: =Q20/Q$6 -> 0 | T20: =S20/S$6 -> 0 | W20: =V20/V$6 -> 0 | Y20: =X20/X$6 -> 0 | AA20: =Z20/Z$6 -> 0 | AC20: =AB20/AB$6 -> 0 | AE20: =AD20/AD$6 -> 0 | AG20: 0.2 | AH20: =AG20/AG$6 -> 0.00044698615 | AJ20: =AI20/AI$6 -> 0 | AM20: =AL20/AL$6 -> 0 | AO20: =AN20/AN$6 -> 0 | AQ20: 0.2 | AR20: =AQ20/AQ$6 -> 0.00037316914 | AT20: =AS20/AS$6 -> 0 | AY20: =AX20/AX$6 -> 0 | BA20: 0.2 | BB20: =BA20/BA$6 -> 0.00036269205 | BD20: =BC20/BC$6 -> 0 | BG20: =BF20/BF$6 -> 0
B21: ='Pricing Trends'!R27 -> RBD PALM OLEIN (FOREIGN) | C21: ='Pricing Trends'!S27 -> 45248 | D21: ='Pricing Trends'!U27 -> 61.45051 | E21: FALSE | G21: Production Expenses - Packaging | I21: =0.4*0.35 -> 0.14 | J21: =I21/I$6 -> 0.004 | K21: =0.4*0.5 -> 0.2 | L21: =K21/K$6 -> 0.0039215686 | M21: 0.4 | N21: =M21/M$6 -> 0.0043956044 | O21: 0.4 | P21: =O21/O$6 -> 0.0034228907 | Q21: =M21*2 -> 0.8 | R21: =Q21/Q$6 -> 0.0035363715 | S21: =M21*2 -> 0.8 | T21: =S21/S$6 -> 0.0035363715 | V21: =$M21*0.18 -> 0.072 | W21: =V21/V$6 -> 0.0036 | X21: =$M21*0.3 -> 0.12 | Y21: =X21/X$6 -> 0.0038709677 | Z21: =$M21*0.5 -> 0.2 | AA21: =Z21/Z$6 -> 0.004040404 | AB21: =$M21 -> 0.4 | AC21: =AB21/AB$6 -> 0.0042105263 | AD21: =$M21*2 -> 0.8 | AE21: =AD21/AD$6 -> 0.0044444444 | AG21: =M21*4 -> 1.6 | AH21: =AG21/AG$6 -> 0.0035758892 | AI21: =0.4*15.66*1.1364 -> 7.1184096 | AJ21: =AI21/AI$6 -> 0.004449006 | AL21: 0.4 | AM21: =AL21/AL$6 -> 0.0036866359 | AN21: =AL21*2 -> 0.8 | AO21: =AN21/AN$6 -> 0.0035242291 | AQ21: =AL21*4 -> 1.6 | AR21: =AQ21/AQ$6 -> 0.0029853531 | AS21: =AN21*4 -> 3.2 | AT21: =AS21/AS$6 -> 0.0016179675 | AV21: 0.4 | AW21: =AV21/AV$6 -> 0.0034782609 | AX21: =AV21*2 -> 0.8 | AY21: =AX21/AX$6 -> 0.0033333333 | BA21: =AV21*4 -> 1.6 | BB21: =BA21/BA$6 -> 0.0029015364 | BC21: =M21*15.66*1.1364 -> 7.1184096 | BD21: =BC21/BC$6 -> 0.0033108882 | BF21: =AI21 -> 7.1184096 | BG21: =BF21/BF$6 -> 0.004909248
B22: ='Pricing Trends'!R28 -> RBD PALM OLEIN (FOREIGN) | C22: ='Pricing Trends'!S28 -> 45244 | D22: ='Pricing Trends'!U28 -> 63.35264 | E22: FALSE | G22: Distributors Discount
B23: ='Pricing Trends'!R29 -> RBD PALM OLEIN (FOREIGN) | C23: ='Pricing Trends'!S29 -> 45234 | D23: ='Pricing Trends'!U29 -> 56.63575 | E23: FALSE | G23: Sales Expenses - Internal
B24: ='Pricing Trends'!R30 -> 0 | C24: ='Pricing Trends'!S30 -> 0 | D24: ='Pricing Trends'!U30 -> 0 | E24: FALSE | G24: Sales Expenses - External | J24: =I24/I$6 -> 0 | K24: 1 | N24: =M24/M$6 -> 0 | O24: 1 | Q24: 1 | S24: 1 | V24: 1 | X24: 1 | AB24: 1 | AD24: 1 | AG24: 1 | AI24: 1 | AL24: 1 | AM24: =AL24/AL$6 -> 0.0092165899 | AN24: 1 | AQ24: 1 | AS24: 1 | AV24: 1 | AW24: =AV24/AV$6 -> 0.0086956522 | AX24: 1 | BA24: 1 | BC24: 1 | BF24: 1
B25: ='Pricing Trends'!R31 -> RBD CANOLA OIL | C25: ='Pricing Trends'!S31 -> 45269 | D25: ='Pricing Trends'!U31 -> 73.180847 | E25: FALSE | G25: Marketing Expenses - Trade Investment
B26: ='Pricing Trends'!R32 -> RBD CANOLA OIL | C26: ='Pricing Trends'!S32 -> 45118 | D26: ='Pricing Trends'!U32 -> 80.463781 | E26: FALSE | G26: Marketing Expenses - Brand Building
B27: ='Pricing Trends'!R33 -> 0 | C27: ='Pricing Trends'!S33 -> 0 | D27: ='Pricing Trends'!U33 -> 0 | E27: FALSE | G27: General and Administrative Expenses | I27: =I6*0.01 -> 0.35 | J27: =I27/I$6 -> 0.01 | K27: =K6*0.01 -> 0.51 | L27: =K27/K$6 -> 0.01 | M27: =M6*0.01 -> 0.91 | N27: =M27/M$6 -> 0.01 | O27: =O6*0.01 -> 1.1686029 | P27: =O27/O$6 -> 0.01 | Q27: =Q6*0.01 -> 2.2622058 | R27: =Q27/Q$6 -> 0.01 | S27: =S6*0.01 -> 2.2622058 | T27: =S27/S$6 -> 0.01 | V27: =V6*0.01 -> 0.2 | W27: =V27/V$6 -> 0.01 | X27: =X6*0.01 -> 0.31 | Y27: =X27/X$6 -> 0.01 | Z27: =Z6*0.01 -> 0.495 | AA27: =Z27/Z$6 -> 0.01 | AB27: =AB6*0.01 -> 0.95 | AC27: =AB27/AB$6 -> 0.01 | AD27: =AD6*0.01 -> 1.8 | AE27: =AD27/AD$6 -> 0.01 | AG27: =AG6*0.01 -> 4.4744116 | AH27: =AG27/AG$6 -> 0.01 | AI27: =AI6*0.01 -> 16 | AJ27: =AI27/AI$6 -> 0.01 | AL27: =AL6*0.01 -> 1.085 | AM27: =AL27/AL$6 -> 0.01 | AN27: =AN6*0.01 -> 2.27 | AO27: =AN27/AN$6 -> 0.01 | AQ27: =AQ6*0.01 -> 5.3595 | AR27: =AQ27/AQ$6 -> 0.01 | AS27: =AS6*0.01 -> 19.7779 | AT27: =AS27/AS$6 -> 0.01 | AV27: =AV6*0.01 -> 1.15 | AW27: =AV27/AV$6 -> 0.01 | AX27: =AX6*0.01 -> 2.4 | AY27: =AX27/AX$6 -> 0.01 | BA27: =BA6*0.01 -> 5.51432 | BB27: =BA27/BA$6 -> 0.01 | BC27: =BC6*0.01 -> 21.5 | BD27: =BC27/BC$6 -> 0.01 | BF27: =BF6*0.01 -> 14.5 | BG27: =BF27/BF$6 -> 0.01
B28: ='Pricing Trends'!R34 -> 0 | C28: ='Pricing Trends'!S34 -> 0 | D28: ='Pricing Trends'!U34 -> 0 | E28: FALSE | G28: Utilities Expenses | I28: =I6*0.01 -> 0.35 | J28: =I28/I$6 -> 0.01 | K28: =K6*0.01 -> 0.51 | L28: =K28/K$6 -> 0.01 | M28: =M6*0.01 -> 0.91 | N28: =M28/M$6 -> 0.01 | O28: =O6*0.01 -> 1.1686029 | P28: =O28/O$6 -> 0.01 | Q28: =Q6*0.01 -> 2.2622058 | R28: =Q28/Q$6 -> 0.01 | S28: =S6*0.01 -> 2.2622058 | T28: =S28/S$6 -> 0.01 | V28: =V6*0.01 -> 0.2 | W28: =V28/V$6 -> 0.01 | X28: =X6*0.01 -> 0.31 | Y28: =X28/X$6 -> 0.01 | Z28: =Z6*0.01 -> 0.495 | AA28: =Z28/Z$6 -> 0.01 | AB28: =AB6*0.01 -> 0.95 | AC28: =AB28/AB$6 -> 0.01 | AD28: =AD6*0.01 -> 1.8 | AE28: =AD28/AD$6 -> 0.01 | AG28: =AG6*0.01 -> 4.4744116 | AH28: =AG28/AG$6 -> 0.01 | AI28: =AI6*0.01 -> 16 | AJ28: =AI28/AI$6 -> 0.01 | AL28: =AL6*0.01 -> 1.085 | AM28: =AL28/AL$6 -> 0.01 | AN28: =AN6*0.01 -> 2.27 | AO28: =AN28/AN$6 -> 0.01 | AQ28: =AQ6*0.01 -> 5.3595 | AR28: =AQ28/AQ$6 -> 0.01 | AS28: =AS6*0.01 -> 19.7779 | AT28: =AS28/AS$6 -> 0.01 | AV28: =AV6*0.01 -> 1.15 | AW28: =AV28/AV$6 -> 0.01 | AX28: =AX6*0.01 -> 2.4 | AY28: =AX28/AX$6 -> 0.01 | BA28: =BA6*0.01 -> 5.51432 | BB28: =BA28/BA$6 -> 0.01 | BC28: =BC6*0.01 -> 21.5 | BD28: =BC28/BC$6 -> 0.01 | BF28: =BF6*0.01 -> 14.5 | BG28: =BF28/BF$6 -> 0.01
B29: ='Pricing Trends'!R35 -> 0 | C29: ='Pricing Trends'!S35 -> 0 | D29: ='Pricing Trends'!U35 -> 0 | E29: FALSE | G29: Logistics Expenses - Delivery | I29: =I6*0.03 -> 1.05 | J29: =I29/I$6 -> 0.03 | K29: =K6*0.03 -> 1.53 | L29: =K29/K$6 -> 0.03 | M29: =M6*0.03 -> 2.73 | N29: =M29/M$6 -> 0.03 | O29: =O6*0.03 -> 3.5058087 | P29: =O29/O$6 -> 0.03 | Q29: =Q6*0.03 -> 6.7866174 | R29: =Q29/Q$6 -> 0.03 | S29: =S6*0.03 -> 6.7866174 | T29: =S29/S$6 -> 0.03 | V29: =V6*0.03 -> 0.6 | W29: =V29/V$6 -> 0.03 | X29: =X6*0.03 -> 0.93 | Y29: =X29/X$6 -> 0.03 | Z29: =Z6*0.03 -> 1.485 | AA29: =Z29/Z$6 -> 0.03 | AB29: =AB6*0.03 -> 2.85 | AC29: =AB29/AB$6 -> 0.03 | AD29: =AD6*0.03 -> 5.4 | AE29: =AD29/AD$6 -> 0.03 | AG29: =AG6*0.03 -> 13.423235 | AH29: =AG29/AG$6 -> 0.03 | AI29: =AI6*0.03 -> 48 | AJ29: =AI29/AI$6 -> 0.03 | AL29: =AL6*0.03 -> 3.255 | AM29: =AL29/AL$6 -> 0.03 | AN29: =AN6*0.03 -> 6.81 | AO29: =AN29/AN$6 -> 0.03 | AQ29: =AQ6*0.03 -> 16.0785 | AR29: =AQ29/AQ$6 -> 0.03 | AS29: =AS6*0.03 -> 59.3337 | AT29: =AS29/AS$6 -> 0.03 | AV29: =AV6*0.03 -> 3.45 | AW29: =AV29/AV$6 -> 0.03 | AX29: =AX6*0.03 -> 7.2 | AY29: =AX29/AX$6 -> 0.03 | BA29: =BA6*0.03 -> 16.54296 | BB29: =BA29/BA$6 -> 0.03 | BC29: =BC6*0.03 -> 64.5 | BD29: =BC29/BC$6 -> 0.03 | BF29: =BF6*0.03 -> 43.5 | BG29: =BF29/BF$6 -> 0.03
B30: ='Pricing Trends'!R36 -> 0 | C30: ='Pricing Trends'!S36 -> 0 | D30: ='Pricing Trends'!U36 -> 0 | E30: FALSE | G30: Logistics Expenses - Pick Up | H30: l | I30: =M30*0.35 -> 0 | J30: =I30/I$6 -> 0 | K30: =M30*0.5 -> 0 | L30: =K30/K$6 -> 0 | M30: =((IFERROR(VLOOKUP(I2&$G$11,Validation!$E:$F,2,FALSE),0)*'Pick Up Cost'!$C$16)+(IFERROR(VLOOKUP(I2&$G$8,Validation!$E:$F,2,FALSE),0)*'Pick Up Cost'!$C$16)) -> 0 | N30: =M30/M$6 -> 0 | O30: =((IFERROR(VLOOKUP(I2&$G$11,Validation!$E:$F,2,FALSE),0)*'Pick Up Cost'!$C$16)+(IFERROR(VLOOKUP(I2&$G$8,Validation!$E:$F,2,FALSE),0)*'Pick Up Cost'!$C$16)) -> 0 | P30: =O30/O$6 -> 0 | Q30: =M30*2 -> 0 | R30: =Q30/Q$6 -> 0 | S30: =M30*2 -> 0 | T30: =S30/S$6 -> 0 | V30: =$AB30*0.18 -> 0 | W30: =V30/V$6 -> 0 | X30: =$AB30*0.3 -> 0 | Y30: =X30/X$6 -> 0 | Z30: =$AB30*0.5 -> 0 | AA30: =Z30/Z$6 -> 0 | AB30: =((IFERROR(VLOOKUP(V2&$G$11,Validation!$E:$F,2,FALSE),0)*'Pick Up Cost'!$C$16)+(IFERROR(VLOOKUP(V2&$G$8,Validation!$E:$F,2,FALSE),0)*'Pick Up Cost'!$C$16)) -> 0 | AC30: =AB30/AB$6 -> 0 | AD30: =$AB30*2 -> 0 | AE30: =AD30/AD$6 -> 0 | AG30: =((IFERROR(VLOOKUP(AG2&$G$11,Validation!$E:$F,2,FALSE),0)*'Pick Up Cost'!$C$16)+(IFERROR(VLOOKUP(AG2&$G$8,Validation!$E:$F,2,FALSE),0)*'Pick Up Cost'!$C$16))*AH5 -> 0 | AH30: =AG30/AG$6 -> 0 | AI30: =((IFERROR(VLOOKUP(AG2&$G$11,Validation!$E:$F,2,FALSE),0)*'Pick Up Cost'!$C$16)+(IFERROR(VLOOKUP(AG2&$G$8,Validation!$E:$F,2,FALSE),0)*'Pick Up Cost'!$C$16))*15.66*1.1364 -> 0 | AJ30: =AI30/AI$6 -> 0 | AL30: =((IFERROR(VLOOKUP(AL2&$G$11,Validation!$E:$F,2,FALSE),0)*'Pick Up Cost'!$C$16)+(IFERROR(VLOOKUP(AL2&$G$8,Validation!$E:$F,2,FALSE),0)*'Pick Up Cost'!$C$16)) -> 0 | AM30: =AL30/AL$6 -> 0 | AN30: =AL30*2 -> 0 | AO30: =AN30/AN$6 -> 0 | AQ30: =((IFERROR(VLOOKUP(AQ2&$G$11,Validation!$E:$F,2,FALSE),0)*'Pick Up Cost'!$C$16)+(IFERROR(VLOOKUP(AQ2&$G$8,Validation!$E:$F,2,FALSE),0)*'Pick Up Cost'!$C$16))*AR5 -> 0 | AR30: =AQ30/AQ$6 -> 0 | AS30: =((IFERROR(VLOOKUP(AQ2&$G$11,Validation!$E:$F,2,FALSE),0)*'Pick Up Cost'!$C$16)+(IFERROR(VLOOKUP(AQ2&$G$8,Validation!$E:$F,2,FALSE),0)*'Pick Up Cost'!$C$16))*AR5*15.66*1.1364 -> 0 | AT30: =AS30/AS$6 -> 0 | AV30: =((IFERROR(VLOOKUP(AV2&$G$11,Validation!$E:$F,2,FALSE),0)*'Pick Up Cost'!$C$16)+(IFERROR(VLOOKUP(AV2&$G$8,Validation!$E:$F,2,FALSE),0)*'Pick Up Cost'!$C$16)) -> 0 | AW30: =AV30/AV$6 -> 0 | AX30: =AV30*2 -> 0 | AY30: =AX30/AX$6 -> 0 | BA30: =((IFERROR(VLOOKUP(I2&$G$11,Validation!$E:$F,2,FALSE),0)*'Pick Up Cost'!$C$16)+(IFERROR(VLOOKUP(I2&$G$8,Validation!$E:$F,2,FALSE),0)*'Pick Up Cost'!$C$16))*BB5 -> 0 | BB30: =BA30/BA$6 -> 0 | BC30: =((IFERROR(VLOOKUP(I2&$G$11,Validation!$E:$F,2,FALSE),0)*'Pick Up Cost'!$C$16)+(IFERROR(VLOOKUP(I2&$G$8,Validation!$E:$F,2,FALSE),0)*'Pick Up Cost'!$C$16))*15.66*1.1364 -> 0 | BD30: =BC30/BC$6 -> 0 | BF30: =((IFERROR(VLOOKUP(BF2&$G$11,Validation!$E:$F,2,FALSE),0)*'Pick Up Cost'!$C$16)+(IFERROR(VLOOKUP(BF2&$G$8,Validation!$E:$F,2,FALSE),0)*'Pick Up Cost'!$C$16))*15.66*1.1364 -> 31.143042 | BG30: =BF30/BF$6 -> 0.02147796
B31: ='Pricing Trends'!R37 -> 0 | C31: ='Pricing Trends'!S37 -> 0 | D31: ='Pricing Trends'!U37 -> 0 | E31: FALSE | G31: Logistics Expenses - THC and Customs | I31: =M31*0.35 -> 0 | J31: =I31/I$6 -> 0 | K31: =M31*0.5 -> 0 | L31: =K31/K$6 -> 0 | N31: =M31/M$6 -> 0 | O31: =((IFERROR(VLOOKUP(I2&$G$7,Validation!$E:$F,2,FALSE),0)*'Shipping Cost'!$E$4)+(IFERROR(VLOOKUP(I2&$G$9,Validation!$E:$F,2,FALSE),0)*'Shipping Cost'!$C$4)+(IFERROR(VLOOKUP(I2&$G$10,Validation!$E:$F,2,FALSE),0)*'Shipping Cost'!$D$4)) -> 5.1584602 | P31: =O31/O$6 -> 0.044142114 | Q31: =M31*2 -> 0 | R31: =Q31/Q$6 -> 0 | S31: =M31*2 -> 0 | T31: =S31/S$6 -> 0 | V31: =$AB31*0.18 -> 0.92852284 | W31: =V31/V$6 -> 0.046426142 | X31: =$AB31*0.3 -> 1.5475381 | Y31: =X31/X$6 -> 0.049920583 | Z31: =$AB31*0.5 -> 2.5792301 | AA31: =Z31/Z$6 -> 0.052105659 | AB31: =((IFERROR(VLOOKUP(V2&$G$7,Validation!$E:$F,2,FALSE),0)*'Shipping Cost'!$E$4)+(IFERROR(VLOOKUP(V2&$G$9,Validation!$E:$F,2,FALSE),0)*'Shipping Cost'!$C$4)+(IFERROR(VLOOKUP(V2&$G$10,Validation!$E:$F,2,FALSE),0)*'Shipping Cost'!$D$4)) -> 5.1584602 | AC31: =AB31/AB$6 -> 0.054299581 | AD31: =$AB31*2 -> 10.31692 | AE31: =AD31/AD$6 -> 0.057316225 | AG31: =((IFERROR(VLOOKUP(AG2&$G$7,Validation!$E:$F,2,FALSE),0)*'Shipping Cost'!$E$4)+(IFERROR(VLOOKUP(AG2&$G$9,Validation!$E:$F,2,FALSE),0)*'Shipping Cost'!$C$4)+(IFERROR(VLOOKUP(AG2&$G$10,Validation!$E:$F,2,FALSE),0)*'Shipping Cost'!$D$4))*AH5 -> 20.633841 | AH31: =AG31/AG$6 -> 0.046115205 | AI31: =((IFERROR(VLOOKUP(AG2&$G$7,Validation!$E:$F,2,FALSE),0)*'Shipping Cost'!$E$4)+(IFERROR(VLOOKUP(AG2&$G$9,Validation!$E:$F,2,FALSE),0)*'Shipping Cost'!$C$4)+(IFERROR(VLOOKUP(AG2&$G$10,Validation!$E:$F,2,FALSE),0)*'Shipping Cost'!$D$4))*15.66*1.1364 -> 91.800082 | AJ31: =AI31/AI$6 -> 0.057375051 | AL31: =((IFERROR(VLOOKUP(AL2&$G$7,Validation!$E:$F,2,FALSE),0)*'Shipping Cost'!$E$4)+(IFERROR(VLOOKUP(AL2&$G$9,Validation!$E:$F,2,FALSE),0)*'Shipping Cost'!$C$4)+(IFERROR(VLOOKUP(AL2&$G$10,Validation!$E:$F,2,FALSE),0)*'Shipping Cost'!$D$4)) -> 5.25592 | AM31: =AL31/AL$6 -> 0.048441659 | AN31: =AL31*2 -> 10.51184 | AO31: =AN31/AN$6 -> 0.046307665 | AQ31: =((IFERROR(VLOOKUP(AQ2&$G$7,Validation!$E:$F,2,FALSE),0)*'Shipping Cost'!$E$4)+(IFERROR(VLOOKUP(AQ2&$G$9,Validation!$E:$F,2,FALSE),0)*'Shipping Cost'!$C$4)+(IFERROR(VLOOKUP(AQ2&$G$10,Validation!$E:$F,2,FALSE),0)*'Shipping Cost'!$D$4))*AR5 -> 21.02368 | AR31: =AQ31/AQ$6 -> 0.039226943 | AS31: =((IFERROR(VLOOKUP(I2&$G$7,Validation!$E:$F,2,FALSE),0)*'Shipping Cost'!$E$4)+(IFERROR(VLOOKUP(I2&$G$9,Validation!$E:$F,2,FALSE),0)*'Shipping Cost'!$C$4)+(IFERROR(VLOOKUP(I2&$G$10,Validation!$E:$F,2,FALSE),0)*'Shipping Cost'!$D$4))*15.66*1.1364 -> 91.800082 | AT31: =AS31/AS$6 -> 0.046415485 | AV31: =((IFERROR(VLOOKUP(AV2&$G$7,Validation!$E:$F,2,FALSE),0)*'Shipping Cost'!$E$4)+(IFERROR(VLOOKUP(AV2&$G$9,Validation!$E:$F,2,FALSE),0)*'Shipping Cost'!$C$4)+(IFERROR(VLOOKUP(AV2&$G$10,Validation!$E:$F,2,FALSE),0)*'Shipping Cost'!$D$4)) -> 5.2868079 | AW31: =AV31/AV$6 -> 0.045972243 | AX31: =AV31*2 -> 10.573616 | AY31: =AX31/AX$6 -> 0.044056733 | BA31: =((IFERROR(VLOOKUP(BA2&$G$7,Validation!$E:$F,2,FALSE),0)*'Shipping Cost'!$E$4)+(IFERROR(VLOOKUP(BA2&$G$9,Validation!$E:$F,2,FALSE),0)*'Shipping Cost'!$C$4)+(IFERROR(VLOOKUP(BA2&$G$10,Validation!$E:$F,2,FALSE),0)*'Shipping Cost'!$D$4))*BB5 -> 21.147232 | BB31: =BA31/BA$6 -> 0.038349664 | BC31: =((IFERROR(VLOOKUP(BA2&$G$7,Validation!$E:$F,2,FALSE),0)*'Shipping Cost'!$E$4)+(IFERROR(VLOOKUP(BA2&$G$9,Validation!$E:$F,2,FALSE),0)*'Shipping Cost'!$C$4)+(IFERROR(VLOOKUP(BA2&$G$10,Validation!$E:$F,2,FALSE),0)*'Shipping Cost'!$D$4))*15.66*1.1364 -> 94.084161 | BD31: =BC31/BC$6 -> 0.043760075 | BF31: =((IFERROR(VLOOKUP(BF2&$G$7,Validation!$E:$F,2,FALSE),0)*'Shipping Cost'!$E$4)+(IFERROR(VLOOKUP(BF2&$G$9,Validation!$E:$F,2,FALSE),0)*'Shipping Cost'!$C$4)+(IFERROR(VLOOKUP(BF2&$G$10,Validation!$E:$F,2,FALSE),0)*'Shipping Cost'!$D$4)) -> 0 | BG31: =BF31/BF$6 -> 0
B32: ='Pricing Trends'!R38 -> RBD COCONUT OIL | C32: ='Pricing Trends'!S38 -> 45468 | D32: ='Pricing Trends'!U38 -> 85.357269 | E32: FALSE | G32: Dollar Fluctuation Allowance Pricing | J32: =I32/I$6 -> 0 | K32: =K6*0.01 -> 0.51 | L32: =K32/K$6 -> 0.01 | N32: =M32/M$6 -> 0 | O32: =O6*0.01 -> 1.1686029 | P32: =O32/O$6 -> 0.01 | Q32: =Q6*0.01 -> 2.2622058 | R32: =Q32/Q$6 -> 0.01 | S32: =S6*0.01 -> 2.2622058 | T32: =S32/S$6 -> 0.01 | V32: =V6*0.01 -> 0.2 | W32: =V32/V$6 -> 0.01 | X32: =X6*0.01 -> 0.31 | Y32: =X32/X$6 -> 0.01 | Z32: =Z6*0.01 -> 0.495 | AA32: =Z32/Z$6 -> 0.01 | AB32: =AB6*0.01 -> 0.95 | AC32: =AB32/AB$6 -> 0.01 | AD32: =AD6*0.01 -> 1.8 | AE32: =AD32/AD$6 -> 0.01 | AG32: =AG6*0.01 -> 4.4744116 | AH32: =AG32/AG$6 -> 0.01 | AI32: =AI6*0.01 -> 16 | AJ32: =AI32/AI$6 -> 0.01 | AL32: =AL10*0.05 -> 3.762 | AM32: =AL32/AL$6 -> 0.034672811 | AN32: =AN6*0.01 -> 2.27 | AO32: =AN32/AN$6 -> 0.01 | AQ32: =AQ6*0.01 -> 5.3595 | AR32: =AQ32/AQ$6 -> 0.01 | AS32: =AS6*0.01 -> 19.7779 | AT32: =AS32/AS$6 -> 0.01 | AV32: =AV7*0.05 -> 3.7815 | AW32: =AV32/AV$6 -> 0.032882609 | AX32: =AX6*0.01 -> 2.4 | AY32: =AX32/AX$6 -> 0.01 | BA32: =BA6*0.01 -> 5.51432 | BB32: =BA32/BA$6 -> 0.01 | BC32: =BC6*0.01 -> 21.5 | BD32: =BC32/BC$6 -> 0.01 | BF32: =BF6*0.01 -> 14.5 | BG32: =BF32/BF$6 -> 0.01
B33: ='Pricing Trends'!R39 -> 0 | C33: ='Pricing Trends'!S39 -> 0 | D33: ='Pricing Trends'!U39 -> 0 | E33: FALSE | G33: Cost of Money | J33: =I33/I$6 -> 0 | K33: =K6*0.01 -> 0.51 | L33: =K33/K$6 -> 0.01 | N33: =M33/M$6 -> 0 | O33: =O6*0.01 -> 1.1686029 | P33: =O33/O$6 -> 0.01 | Q33: =Q6*0.01 -> 2.2622058 | R33: =Q33/Q$6 -> 0.01 | S33: =S6*0.01 -> 2.2622058 | T33: =S33/S$6 -> 0.01 | V33: =V6*0.01 -> 0.2 | W33: =V33/V$6 -> 0.01 | X33: =X6*0.01 -> 0.31 | Y33: =X33/X$6 -> 0.01 | Z33: =Z6*0.01 -> 0.495 | AA33: =Z33/Z$6 -> 0.01 | AB33: =AB6*0.01 -> 0.95 | AC33: =AB33/AB$6 -> 0.01 | AD33: =AD6*0.01 -> 1.8 | AE33: =AD33/AD$6 -> 0.01 | AG33: =AG6*0.01 -> 4.4744116 | AH33: =AG33/AG$6 -> 0.01 | AI33: =AI6*0.01 -> 16 | AJ33: =AI33/AI$6 -> 0.01 | AL33: =AL6*0.01 -> 1.085 | AM33: =AL33/AL$6 -> 0.01 | AN33: =AN6*0.01 -> 2.27 | AO33: =AN33/AN$6 -> 0.01 | AQ33: =AQ6*0.01 -> 5.3595 | AR33: =AQ33/AQ$6 -> 0.01 | AS33: =AS6*0.01 -> 19.7779 | AT33: =AS33/AS$6 -> 0.01 | AV33: =AV6*0.01 -> 1.15 | AW33: =AV33/AV$6 -> 0.01 | AX33: =AX6*0.01 -> 2.4 | AY33: =AX33/AX$6 -> 0.01 | BA33: =BA6*0.01 -> 5.51432 | BB33: =BA33/BA$6 -> 0.01 | BC33: =BC6*0.01 -> 21.5 | BD33: =BC33/BC$6 -> 0.01 | BF33: =BF6*0.01 -> 14.5 | BG33: =BF33/BF$6 -> 0.01
B34: ='Pricing Trends'!R40 -> RBD CANOLA OIL | C34: ='Pricing Trends'!S40 -> 0 | D34: ='Pricing Trends'!U40 -> 83.220041 | E34: TRUE | G34: Value Added Tax | J34: =I34/I$6 -> 0 | K34: =((K6/1.12)*0.12)-((K17/1.12)*0.12) -> 0.50661526 | L34: =K34/K$6 -> 0.0099336325 | N34: =M34/M$6 -> 0 | O34: =((O6/1.12)*0.12)-((O17/1.12)*0.12) -> 5.0561211 | P34: =O34/O$6 -> 0.043266374 | Q34: =((Q6/1.12)*0.12)-((Q17/1.12)*0.12) -> 8.9529564 | R34: =Q34/Q$6 -> 0.039576224 | S34: =((S6/1.12)*0.12)-((S17/1.12)*0.12) -> 8.4672421 | T34: =S34/S$6 -> 0.037429142 | V34: =V6*0.02 -> 0.4 | W34: =V34/V$6 -> 0.02 | X34: =X6*0.02 -> 0.62 | Y34: =X34/X$6 -> 0.02 | Z34: =Z6*0.02 -> 0.99 | AA34: =Z34/Z$6 -> 0.02 | AB34: =AB6*0.02 -> 1.9 | AC34: =AB34/AB$6 -> 0.02 | AD34: =AD6*0.02 -> 3.6 | AE34: =AD34/AD$6 -> 0.02 | AG34: =((AG6/1.12)*0.12)-((AG17/1.12)*0.12) -> 17.273949 | AH34: =AG34/AG$6 -> 0.038606079 | AI34: =((AI6/1.12)*0.12)-((AI17/1.12)*0.12) -> 55.780169 | AJ34: =AI34/AI$6 -> 0.034862606 | AL34: =((AL6/1.12)*0.12)-((AL17/1.12)*0.12) -> 2.6408929 | AM34: =AL34/AL$6 -> 0.024340026 | AN34: =((AN6/1.12)*0.12)-((AN17/1.12)*0.12) -> 4.1349912 | AO34: =AN34/AN$6 -> 0.01821582 | AQ34: =((AQ6/1.12)*0.12)-((AQ17/1.12)*0.12) -> 17.085518 | AR34: =AQ34/AQ$6 -> 0.03187894 | AS34: =((AS6/1.12)*0.12)-((AS17/1.12)*0.12) -> 53.229016 | AT34: =AS34/AS$6 -> 0.026913381 | AV34: =((AV6/1.12)*0.12)-((AV17/1.12)*0.12) -> 3.2955357 | AW34: =AV34/AV$6 -> 0.028656832 | AX34: =((AX6/1.12)*0.12)-((AX17/1.12)*0.12) -> 8.4616703 | AY34: =AX34/AX$6 -> 0.03525696 | BA34: =((BA6/1.12)*0.12)-((BA17/1.12)*0.12) -> 24.804805 | BB34: =BA34/BA$6 -> 0.044982527 | BC34: =((BC6/1.12)*0.12)-((BC17/1.12)*0.12) -> 98.643293 | BD34: =BC34/BC$6 -> 0.045880602 | BG34: =BF34/BF$6 -> 0
B35: ='Pricing Trends'!R41 -> RBD SOYA BEAN OIL | C35: ='Pricing Trends'!S41 -> 0 | D35: ='Pricing Trends'!U41 -> 81.666042 | E35: TRUE | G35: Income Tax | J35: =I35/I$6 -> 0 | K35: =K6*0.01 -> 0.51 | L35: =K35/K$6 -> 0.01 | N35: =M35/M$6 -> 0 | O35: =O6*0.01 -> 1.1686029 | P35: =O35/O$6 -> 0.01 | Q35: =Q6*0.01 -> 2.2622058 | R35: =Q35/Q$6 -> 0.01 | S35: =S6*0.01 -> 2.2622058 | T35: =S35/S$6 -> 0.01 | V35: =V6*0.01 -> 0.2 | W35: =V35/V$6 -> 0.01 | X35: =X6*0.01 -> 0.31 | Y35: =X35/X$6 -> 0.01 | Z35: =Z6*0.01 -> 0.495 | AA35: =Z35/Z$6 -> 0.01 | AB35: =AB6*0.01 -> 0.95 | AC35: =AB35/AB$6 -> 0.01 | AD35: =AD6*0.01 -> 1.8 | AE35: =AD35/AD$6 -> 0.01 | AG35: =AG6*0.01 -> 4.4744116 | AH35: =AG35/AG$6 -> 0.01 | AI35: =AI6*0.01 -> 16 | AJ35: =AI35/AI$6 -> 0.01 | AL35: =AL6*0.01 -> 1.085 | AM35: =AL35/AL$6 -> 0.01 | AN35: =AN6*0.01 -> 2.27 | AO35: =AN35/AN$6 -> 0.01 | AQ35: =AQ6*0.01 -> 5.3595 | AR35: =AQ35/AQ$6 -> 0.01 | AS35: =AS6*0.01 -> 19.7779 | AT35: =AS35/AS$6 -> 0.01 | AV35: =AV6*0.01 -> 1.15 | AW35: =AV35/AV$6 -> 0.01 | AX35: =AX6*0.01 -> 2.4 | AY35: =AX35/AX$6 -> 0.01 | BA35: =BA6*0.01 -> 5.51432 | BB35: =BA35/BA$6 -> 0.01 | BC35: =BC6*0.01 -> 21.5 | BD35: =BC35/BC$6 -> 0.01 | BG35: =BF35/BF$6 -> 0
B36: ='Pricing Trends'!R42 -> 0 | C36: ='Pricing Trends'!S42 -> 0 | D36: ='Pricing Trends'!U42 -> 0 | E36: FALSE | G36: NET PROFIT | I36: =I18-I19 -> -1.0427248 | J36: =I36/I6 -> -0.029792136 | K36: =K18-K19 -> -1.2582062 | L36: =K36/K6 -> -0.024670709 | M36: =M18-M19 -> -6.2881818 | N36: =M36/M6 -> -0.069100899 | O36: =O18-O19 -> 26.227059 | P36: =O36/O6 -> 0.22443089 | Q36: =Q18-Q19 -> 54.710324 | R36: =Q36/Q6 -> 0.24184503 | S36: =S18-S19 -> 50.662705 | T36: =S36/S6 -> 0.22395268 | V36: =V18-V19 -> 2.4506584 | W36: =V36/V6 -> 0.12253292 | X36: =X18-X19 -> 3.7281806 | Y36: =X36/X6 -> 0.12026389 | Z36: =Z18-Z19 -> 10.50669 | AA36: =Z36/Z6 -> 0.21225636 | AB36: =AB18-AB19 -> 10.96338 | AC36: =AB36/AB6 -> 0.115404 | AD36: =AD18-AD19 -> 17.823426 | AE36: =AD36/AD6 -> 0.099019035 | AG36: =AG18-AG19 -> 84.720437 | AH36: =AG36/AG6 -> 0.18934431 | AI36: =AI18-AI19 -> 236.91625 | AJ36: =AI36/AI6 -> 0.14807266 | AL36: =AL18-AL19 -> 3.9945205 | AM36: =AL36/AL6 -> 0.036815857 | AN36: =AN18-AN19 -> 3.9864197 | AO36: =AN36/AN6 -> 0.01756132 | AQ36: =AQ18-AQ19 -> 75.679637 | AR36: =AQ36/AQ6 -> 0.14120653 | AS36: =AS18-AS19 -> 189.35185 | AT36: =AS36/AS6 -> 0.095739108 | AV36: =AV18-AV19 -> 8.9444897 | AW36: =AV36/AV6 -> 0.077778171 | AX36: =AX18-AX19 -> 38.940303 | AY36: =AX36/AX6 -> 0.16225126 | BA36: =BA18-BA19 -> 138.64492 | BB36: =BA36/BA6 -> 0.25142704 | BC36: =BC18-BC19 -> 547.82487 | BD36: =BC36/BC6 -> 0.25480227 | BF36: =BF18-BF19 -> -209.78145 | BG36: =BF36/BF6 -> -0.14467686
B37: ='Pricing Trends'!R43 -> RBD PALM OLEIN (FOREIGN) | C37: ='Pricing Trends'!S43 -> 0 | D37: ='Pricing Trends'!U43 -> 64.843399 | E37: FALSE
B38: ='Pricing Trends'!R44 -> 0 | C38: ='Pricing Trends'!S44 -> 0 | D38: ='Pricing Trends'!U44 -> 0 | E38: FALSE
B39: ='Pricing Trends'!R45 -> RBD PALM OLEIN (FOREIGN) | C39: ='Pricing Trends'!S45 -> 0 | D39: ='Pricing Trends'!U45 -> 82.366515 | E39: FALSE
B40: ='Pricing Trends'!R46 -> RBD PALM OLEIN (FOREIGN) | C40: ='Pricing Trends'!S46 -> 0 | D40: ='Pricing Trends'!U46 -> 74.65686 | E40: FALSE
B41: ='Pricing Trends'!R47 -> 0 | C41: ='Pricing Trends'!S47 -> 0 | D41: ='Pricing Trends'!U47 -> 0 | E41: FALSE
B42: ='Pricing Trends'!R48 -> 0 | C42: ='Pricing Trends'!S48 -> 0 | D42: ='Pricing Trends'!U48 -> 0 | E42: FALSE
B43: ='Pricing Trends'!R49 -> 0 | C43: ='Pricing Trends'!S49 -> 0 | D43: ='Pricing Trends'!U49 -> 0 | E43: FALSE
B44: ='Pricing Trends'!R50 -> 0 | C44: ='Pricing Trends'!S50 -> 0 | D44: ='Pricing Trends'!U50 -> 0 | E44: FALSE
B45: ='Pricing Trends'!R51 -> 0 | C45: ='Pricing Trends'!S51 -> 0 | D45: ='Pricing Trends'!U51 -> 0 | E45: FALSE
B46: ='Pricing Trends'!R52 -> 0 | C46: ='Pricing Trends'!S52 -> 0 | D46: ='Pricing Trends'!U52 -> 0 | E46: FALSE
B47: ='Pricing Trends'!R53 -> 0 | C47: ='Pricing Trends'!S53 -> 0 | D47: ='Pricing Trends'!U53 -> 0 | E47: FALSE
B48: ='Pricing Trends'!R54 -> 0 | C48: ='Pricing Trends'!S54 -> 0 | D48: ='Pricing Trends'!U54 -> 0 | E48: FALSE
B49: ='Pricing Trends'!R55 -> 0 | C49: ='Pricing Trends'!S55 -> 0 | D49: ='Pricing Trends'!U55 -> 0 | E49: FALSE

Sheet Profitability - New
G1: NOTE: THAT THE DIFFERENCE OF DECLARED VAT IMPORTATION IS 2-5% ONLY | U1: PET | AF1: SUP | AK1: PPR | AL1: 128.5 | AM1: =(AL6-AL1)/AL1 -> 0 | AN1: 236.17 | AO1: =(AN6-AN1)/AN1 -> 0 | AP1: CNE | AQ1: 535.95 | AR1: =(AQ6-AQ1)/AQ1 -> 0 | AU1: CNL | AZ1: SYA | BE1: SYP | BH1: VEG
B2: OIL COSTING | G2: PROFITABILITY | I2: PALMF.100 | V2: PALMF.100 | AG2: PALMF.100 | AL2: CANF.82 | AQ2: CAN.100 | AV2: SOY.100 | BA2: SOY.100 | BF2: VG100
I3: PALM OIL PET | V3: PALM OIL SUP | AG3: PALM | AL3: CANOLEIN | AQ3: CANOLA | AV3: SOYA | BA3: SOYA | BF3: VEGE
G5: DESCRIPTION | I5: 350ML | J5: 36 | K5: 500ML | L5: 24 | M5: 1LSWAK | N5: 12 | O5: 1LMZL | P5: 12 | Q5: 2LNUTRI | R5: 6 | S5: 2LMZL | T5: 6 | V5: 180ML | W5: 48 | X5: 300ML | Y5: 36 | Z5: 500ML | AA5: 24 | AB5: 1LITER | AC5: 12 | AD5: 2LITERS | AE5: 6 | AG5: 4LITER | AH5: 4 | AI5: 17KG | AJ5: 1 | AL5: 1LITER | AM5: 12 | AN5: 2LITER | AO5: 6 | AQ5: 4LITER | AR5: 4 | AS5: 17KG | AT5: 1 | AV5: 1LITER | AW5: 12 | AX5: 2LITER | AY5: 6 | BA5: 4LITER | BB5: 4 | BC5: 17KG | BD5: 1 | BF5: 17KG | BG5: 1
B6: Description | C6: Date | D6: Price | E6: isUsed | G6: SALES | I6: 43.088601 | J6: =I6/I6 -> 1 | K6: 60.455145 | L6: =K6/K6 -> 1 | M6: 116.86029 | N6: =M6/M6 -> 1 | O6: 116.86029 | P6: =O6/O6 -> 1 | Q6: 226.22058 | R6: =Q6/Q6 -> 1 | S6: 226.22058 | T6: =S6/S6 -> 1 | U6: =AQ6/4 -> 133.9875 | V6: =AB6*0.18+2 -> 22.448052 | W6: =V6/V6 -> 1 | X6: =AB6*0.3+2 -> 36.080087 | Y6: =X6/X6 -> 1 | Z6: =AB6*0.5+2 -> 58.800145 | AA6: =Z6/Z6 -> 1 | AB6: 113.60029 | AC6: =AB6/AB6 -> 1 | AD6: 222.51625 | AE6: =AD6/AD6 -> 1 | AG6: 447.44116 | AH6: =AG6/AG6 -> 1 | AI6: 1600 | AJ6: =AI6/AI6 -> 1 | AL6: 128.5 | AM6: =AL6/AL6 -> 1 | AN6: 236.17 | AO6: =AN6/AN6 -> 1 | AQ6: 535.95 | AR6: =AQ6/AQ6 -> 1 | AS6: 1977.79 | AT6: =AS6/AS6 -> 1 | AV6: 144.608 | AW6: =AV6/AV6 -> 1 | AX6: 278.216 | AY6: =AX6/AX6 -> 1 | BA6: 551.432 | BB6: =BA6/BA6 -> 1 | BC6: 2150 | BD6: =BC6/BC6 -> 1 | BF6: 1900 | BG6: =BF6/BF6 -> 1
B7: ='Pricing Trends'!R13 -> RBD SOYA BEAN OIL | C7: ='Pricing Trends'!S13 -> 45314 | D7: ='Pricing Trends'!U13 -> 69.078872 | E7: TRUE | G7: RBD SOYA BEAN OIL | I7: =IFERROR(VLOOKUP($I$2&$G7,Validation!$E:$O,4,FALSE),0) -> 0 | J7: =I7/I$6 -> 0 | K7: =IFERROR(VLOOKUP($I$2&$G7,Validation!$E:$O,5,FALSE),0) -> 0 | L7: =K7/K$6 -> 0 | M7: =IFERROR(VLOOKUP($I$2&$G7,Validation!$E:$O,6,FALSE),0) -> 0 | N7: =M7/M$6 -> 0 | O7: =IFERROR(VLOOKUP($I$2&$G7,Validation!$E:$O,6,FALSE),0) -> 0 | P7: =O7/O$6 -> 0 | Q7: =IFERROR(VLOOKUP($I$2&$G7,Validation!$E:$O,7,FALSE),0) -> 0 | R7: =Q7/Q$6 -> 0 | S7: =IFERROR(VLOOKUP($I$2&$G7,Validation!$E:$O,7,FALSE),0) -> 0 | T7: =S7/S$6 -> 0 | V7: =IFERROR(VLOOKUP($V$2&$G7,Validation!$E:$O,9,FALSE),0) -> 0 | W7: =V7/V$6 -> 0 | X7: =IFERROR(VLOOKUP($V$2&$G7,Validation!$E:$O,10,FALSE),0) -> 0 | Y7: =X7/X$6 -> 0 | Z7: =IFERROR(VLOOKUP($V$2&$G7,Validation!$E:$O,5,FALSE),0) -> 0 | AA7: =Z7/Z$6 -> 0 | AB7: =IFERROR(VLOOKUP($V$2&$G7,Validation!$E:$O,6,FALSE),0) -> 0 | AC7: =AB7/AB$6 -> 0 | AD7: =IFERROR(VLOOKUP($V$2&$G7,Validation!$E:$O,7,FALSE),0) -> 0 | AE7: =AD7/AD$6 -> 0 | AG7: =IFERROR(VLOOKUP($AG$2&$G7,Validation!E:O,8,FALSE),0) -> 0 | AH7: =AG7/AG$6 -> 0 | AI7: =IFERROR(VLOOKUP($AG$2&$G7,Validation!E:O,11,FALSE),0) -> 0 | AJ7: =AI7/AI$6 -> 0 | AL7: =IFERROR(VLOOKUP($AL$2&$G7,Validation!$E:$O,6,FALSE),0) -> 0 | AM7: =AL7/AL$6 -> 0 | AN7: =IFERROR(VLOOKUP($AL$2&$G7,Validation!$E:$O,7,FALSE),0) -> 0 | AO7: =AN7/AN$6 -> 0 | AQ7: =IFERROR(VLOOKUP($AQ$2&$G7,Validation!$E:$O,8,FALSE),0) -> 0 | AR7: =AQ7/AQ$6 -> 0 | AS7: =IFERROR(VLOOKUP($AQ$2&$G7,Validation!$E:$O,11,FALSE),0) -> 0 | AT7: =AS7/AS$6 -> 0 | AV7: =IFERROR(VLOOKUP($AV$2&$G7,Validation!$E:$O,6,FALSE),0) -> 69.078872 | AW7: =AV7/AV$6 -> 0.47769744 | AX7: =IFERROR(VLOOKUP($AV$2&$G7,Validation!$E:$O,7,FALSE),0) -> 138.15774 | AY7: =AX7/AX$6 -> 0.49658447 | BA7: =IFERROR(VLOOKUP($BA$2&$G7,Validation!$E:$L,8,FALSE),0) -> 276.31549 | BB7: =BA7/BA$6 -> 0.50108715 | BC7: =IFERROR(VLOOKUP($BA$2&$G7,Validation!$E:$O,11,FALSE),0) -> 1229.3293 | BD7: =BC7/BC$6 -> 0.57178105 | BF7: =IFERROR(VLOOKUP($BF$2&$G7,Validation!E:O,11,FALSE),0) -> 0 | BG7: =BF7/BF$6 -> 0
B8: ='Pricing Trends'!R14 -> RBD SOYA BEAN OIL | C8: ='Pricing Trends'!S14 -> 45256 | D8: ='Pricing Trends'!U14 -> 68.75434 | E8: FALSE | G8: RBD PALM OLEIN (LOCAL) | I8: =IFERROR(VLOOKUP($I$2&$G8,Validation!$E:$O,4,FALSE),0) -> 0 | J8: =I8/I$6 -> 0 | K8: =IFERROR(VLOOKUP($I$2&$G8,Validation!$E:$O,5,FALSE),0) -> 0 | L8: =K8/K$6 -> 0 | M8: =IFERROR(VLOOKUP($I$2&$G8,Validation!$E:$O,6,FALSE),0) -> 0 | N8: =M8/M$6 -> 0 | O8: =IFERROR(VLOOKUP($I$2&$G8,Validation!$E:$O,6,FALSE),0) -> 0 | P8: =O8/O$6 -> 0 | Q8: =IFERROR(VLOOKUP($I$2&$G8,Validation!$E:$O,7,FALSE),0) -> 0 | R8: =Q8/Q$6 -> 0 | S8: =IFERROR(VLOOKUP($I$2&$G8,Validation!$E:$O,7,FALSE),0) -> 0 | T8: =S8/S$6 -> 0 | V8: =IFERROR(VLOOKUP($V$2&$G8,Validation!$E:$O,9,FALSE),0) -> 0 | W8: =V8/V$6 -> 0 | X8: =IFERROR(VLOOKUP($V$2&$G8,Validation!$E:$O,10,FALSE),0) -> 0 | Y8: =X8/X$6 -> 0 | Z8: =IFERROR(VLOOKUP($V$2&$G8,Validation!$E:$O,5,FALSE),0) -> 0 | AA8: =Z8/Z$6 -> 0 | AB8: =IFERROR(VLOOKUP($V$2&$G8,Validation!$E:$O,6,FALSE),0) -> 0 | AC8: =AB8/AB$6 -> 0 | AD8: =IFERROR(VLOOKUP($V$2&$G8,Validation!$E:$O,7,FALSE),0) -> 0 | AE8: =AD8/AD$6 -> 0 | AG8: =IFERROR(VLOOKUP($AG$2&$G8,Validation!E:O,8,FALSE),0) -> 0 | AH8: =AG8/AG$6 -> 0 | AI8: =IFERROR(VLOOKUP($AG$2&$G8,Validation!E:O,11,FALSE),0) -> 0 | AJ8: =AI8/AI$6 -> 0 | AL8: =IFERROR(VLOOKUP($AL$2&$G8,Validation!$E:$O,6,FALSE),0) -> 0 | AM8: =AL8/AL$6 -> 0 | AN8: =IFERROR(VLOOKUP($AL$2&$G8,Validation!$E:$O,7,FALSE),0) -> 0 | AO8: =AN8/AN$6 -> 0 | AQ8: =IFERROR(VLOOKUP($AQ$2&$G8,Validation!$E:$O,8,FALSE),0) -> 0 | AR8: =AQ8/AQ$6 -> 0 | AS8: =IFERROR(VLOOKUP($AQ$2&$G8,Validation!$E:$O,11,FALSE),0) -> 0 | AT8: =AS8/AS$6 -> 0 | AV8: =IFERROR(VLOOKUP($AV$2&$G8,Validation!$E:$O,6,FALSE),0) -> 0 | AW8: =AV8/AV$6 -> 0 | AX8: =IFERROR(VLOOKUP($AV$2&$G8,Validation!$E:$O,7,FALSE),0) -> 0 | AY8: =AX8/AX$6 -> 0 | BA8: =IFERROR(VLOOKUP($BA$2&$G8,Validation!$E:$L,8,FALSE),0) -> 0 | BB8: =BA8/BA$6 -> 0 | BC8: =IFERROR(VLOOKUP($BA$2&$G8,Validation!$E:$O,11,FALSE),0) -> 0 | BD8: =BC8/BC$6 -> 0 | BF8: =IFERROR(VLOOKUP($BF$2&$G8,Validation!E:O,11,FALSE),0) -> 0 | BG8: =BF8/BF$6 -> 0
B9: ='Pricing Trends'!R15 -> RBD SOYA BEAN OIL | C9: ='Pricing Trends'!S15 -> 45132 | D9: ='Pricing Trends'!U15 -> 64.59293 | E9: FALSE | G9: RBD PALM OLEIN (FOREIGN) | I9: =IFERROR(VLOOKUP($I$2&$G9,Validation!$E:$O,4,FALSE),0) -> 21.228606 | J9: =I9/I$6 -> 0.49267336 | K9: =IFERROR(VLOOKUP($I$2&$G9,Validation!$E:$O,5,FALSE),0) -> 30.32658 | L9: =K9/K$6 -> 0.5016377 | M9: =IFERROR(VLOOKUP($I$2&$G9,Validation!$E:$O,6,FALSE),0) -> 60.65316 | N9: =M9/M$6 -> 0.51902284 | O9: =IFERROR(VLOOKUP($I$2&$G9,Validation!$E:$O,6,FALSE),0) -> 60.65316 | P9: =O9/O$6 -> 0.51902284 | Q9: =IFERROR(VLOOKUP($I$2&$G9,Validation!$E:$O,7,FALSE),0) -> 121.30632 | R9: =Q9/Q$6 -> 0.53623026 | S9: =IFERROR(VLOOKUP($I$2&$G9,Validation!$E:$O,7,FALSE),0) -> 121.30632 | T9: =S9/S$6 -> 0.53623026 | V9: =IFERROR(VLOOKUP($V$2&$G9,Validation!$E:$O,9,FALSE),0) -> 10.917569 | W9: =V9/V$6 -> 0.48634816 | X9: =IFERROR(VLOOKUP($V$2&$G9,Validation!$E:$O,10,FALSE),0) -> 18.195948 | Y9: =X9/X$6 -> 0.50432107 | Z9: =IFERROR(VLOOKUP($V$2&$G9,Validation!$E:$O,5,FALSE),0) -> 30.32658 | AA9: =Z9/Z$6 -> 0.51575689 | AB9: =IFERROR(VLOOKUP($V$2&$G9,Validation!$E:$O,6,FALSE),0) -> 60.65316 | AC9: =AB9/AB$6 -> 0.5339173 | AD9: =IFERROR(VLOOKUP($V$2&$G9,Validation!$E:$O,7,FALSE),0) -> 121.30632 | AE9: =AD9/AD$6 -> 0.54515713 | AG9: =IFERROR(VLOOKUP($AG$2&$G9,Validation!E:O,8,FALSE),0) -> 242.61264 | AH9: =AG9/AG$6 -> 0.54222245 | AI9: =IFERROR(VLOOKUP($AG$2&$G9,Validation!E:O,11,FALSE),0) -> 1079.3851 | AJ9: =AI9/AI$6 -> 0.67461568 | AL9: =IFERROR(VLOOKUP($AL$2&$G9,Validation!$E:$O,6,FALSE),0) -> 12.130632 | AM9: =AL9/AL$6 -> 0.094401805 | AN9: =IFERROR(VLOOKUP($AL$2&$G9,Validation!$E:$O,7,FALSE),0) -> 24.261264 | AO9: =AN9/AN$6 -> 0.10272797 | AQ9: =IFERROR(VLOOKUP($AQ$2&$G9,Validation!$E:$O,8,FALSE),0) -> 0 | AR9: =AQ9/AQ$6 -> 0 | AS9: =IFERROR(VLOOKUP($AQ$2&$G9,Validation!$E:$O,11,FALSE),0) -> 0 | AT9: =AS9/AS$6 -> 0 | AV9: =IFERROR(VLOOKUP($AV$2&$G9,Validation!$E:$O,6,FALSE),0) -> 0 | AW9: =AV9/AV$6 -> 0 | AX9: =IFERROR(VLOOKUP($AV$2&$G9,Validation!$E:$O,7,FALSE),0) -> 0 | AY9: =AX9/AX$6 -> 0 | BA9: =IFERROR(VLOOKUP($BA$2&$G9,Validation!$E:$L,8,FALSE),0) -> 0 | BB9: =BA9/BA$6 -> 0 | BC9: =IFERROR(VLOOKUP($BA$2&$G9,Validation!$E:$O,11,FALSE),0) -> 0 | BD9: =BC9/BC$6 -> 0 | BF9: =IFERROR(VLOOKUP($BF$2&$G9,Validation!E:O,11,FALSE),0) -> 0 | BG9: =BF9/BF$6 -> 0
B10: ='Pricing Trends'!R16 -> RBD SOYA BEAN OIL | C10: ='Pricing Trends'!S16 -> 44961 | D10: ='Pricing Trends'!U16 -> 81.901482 | E10: FALSE | G10: RBD CANOLA OIL | I10: =IFERROR(VLOOKUP($I$2&$G10,Validation!$E:$O,4,FALSE),0) -> 0 | J10: =I10/I$6 -> 0 | K10: =IFERROR(VLOOKUP($I$2&$G10,Validation!$E:$O,5,FALSE),0) -> 0 | L10: =K10/K$6 -> 0 | M10: =IFERROR(VLOOKUP($I$2&$G10,Validation!$E:$O,6,FALSE),0) -> 0 | N10: =M10/M$6 -> 0 | O10: =IFERROR(VLOOKUP($I$2&$G10,Validation!$E:$O,6,FALSE),0) -> 0 | P10: =O10/O$6 -> 0 | Q10: =IFERROR(VLOOKUP($I$2&$G10,Validation!$E:$O,7,FALSE),0) -> 0 | R10: =Q10/Q$6 -> 0 | S10: =IFERROR(VLOOKUP($I$2&$G10,Validation!$E:$O,7,FALSE),0) -> 0 | T10: =S10/S$6 -> 0 | V10: =IFERROR(VLOOKUP($V$2&$G10,Validation!$E:$O,9,FALSE),0) -> 0 | W10: =V10/V$6 -> 0 | X10: =IFERROR(VLOOKUP($V$2&$G10,Validation!$E:$O,10,FALSE),0) -> 0 | Y10: =X10/X$6 -> 0 | Z10: =IFERROR(VLOOKUP($V$2&$G10,Validation!$E:$O,5,FALSE),0) -> 0 | AA10: =Z10/Z$6 -> 0 | AB10: =IFERROR(VLOOKUP($V$2&$G10,Validation!$E:$O,6,FALSE),0) -> 0 | AC10: =AB10/AB$6 -> 0 | AD10: =IFERROR(VLOOKUP($V$2&$G10,Validation!$E:$O,7,FALSE),0) -> 0 | AE10: =AD10/AD$6 -> 0 | AG10: =IFERROR(VLOOKUP($AG$2&$G10,Validation!E:O,8,FALSE),0) -> 0 | AH10: =AG10/AG$6 -> 0 | AI10: =IFERROR(VLOOKUP($AG$2&$G10,Validation!E:O,11,FALSE),0) -> 0 | AJ10: =AI10/AI$6 -> 0 | AL10: =IFERROR(VLOOKUP($AL$2&$G10,Validation!$E:$O,6,FALSE),0) -> 66.576033 | AM10: =AL10/AL$6 -> 0.51810142 | AN10: =IFERROR(VLOOKUP($AL$2&$G10,Validation!$E:$O,7,FALSE),0) -> 133.15207 | AO10: =AN10/AN$6 -> 0.56379754 | AQ10: =IFERROR(VLOOKUP($AQ$2&$G10,Validation!$E:$O,8,FALSE),0) -> 332.88017 | AR10: =AQ10/AQ$6 -> 0.62110302 | AS10: =IFERROR(VLOOKUP($AQ$2&$G10,Validation!$E:$O,11,FALSE),0) -> 1480.9859 | AT10: =AS10/AS$6 -> 0.74880844 | AV10: =IFERROR(VLOOKUP($AV$2&$G10,Validation!$E:$O,6,FALSE),0) -> 0 | AW10: =AV10/AV$6 -> 0 | AX10: =IFERROR(VLOOKUP($AV$2&$G10,Validation!$E:$O,7,FALSE),0) -> 0 | AY10: =AX10/AX$6 -> 0 | BA10: =IFERROR(VLOOKUP($BA$2&$G10,Validation!$E:$L,8,FALSE),0) -> 0 | BB10: =BA10/BA$6 -> 0 | BC10: =IFERROR(VLOOKUP($BA$2&$G10,Validation!$E:$O,11,FALSE),0) -> 0 | BD10: =BC10/BC$6 -> 0 | BF10: =IFERROR(VLOOKUP($BF$2&$G10,Validation!E:O,11,FALSE),0) -> 0 | BG10: =BF10/BF$6 -> 0
B11: ='Pricing Trends'!R17 -> 0 | C11: ='Pricing Trends'!S17 -> 0 | D11: ='Pricing Trends'!U17 -> 0 | E11: FALSE | G11: RBD COCONUT OIL | I11: =IFERROR(VLOOKUP($I$2&$G11,Validation!$E:$O,4,FALSE),0) -> 0 | J11: =I11/I$6 -> 0 | K11: =IFERROR(VLOOKUP($I$2&$G11,Validation!$E:$O,5,FALSE),0) -> 0 | L11: =K11/K$6 -> 0 | M11: =IFERROR(VLOOKUP($I$2&$G11,Validation!$E:$O,6,FALSE),0) -> 0 | N11: =M11/M$6 -> 0 | O11: =IFERROR(VLOOKUP($I$2&$G11,Validation!$E:$O,6,FALSE),0) -> 0 | P11: =O11/O$6 -> 0 | Q11: =IFERROR(VLOOKUP($I$2&$G11,Validation!$E:$O,7,FALSE),0) -> 0 | R11: =Q11/Q$6 -> 0 | S11: =IFERROR(VLOOKUP($I$2&$G11,Validation!$E:$O,7,FALSE),0) -> 0 | T11: =S11/S$6 -> 0 | V11: =IFERROR(VLOOKUP($V$2&$G11,Validation!$E:$O,9,FALSE),0) -> 0 | W11: =V11/V$6 -> 0 | X11: =IFERROR(VLOOKUP($V$2&$G11,Validation!$E:$O,10,FALSE),0) -> 0 | Y11: =X11/X$6 -> 0 | Z11: =IFERROR(VLOOKUP($V$2&$G11,Validation!$E:$O,5,FALSE),0) -> 0 | AA11: =Z11/Z$6 -> 0 | AB11: =IFERROR(VLOOKUP($V$2&$G11,Validation!$E:$O,6,FALSE),0) -> 0 | AC11: =AB11/AB$6 -> 0 | AD11: =IFERROR(VLOOKUP($V$2&$G11,Validation!$E:$O,7,FALSE),0) -> 0 | AE11: =AD11/AD$6 -> 0 | AG11: =IFERROR(VLOOKUP($AG$2&$G11,Validation!E:O,8,FALSE),0) -> 0 | AH11: =AG11/AG$6 -> 0 | AI11: =IFERROR(VLOOKUP($AG$2&$G11,Validation!E:O,11,FALSE),0) -> 0 | AJ11: =AI11/AI$6 -> 0 | AL11: =IFERROR(VLOOKUP($AL$2&$G11,Validation!$E:$O,6,FALSE),0) -> 0 | AM11: =AL11/AL$6 -> 0 | AN11: =IFERROR(VLOOKUP($AL$2&$G11,Validation!$E:$O,7,FALSE),0) -> 0 | AO11: =AN11/AN$6 -> 0 | AQ11: =IFERROR(VLOOKUP($AQ$2&$G11,Validation!$E:$O,8,FALSE),0) -> 0 | AR11: =AQ11/AQ$6 -> 0 | AS11: =IFERROR(VLOOKUP($AQ$2&$G11,Validation!$E:$O,11,FALSE),0) -> 0 | AT11: =AS11/AS$6 -> 0 | AV11: =IFERROR(VLOOKUP($AV$2&$G11,Validation!$E:$O,6,FALSE),0) -> 0 | AW11: =AV11/AV$6 -> 0 | AX11: =IFERROR(VLOOKUP($AV$2&$G11,Validation!$E:$O,7,FALSE),0) -> 0 | AY11: =AX11/AX$6 -> 0 | BA11: =IFERROR(VLOOKUP($I$2&$G11,Validation!$E:$K,4,FALSE),0) -> 0 | BB11: =BA11/BA$6 -> 0 | BC11: =IFERROR(VLOOKUP($BA$2&$G11,Validation!$E:$O,11,FALSE),0) -> 0 | BD11: =BC11/BC$6 -> 0 | BF11: =IFERROR(VLOOKUP($BF$2&$G11,Validation!E:O,11,FALSE),0) -> 1519.02 | BG11: =BF11/BF$6 -> 0.79948421
B12: ='Pricing Trends'!R18 -> RBD COCONUT OIL | C12: ='Pricing Trends'!S18 -> 45468 | D12: ='Pricing Trends'!U18 -> 64.678486 | E12: FALSE | G12: LABEL | I12: =IFERROR(VLOOKUP("350ML LABEL PALM",'Pricing Trends'!$K:$N,4,FALSE),0) -> 0.3 | J12: =I12/I$6 -> 0.0069623982 | K12: =IFERROR(VLOOKUP("500ML LABEL PALM",'Pricing Trends'!$K:$N,4,FALSE),0) -> 0.45 | L12: =K12/K$6 -> 0.0074435352 | M12: =IFERROR(VLOOKUP("1LITER LABEL PALM",'Pricing Trends'!$K:$N,4,FALSE),0) -> 0.55 | N12: =M12/M$6 -> 0.0047064747 | O12: =IFERROR(VLOOKUP("1LITER LABEL PALM MZL",'Pricing Trends'!$K:$N,4,FALSE),0) -> 0.7 | P12: =O12/O$6 -> 0.0059900587 | Q12: =IFERROR(VLOOKUP("2LITERS LABEL PALM",'Pricing Trends'!$K:$N,4,FALSE),0) -> 1.02 | R12: =Q12/Q$6 -> 0.0045088736 | S12: =IFERROR(VLOOKUP("2LITERS LABEL PALM",'Pricing Trends'!$K:$N,4,FALSE),0) -> 1.02 | T12: =S12/S$6 -> 0.0045088736 | W12: =V12/V$6 -> 0 | Y12: =X12/X$6 -> 0 | AA12: =Z12/Z$6 -> 0 | AC12: =AB12/AB$6 -> 0 | AE12: =AD12/AD$6 -> 0 | AG12: =IFERROR(VLOOKUP("4LITERS LABEL PALM",'Pricing Trends'!$K:$N,4,FALSE),0) -> 7 | AH12: =AG12/AG$6 -> 0.015644515 | AJ12: =AI12/AI$6 -> 0 | AL12: =IFERROR(VLOOKUP("1LITER LABEL CANOLEIN",'Pricing Trends'!$K:$N,4,FALSE),0) -> 0.72 | AM12: =AL12/AL$6 -> 0.0056031128 | AN12: =IFERROR(VLOOKUP("2LITERS LABEL CANOLEIN",'Pricing Trends'!$K:$N,4,FALSE),0) -> 1.05 | AO12: =AN12/AN$6 -> 0.00444595 | AQ12: =IFERROR(VLOOKUP("4LITERS LABEL CANOLA",'Pricing Trends'!$K:$N,4,FALSE),0) -> 7 | AR12: =AQ12/AQ$6 -> 0.01306092 | AT12: =AS12/AS$6 -> 0 | AV12: =IFERROR(VLOOKUP("1LITER LABEL SOYA",'Pricing Trends'!$K:$N,4,FALSE),0) -> 0.72 | AW12: =AV12/AV$6 -> 0.0049789776 | AX12: =IFERROR(VLOOKUP("2LITERS LABEL SOYA",'Pricing Trends'!$K:$N,4,FALSE),0) -> 1.05 | AY12: =AX12/AX$6 -> 0.0037740461 | BA12: =IFERROR(VLOOKUP("4LITERS LABEL SOYA",'Pricing Trends'!$K:$N,4,FALSE),0) -> 7 | BB12: =BA12/BA$6 -> 0.012694222 | BD12: =BC12/BC$6 -> 0 | BG12: =BF12/BF$6 -> 0
B13: ='Pricing Trends'!R19 -> RBD COCONUT OIL | C13: ='Pricing Trends'!S19 -> 45222 | D13: ='Pricing Trends'!U19 -> 51.4783 | E13: FALSE | G13: BOTTLE / POUCH | I13: =IFERROR(VLOOKUP("350ML BOTTLE PALM [SWAK]",'Pricing Trends'!$A:$D,4,FALSE),0) -> 3.35 | J13: =I13/I$6 -> 0.07774678 | K13: =IFERROR(VLOOKUP("500ML BOTTLE PALM [SWAK]",'Pricing Trends'!$A:$D,4,FALSE),0) -> 3.65 | L13: =K13/K$6 -> 0.060375341 | M13: =IFERROR(VLOOKUP("1LITER BOTTLE PALM [SWAK]",'Pricing Trends'!$A:$D,4,FALSE),0) -> 6.55 | N13: =M13/M$6 -> 0.056049835 | O13: =IFERROR(VLOOKUP("900ML BOTTLE PALM MAZOLA",'Pricing Trends'!$A:$D,4,FALSE),0) -> 6.9 | P13: =O13/O$6 -> 0.059044865 | Q13: =IFERROR(VLOOKUP("2LITERS BOTTLE PALM [NUTRI]",'Pricing Trends'!$A:$D,4,FALSE),0) -> 15.75 | R13: =Q13/Q$6 -> 0.069622313 | S13: =IFERROR(VLOOKUP("2LITERS BOTTLE PALM MAZOLA",'Pricing Trends'!$A:$D,4,FALSE),0) -> 21.95 | T13: =S13/S$6 -> 0.097029192 | V13: =IFERROR(VLOOKUP("180ML POUCH PALM [SUP]",'Pricing Trends'!$A:$D,4,FALSE),0) -> 2.1 | W13: =V13/V$6 -> 0.093549319 | X13: =IFERROR(VLOOKUP("300ML POUCH PALM [SUP]",'Pricing Trends'!$A:$D,4,FALSE),0) -> 2.6 | Y13: =X13/X$6 -> 0.072061911 | Z13: =IFERROR(VLOOKUP("500ML POUCH PALM [SUP]",'Pricing Trends'!$A:$D,4,FALSE),0) -> 0 | AA13: =Z13/Z$6 -> 0 | AB13: =IFERROR(VLOOKUP("1LITER POUCH PALM [SUP]",'Pricing Trends'!$A:$D,4,FALSE),0) -> 4.7 | AC13: =AB13/AB$6 -> 0.041373134 | AD13: =IFERROR(VLOOKUP("2LITERS POUCH PALM [SUP]",'Pricing Trends'!$A:$D,4,FALSE),0) -> 6.17 | AE13: =AD13/AD$6 -> 0.027728312 | AG13: =IFERROR(VLOOKUP("4LITERS BOTTLE GODZILLA",'Pricing Trends'!$A:$D,4,FALSE),0) -> 32.48 | AH13: =AG13/AG$6 -> 0.07259055 | AJ13: =AI13/AI$6 -> 0 | AL13: =IFERROR(VLOOKUP("1LITER BOTTLE CANSOY [NUTRI]",'Pricing Trends'!$A:$D,4,FALSE),0) -> 6.6 | AM13: =AL13/AL$6 -> 0.051361868 | AN13: =IFERROR(VLOOKUP("2LITERS BOTTLE CANOLEIN [ROUND]",'Pricing Trends'!$A:$D,4,FALSE),0) -> 18.1 | AO13: =AN13/AN$6 -> 0.076639709 | AQ13: =IFERROR(VLOOKUP("4LITERS BOTTLE GODZILLA",'Pricing Trends'!$A:$D,4,FALSE),0) -> 32.48 | AR13: =AQ13/AQ$6 -> 0.060602668 | AT13: =AS13/AS$6 -> 0 | AV13: =IFERROR(VLOOKUP("1LITER BOTTLE CANSOY [NUTRI]",'Pricing Trends'!$A:$D,4,FALSE),0) -> 6.6 | AW13: =AV13/AV$6 -> 0.045640628 | AX13: =IFERROR(VLOOKUP("2LITERS BOTTLE SOYA [ROUND]",'Pricing Trends'!$A:$D,4,FALSE),0) -> 19 | AY13: =AX13/AX$6 -> 0.068292262 | BA13: =IFERROR(VLOOKUP("4LITERS BOTTLE GODZILLA",'Pricing Trends'!$A:$D,4,FALSE),0) -> 32.48 | BB13: =BA13/BA$6 -> 0.058901188 | BD13: =BC13/BC$6 -> 0 | BG13: =BF13/BF$6 -> 0
B14: ='Pricing Trends'!R20 -> RBD COCONUT OIL | C14: ='Pricing Trends'!S20 -> 45133 | D14: ='Pricing Trends'!U20 -> 54.559 | E14: FALSE | G14: BOX | I14: =IFERROR(VLOOKUP("350ML BOX PALM",'Pricing Trends'!$F:$I,4,FALSE),0)/J5 -> 0.80555556 | J14: =I14/I$6 -> 0.018695328 | K14: =IFERROR(VLOOKUP("500ML BOX PALM",'Pricing Trends'!$F:$I,4,FALSE),0)/L5 -> 0.8625 | L14: =K14/K$6 -> 0.014266776 | M14: =IFERROR(VLOOKUP("1LITER BOX PALM",'Pricing Trends'!$F:$I,4,FALSE),0)/N5 -> 2.5833333 | N14: =M14/M$6 -> 0.022106169 | O14: =IFERROR(VLOOKUP("1LITER BOX PALM MZL",'Pricing Trends'!$F:$I,4,FALSE),0)/P5 -> 1.375 | P14: =O14/O$6 -> 0.011766187 | Q14: =IFERROR(VLOOKUP("2LITERS BOX PALM",'Pricing Trends'!$F:$I,4,FALSE),0)/R5 -> 4.5 | R14: =Q14/Q$6 -> 0.019892089 | S14: =IFERROR(VLOOKUP("2LITERS BOX PALM MZL",'Pricing Trends'!$F:$I,4,FALSE),0)/T5 -> 2.8333333 | T14: =S14/S$6 -> 0.012524649 | V14: =IFERROR(VLOOKUP("180ML BOX PALM SUP",'Pricing Trends'!$F:$I,4,FALSE),0)/W5 -> 0.52083333 | W14: =V14/V$6 -> 0.023201716 | X14: =IFERROR(VLOOKUP("300ML BOX PALM SUP",'Pricing Trends'!$F:$I,4,FALSE),0)/Y5 -> 0.69444444 | Y14: =X14/X$6 -> 0.019247305 | Z14: =IFERROR(VLOOKUP("500ML BOX PALM SUP",'Pricing Trends'!$F:$I,4,FALSE),0)/AA5 -> 0.91666667 | AA14: =Z14/Z$6 -> 0.015589531 | AB14: =IFERROR(VLOOKUP("1LITER BOX PALM SUP",'Pricing Trends'!$F:$I,4,FALSE),0)/AC5 -> 2.5833333 | AC14: =AB14/AB$6 -> 0.022740552 | AD14: =IFERROR(VLOOKUP("2LITERS BOX PALM SUP",'Pricing Trends'!$F:$I,4,FALSE),0)/AE5 -> 4.5 | AE14: =AD14/AD$6 -> 0.020223242 | AG14: =IFERROR(VLOOKUP("4LITERS BOX CHECK",'Pricing Trends'!$F:$I,4,FALSE),0)/AH5 -> 4 | AH14: =AG14/AG$6 -> 0.0089397229 | AJ14: =AI14/AI$6 -> 0 | AL14: =IFERROR(VLOOKUP("1LITER BOX CANOLEIN",'Pricing Trends'!$F:$I,4,FALSE),0)/AM5 -> 1.25 | AM14: =AL14/AL$6 -> 0.0097276265 | AN14: =IFERROR(VLOOKUP("2LITERS BOX CANOLEIN",'Pricing Trends'!$F:$I,4,FALSE),0)/AO5 -> 2.7333333 | AO14: =AN14/AN$6 -> 0.011573584 | AQ14: =IFERROR(VLOOKUP("4LITERS BOX CHECK",'Pricing Trends'!$F:$I,4,FALSE),0)/AR5 -> 4 | AR14: =AQ14/AQ$6 -> 0.0074633828 | AT14: =AS14/AS$6 -> 0 | AV14: =IFERROR(VLOOKUP("1LITER BOX SOYA",'Pricing Trends'!$F:$I,4,FALSE),0)/AW5 -> 1.25 | AW14: =AV14/AV$6 -> 0.0086440584 | AX14: =IFERROR(VLOOKUP("2LITERS BOX CANOLEIN",'Pricing Trends'!$F:$I,4,FALSE),0)/AY5 -> 2.7333333 | AY14: =AX14/AX$6 -> 0.0098245009 | BA14: =IFERROR(VLOOKUP("4LITERS BOX CHECK",'Pricing Trends'!$F:$I,4,FALSE),0)/BB5 -> 4 | BB14: =BA14/BA$6 -> 0.0072538409 | BD14: =BC14/BC$6 -> 0 | BG14: =BF14/BF$6 -> 0
B15: ='Pricing Trends'!R21 -> RBD COCONUT OIL | C15: ='Pricing Trends'!S21 -> 44965 | D15: ='Pricing Trends'!U21 -> 52.7983 | E15: FALSE | G15: PACKAGING TAPE CLEAR | I15: =((IFERROR(VLOOKUP($G$15,'Pricing Trends'!$W:$Z,4,FALSE),0)/10000)*200)/J5 -> 0.013888889 | J15: =I15/I$6 -> 0.00032233325 | K15: =((IFERROR(VLOOKUP($G$15,'Pricing Trends'!$W:$Z,4,FALSE),0)/10000)*200)/L5 -> 0.020833333 | L15: =K15/K$6 -> 0.00034460811 | M15: =((IFERROR(VLOOKUP($G$15,'Pricing Trends'!$W:$Z,4,FALSE),0)/10000)*200)/N5 -> 0.041666667 | N15: =M15/M$6 -> 0.00035655111 | O15: =((IFERROR(VLOOKUP($G$15,'Pricing Trends'!$W:$Z,4,FALSE),0)/10000)*200)/P5 -> 0.041666667 | P15: =O15/O$6 -> 0.00035655111 | Q15: =((IFERROR(VLOOKUP($G$15,'Pricing Trends'!$W:$Z,4,FALSE),0)/10000)*200)/R5 -> 0.083333333 | R15: =Q15/Q$6 -> 0.00036837203 | S15: =((IFERROR(VLOOKUP($G$15,'Pricing Trends'!$W:$Z,4,FALSE),0)/10000)*200)/T5 -> 0.083333333 | T15: =S15/S$6 -> 0.00036837203 | V15: =((IFERROR(VLOOKUP($G$15,'Pricing Trends'!$W:$Z,4,FALSE),0)/10000)*200)/W5 -> 0.010416667 | W15: =V15/V$6 -> 0.00046403432 | X15: =((IFERROR(VLOOKUP($G$15,'Pricing Trends'!$W:$Z,4,FALSE),0)/10000)*200)/Y5 -> 0.013888889 | Y15: =X15/X$6 -> 0.0003849461 | Z15: =((IFERROR(VLOOKUP($G$15,'Pricing Trends'!$W:$Z,4,FALSE),0)/10000)*200)/AA5 -> 0.020833333 | AA15: =Z15/Z$6 -> 0.00035430752 | AB15: =((IFERROR(VLOOKUP($G$15,'Pricing Trends'!$W:$Z,4,FALSE),0)/10000)*200)/AC5 -> 0.041666667 | AC15: =AB15/AB$6 -> 0.0003667831 | AD15: =((IFERROR(VLOOKUP($G$15,'Pricing Trends'!$W:$Z,4,FALSE),0)/10000)*200)/AE5 -> 0.083333333 | AE15: =AD15/AD$6 -> 0.00037450448 | AG15: =((IFERROR(VLOOKUP($G$15,'Pricing Trends'!$W:$Z,4,FALSE),0)/10000)*200)/AH5 -> 0.125 | AH15: =AG15/AG$6 -> 0.00027936634 | AJ15: =AI15/AI$6 -> 0 | AL15: =((IFERROR(VLOOKUP($G$15,'Pricing Trends'!$W:$Z,4,FALSE),0)/10000)*200)/AM5 -> 0.041666667 | AM15: =AL15/AL$6 -> 0.00032425422 | AN15: =((IFERROR(VLOOKUP($G$15,'Pricing Trends'!$W:$Z,4,FALSE),0)/10000)*200)/AO5 -> 0.083333333 | AO15: =AN15/AN$6 -> 0.00035285317 | AQ15: =((IFERROR(VLOOKUP($G$15,'Pricing Trends'!$W:$Z,4,FALSE),0)/10000)*200)/AR5 -> 0.125 | AR15: =AQ15/AQ$6 -> 0.00023323071 | AT15: =AS15/AS$6 -> 0 | AV15: =((IFERROR(VLOOKUP($G$15,'Pricing Trends'!$W:$Z,4,FALSE),0)/10000)*200)/AW5 -> 0.041666667 | AW15: =AV15/AV$6 -> 0.00028813528 | AX15: =((IFERROR(VLOOKUP($G$15,'Pricing Trends'!$W:$Z,4,FALSE),0)/10000)*200)/AY5 -> 0.083333333 | AY15: =AX15/AX$6 -> 0.00029952747 | BA15: =((IFERROR(VLOOKUP($G$15,'Pricing Trends'!$W:$Z,4,FALSE),0)/10000)*200)/BB5 -> 0.125 | BB15: =BA15/BA$6 -> 0.00022668253 | BD15: =BC15/BC$6 -> 0 | BG15: =BF15/BF$6 -> 0
B16: ='Pricing Trends'!R22 -> 0 | C16: ='Pricing Trends'!S22 -> 0 | D16: ='Pricing Trends'!U22 -> 0 | E16: FALSE | G16: DOUBLE SIDED TAPE 3/4"X30M | I16: =((45/3000)*7) -> 0.105 | J16: =I16/I$6 -> 0.0024368394 | K16: =((45/3000)*7) -> 0.105 | L16: =K16/K$6 -> 0.0017368249 | M16: =((45/3000)*12) -> 0.18 | N16: =M16/M$6 -> 0.0015403008 | P16: =O16/O$6 -> 0 | R16: =Q16/Q$6 -> 0 | T16: =S16/S$6 -> 0 | W16: =V16/V$6 -> 0 | Y16: =X16/X$6 -> 0 | AA16: =Z16/Z$6 -> 0 | AC16: =AB16/AB$6 -> 0 | AE16: =AD16/AD$6 -> 0 | AH16: =AG16/AG$6 -> 0 | AJ16: =AI16/AI$6 -> 0 | AM16: =AL16/AL$6 -> 0 | AO16: =AN16/AN$6 -> 0 | AR16: =AQ16/AQ$6 -> 0 | AT16: =AS16/AS$6 -> 0 | AW16: =AV16/AV$6 -> 0 | AY16: =AX16/AX$6 -> 0 | BB16: =BA16/BA$6 -> 0 | BD16: =BC16/BC$6 -> 0 | BG16: =BF16/BF$6 -> 0
B17: ='Pricing Trends'!R23 -> RBD PALM OLEIN (FOREIGN) | C17: ='Pricing Trends'!S23 -> 45547 | D17: ='Pricing Trends'!U23 -> 60.65316 | E17: TRUE | G17: COST OF GOODS SOLD | I17: =SUM(I7:I16) -> 25.80305 | J17: =I17/I6 -> 0.59883704 | K17: =SUM(K7:K16) -> 35.414913 | L17: =K17/K6 -> 0.58580479 | M17: =SUM(M7:M16) -> 70.55816 | N17: =M17/M6 -> 0.60378217 | O17: =SUM(O7:O16) -> 69.669827 | P17: =O17/O6 -> 0.59618051 | Q17: =SUM(Q7:Q16) -> 142.65965 | R17: =Q17/Q6 -> 0.63062191 | S17: =SUM(S7:S16) -> 147.19299 | T17: =S17/S6 -> 0.65066134 | V17: =SUM(V7:V16) -> 13.548819 | W17: =V17/V6 -> 0.60356323 | X17: =SUM(X7:X16) -> 21.504281 | Y17: =X17/X6 -> 0.59601523 | Z17: =SUM(Z7:Z16) -> 31.26408 | AA17: =Z17/Z6 -> 0.53170073 | AB17: =SUM(AB7:AB16) -> 67.97816 | AC17: =AB17/AB6 -> 0.59839777 | AD17: =SUM(AD7:AD16) -> 132.05965 | AE17: =AD17/AD6 -> 0.59348318 | AG17: =SUM(AG7:AG16) -> 286.21764 | AH17: =AG17/AG6 -> 0.6396766 | AI17: =SUM(AI7:AI16) -> 1079.3851 | AJ17: =AI17/AI6 -> 0.67461568 | AL17: =SUM(AL7:AL16) -> 87.318332 | AM17: =AL17/AL6 -> 0.67952009 | AN17: =SUM(AN7:AN16) -> 179.38 | AO17: =AN17/AN6 -> 0.75953761 | AQ17: =SUM(AQ7:AQ16) -> 376.48517 | AR17: =AQ17/AQ6 -> 0.70246322 | AS17: =SUM(AS7:AS16) -> 1480.9859 | AT17: =AS17/AS6 -> 0.74880844 | AV17: =SUM(AV7:AV16) -> 77.690539 | AW17: =AV17/AV6 -> 0.53724924 | AX17: =SUM(AX7:AX16) -> 161.02441 | AY17: =AX17/AX6 -> 0.5787748 | BA17: =SUM(BA7:BA16) -> 319.92049 | BB17: =BA17/BA6 -> 0.58016308 | BC17: =SUM(BC7:BC16) -> 1229.3293 | BD17: =BC17/BC6 -> 0.57178105 | BF17: =SUM(BF7:BF16) -> 1519.02 | BG17: =BF17/BF6 -> 0.79948421
B18: ='Pricing Trends'!R24 -> RBD PALM OLEIN (FOREIGN) | C18: ='Pricing Trends'!S24 -> 45517 | D18: ='Pricing Trends'!U24 -> 60.97 | E18: FALSE | G18: GROSS PROFIT | I18: =I6-I17 -> 17.285551 | J18: =I18/I6 -> 0.40116296 | K18: =K6-K17 -> 25.040232 | L18: =K18/K6 -> 0.41419521 | M18: =M6-M17 -> 46.30213 | N18: =M18/M6 -> 0.39621783 | O18: =O6-O17 -> 47.190463 | P18: =O18/O6 -> 0.40381949 | Q18: =Q6-Q17 -> 83.560926 | R18: =Q18/Q6 -> 0.36937809 | S18: =S6-S17 -> 79.027593 | T18: =S18/S6 -> 0.34933866 | V18: =V6-V17 -> 8.8992334 | W18: =V18/V6 -> 0.39643677 | X18: =X6-X17 -> 14.575806 | Y18: =X18/X6 -> 0.40398477 | Z18: =Z6-Z17 -> 27.536065 | AA18: =Z18/Z6 -> 0.46829927 | AB18: =AB6-AB17 -> 45.62213 | AC18: =AB18/AB6 -> 0.40160223 | AD18: =AD6-AD17 -> 90.456598 | AE18: =AD18/AD6 -> 0.40651682 | AG18: =AG6-AG17 -> 161.22352 | AH18: =AG18/AG6 -> 0.3603234 | AI18: =AI6-AI17 -> 520.61491 | AJ18: =AI18/AI6 -> 0.32538432 | AL18: =AL6-AL17 -> 41.181668 | AM18: =AL18/AL6 -> 0.32047991 | AN18: =AN6-AN17 -> 56.790003 | AO18: =AN18/AN6 -> 0.24046239 | AQ18: =AQ6-AQ17 -> 159.46483 | AR18: =AQ18/AQ6 -> 0.29753678 | AS18: =AS6-AS17 -> 496.80415 | AT18: =AS18/AS6 -> 0.25119156 | AV18: =AV6-AV17 -> 66.917461 | AW18: =AV18/AV6 -> 0.46275076 | AX18: =AX6-AX17 -> 117.19159 | AY18: =AX18/AX6 -> 0.4212252 | BA18: =BA6-BA17 -> 231.51151 | BB18: =BA18/BA6 -> 0.41983692 | BC18: =BC6-BC17 -> 920.67074 | BD18: =BC18/BC6 -> 0.42821895 | BF18: =BF6-BF17 -> 380.98 | BG18: =BF18/BF6 -> 0.20051579
B19: ='Pricing Trends'!R25 -> RBD PALM OLEIN (FOREIGN) | C19: ='Pricing Trends'!S25 -> 45494 | D19: ='Pricing Trends'!U25 -> 60.49687 | E19: FALSE | G19: EXPENSES | I19: =SUM(I20:I35) -> 18.147781 | J19: =I19/I6 -> 0.42117359 | K19: =SUM(K20:K35) -> 25.515582 | L19: =K19/K6 -> 0.42205807 | M19: =SUM(M20:M35) -> 49.096322 | N19: =M19/M6 -> 0.42012836 | O19: =SUM(O20:O35) -> 48.9915 | P19: =O19/O6 -> 0.41923138 | Q19: =SUM(Q20:Q35) -> 94.360715 | R19: =Q19/Q6 -> 0.41711817 | S19: =SUM(S20:S35) -> 93.875001 | T19: =S19/S6 -> 0.41497109 | V19: =SUM(V20:V35) -> 8.8214242 | W19: =V19/V6 -> 0.39297059 | X19: =SUM(X20:X35) -> 14.23784 | Y19: =X19/X6 -> 0.39461768 | Z19: =SUM(Z20:Z35) -> 23.265201 | AA19: =Z19/Z6 -> 0.3956657 | AB19: =SUM(AB20:AB35) -> 45.136801 | AC19: =AB19/AB6 -> 0.39732998 | AD19: =SUM(AD20:AD35) -> 88.641582 | AE19: =AD19/AD6 -> 0.39836004 | AG19: =SUM(AG20:AG35) -> 186.64747 | AH19: =AG19/AG6 -> 0.41714416 | AI19: =SUM(AI20:AI35) -> 442.69866 | AJ19: =AI19/AI6 -> 0.27668666 | AL19: =SUM(AL20:AL35) -> 52.24815 | AM19: =AL19/AL6 -> 0.40660039 | AN19: =SUM(AN20:AN35) -> 94.915727 | AO19: =AN19/AN6 -> 0.40189578 | AQ19: =SUM(AQ20:AQ35) -> 215.91518 | AR19: =AQ19/AQ6 -> 0.40286441 | AS19: =SUM(AS20:AS35) -> 504.2313 | AT19: =AS19/AS6 -> 0.25494683 | AV19: =SUM(AV20:AV35) -> 53.315403 | AW19: =AV19/AV6 -> 0.36868917 | AX19: =SUM(AX20:AX35) -> 115.29599 | AY19: =AX19/AX6 -> 0.4144118 | BA19: =SUM(BA20:BA35) -> 228.84231 | BB19: =BA19/BA6 -> 0.41499642 | BC19: =SUM(BC20:BC35) -> 586.84586 | BD19: =BC19/BC6 -> 0.27295156 | BF19: =SUM(BF20:BF35) -> 266.26145 | BG19: =BF19/BF6 -> 0.14013761
B20: ='Pricing Trends'!R26 -> RBD PALM OLEIN (FOREIGN) | C20: ='Pricing Trends'!S26 -> 45314 | D20: ='Pricing Trends'!U26 -> 57.51356 | E20: FALSE | G20: Production Expenses - Labelling | I20: 0.2 | J20: =I20/I$6 -> 0.0046415988 | K20: 0.2 | L20: =K20/K$6 -> 0.0033082379 | M20: 0.2 | N20: =M20/M$6 -> 0.0017114454 | P20: =O20/O$6 -> 0 | R20: =Q20/Q$6 -> 0 | T20: =S20/S$6 -> 0 | W20: =V20/V$6 -> 0 | Y20: =X20/X$6 -> 0 | AA20: =Z20/Z$6 -> 0 | AC20: =AB20/AB$6 -> 0 | AE20: =AD20/AD$6 -> 0 | AG20: 0.2 | AH20: =AG20/AG$6 -> 0.00044698615 | AJ20: =AI20/AI$6 -> 0 | AM20: =AL20/AL$6 -> 0 | AO20: =AN20/AN$6 -> 0 | AQ20: 0.2 | AR20: =AQ20/AQ$6 -> 0.00037316914 | AT20: =AS20/AS$6 -> 0 | AV20: 0.2 | AW20: =AV20/AV$6 -> 0.0013830493 | AY20: =AX20/AX$6 -> 0 | BA20: 0.2 | BB20: =BA20/BA$6 -> 0.00036269205 | BD20: =BC20/BC$6 -> 0 | BG20: =BF20/BF$6 -> 0
B21: ='Pricing Trends'!R27 -> RBD PALM OLEIN (FOREIGN) | C21: ='Pricing Trends'!S27 -> 45248 | D21: ='Pricing Trends'!U27 -> 61.45051 | E21: FALSE | G21: Production Expenses - Packaging | I21: =0.4*0.35 -> 0.14 | J21: =I21/I$6 -> 0.0032491191 | K21: =0.4*0.5 -> 0.2 | L21: =K21/K$6 -> 0.0033082379 | M21: 0.4 | N21: =M21/M$6 -> 0.0034228907 | O21: 0.4 | P21: =O21/O$6 -> 0.0034228907 | Q21: =M21*2 -> 0.8 | R21: =Q21/Q$6 -> 0.0035363715 | S21: =M21*2 -> 0.8 | T21: =S21/S$6 -> 0.0035363715 | V21: =$M21*0.18 -> 0.072 | W21: =V21/V$6 -> 0.0032074052 | X21: =$M21*0.3 -> 0.12 | Y21: =X21/X$6 -> 0.0033259343 | Z21: =$M21*0.5 -> 0.2 | AA21: =Z21/Z$6 -> 0.0034013522 | AB21: =$M21 -> 0.4 | AC21: =AB21/AB$6 -> 0.0035211178 | AD21: =$M21*2 -> 0.8 | AE21: =AD21/AD$6 -> 0.003595243 | AG21: =M21*4 -> 1.6 | AH21: =AG21/AG$6 -> 0.0035758892 | AI21: =0.4*15.66*1.1364 -> 7.1184096 | AJ21: =AI21/AI$6 -> 0.004449006 | AL21: 0.4 | AM21: =AL21/AL$6 -> 0.0031128405 | AN21: =AL21*2 -> 0.8 | AO21: =AN21/AN$6 -> 0.0033873904 | AQ21: =AL21*4 -> 1.6 | AR21: =AQ21/AQ$6 -> 0.0029853531 | AS21: =AN21*4 -> 3.2 | AT21: =AS21/AS$6 -> 0.0016179675 | AV21: 0.4 | AW21: =AV21/AV$6 -> 0.0027660987 | AX21: =AV21*2 -> 0.8 | AY21: =AX21/AX$6 -> 0.0028754637 | BA21: =AV21*4 -> 1.6 | BB21: =BA21/BA$6 -> 0.0029015364 | BC21: =M21*15.66*1.1364 -> 7.1184096 | BD21: =BC21/BC$6 -> 0.0033108882 | BF21: =AI21 -> 7.1184096 | BG21: =BF21/BF$6 -> 0.0037465314
B22: ='Pricing Trends'!R28 -> RBD PALM OLEIN (FOREIGN) | C22: ='Pricing Trends'!S28 -> 45244 | D22: ='Pricing Trends'!U28 -> 63.35264 | E22: FALSE | G22: Distributors Discount | I22: =I6-(I6*0.92*0.98) -> 4.2399184 | J22: =I22/I$6 -> 0.0984 | K22: =K6-(K6*0.92*0.98) -> 5.9487863 | L22: =K22/K$6 -> 0.0984 | M22: =M6-(M6*0.92*0.98) -> 11.499053 | N22: =M22/M$6 -> 0.0984 | O22: =O6-(O6*0.92*0.98) -> 11.499053 | P22: =O22/O$6 -> 0.0984 | Q22: =Q6-(Q6*0.92*0.98) -> 22.260105 | R22: =Q22/Q$6 -> 0.0984 | S22: =S6-(S6*0.92*0.98) -> 22.260105 | T22: =S22/S$6 -> 0.0984 | V22: =V6-(V6*0.92*0.98) -> 2.2088883 | W22: =V22/V$6 -> 0.0984 | X22: =X6-(X6*0.92*0.98) -> 3.5502806 | Y22: =X22/X$6 -> 0.0984 | Z22: =Z6-(Z6*0.92*0.98) -> 5.7859343 | AA22: =Z22/Z$6 -> 0.0984 | AB22: =AB6-(AB6*0.92*0.98) -> 11.178269 | AC22: =AB22/AB$6 -> 0.0984 | AD22: =AD6-(AD6*0.92*0.98) -> 21.895599 | AE22: =AD22/AD$6 -> 0.0984 | AG22: =AG6-(AG6*0.92*0.98) -> 44.02821 | AH22: =AG22/AG$6 -> 0.0984 | AI22: =AI6-(AI6*0.95) -> 80 | AJ22: =AI22/AI$6 -> 0.05 | AL22: =AL6-(AL6*0.92*0.98) -> 12.6444 | AM22: =AL22/AL$6 -> 0.0984 | AN22: =AN6-(AN6*0.92*0.98) -> 23.239128 | AO22: =AN22/AN$6 -> 0.0984 | AQ22: =AQ6-(AQ6*0.92*0.98) -> 52.73748 | AR22: =AQ22/AQ$6 -> 0.0984 | AS22: =AS6-(AS6*0.95) -> 98.8895 | AT22: =AS22/AS$6 -> 0.05 | AV22: =AV6-(AV6*0.92*0.98) -> 14.229427 | AW22: =AV22/AV$6 -> 0.0984 | AX22: =AX6-(AX6*0.92*0.98) -> 27.376454 | AY22: =AX22/AX$6 -> 0.0984 | BA22: =BA6-(BA6*0.92*0.98) -> 54.260909 | BB22: =BA22/BA$6 -> 0.0984 | BC22: =BC6-(BC6*0.95) -> 107.5 | BD22: =BC22/BC$6 -> 0.05 | BG22: =BF22/BF$6 -> 0
B23: ='Pricing Trends'!R29 -> RBD PALM OLEIN (FOREIGN) | C23: ='Pricing Trends'!S29 -> 45234 | D23: ='Pricing Trends'!U29 -> 56.63575 | E23: FALSE | G23: Sales Expenses - Internal | I23: =I6*0.03 -> 1.292658 | J23: =I23/I$6 -> 0.03 | K23: =K6*0.03 -> 1.8136543 | L23: =K23/K$6 -> 0.03 | M23: =M6*0.03 -> 3.5058087 | N23: =M23/M$6 -> 0.03 | O23: =O6*0.03 -> 3.5058087 | P23: =O23/O$6 -> 0.03 | Q23: =Q6*0.03 -> 6.7866174 | R23: =Q23/Q$6 -> 0.03 | S23: =S6*0.03 -> 6.7866174 | T23: =S23/S$6 -> 0.03 | V23: =V6*0.03 -> 0.67344157 | W23: =V23/V$6 -> 0.03 | X23: =X6*0.03 -> 1.0824026 | Y23: =X23/X$6 -> 0.03 | Z23: =Z6*0.03 -> 1.7640043 | AA23: =Z23/Z$6 -> 0.03 | AB23: =AB6*0.03 -> 3.4080087 | AC23: =AB23/AB$6 -> 0.03 | AD23: =AD6*0.03 -> 6.6754875 | AE23: =AD23/AD$6 -> 0.03 | AG23: =AG6*0.03 -> 13.423235 | AH23: =AG23/AG$6 -> 0.03 | AI23: =AI6*0.03 -> 48 | AJ23: =AI23/AI$6 -> 0.03 | AL23: =AL6*0.03 -> 3.855 | AM23: =AL23/AL$6 -> 0.03 | AN23: =AN6*0.03 -> 7.0851 | AO23: =AN23/AN$6 -> 0.03 | AQ23: =AQ6*0.03 -> 16.0785 | AR23: =AQ23/AQ$6 -> 0.03 | AS23: =AS6*0.03 -> 59.3337 | AT23: =AS23/AS$6 -> 0.03 | AV23: =AV6*0.03 -> 4.33824 | AW23: =AV23/AV$6 -> 0.03 | AX23: =AX6*0.03 -> 8.34648 | AY23: =AX23/AX$6 -> 0.03 | BA23: =BA6*0.03 -> 16.54296 | BB23: =BA23/BA$6 -> 0.03 | BC23: =BC6*0.03 -> 64.5 | BD23: =BC23/BC$6 -> 0.03 | BF23: =BF6*0.03 -> 57 | BG23: =BF23/BF$6 -> 0.03
B24: ='Pricing Trends'!R30 -> 0 | C24: ='Pricing Trends'!S30 -> 0 | D24: ='Pricing Trends'!U30 -> 0 | E24: FALSE | G24: Sales Expenses - External | I24: =I6*0.02 -> 0.86177203 | J24: =I24/I$6 -> 0.02 | K24: =K6*0.02 -> 1.2091029 | L24: =K24/K$6 -> 0.02 | M24: =M6*0.02 -> 2.3372058 | N24: =M24/M$6 -> 0.02 | O24: =O6*0.02 -> 2.3372058 | P24: =O24/O$6 -> 0.02 | Q24: =Q6*0.02 -> 4.5244116 | R24: =Q24/Q$6 -> 0.02 | S24: =S6*0.02 -> 4.5244116 | T24: =S24/S$6 -> 0.02 | V24: =V6*0.02 -> 0.44896104 | W24: =V24/V$6 -> 0.02 | X24: =X6*0.02 -> 0.72160174 | Y24: =X24/X$6 -> 0.02 | Z24: =Z6*0.02 -> 1.1760029 | AA24: =Z24/Z$6 -> 0.02 | AB24: =AB6*0.02 -> 2.2720058 | AC24: =AB24/AB$6 -> 0.02 | AD24: =AD6*0.02 -> 4.450325 | AE24: =AD24/AD$6 -> 0.02 | AG24: =AG6*0.02 -> 8.9488232 | AH24: =AG24/AG$6 -> 0.02 | AI24: =AI6*0.02 -> 32 | AJ24: =AI24/AI$6 -> 0.02 | AL24: =AL6*0.02 -> 2.57 | AM24: =AL24/AL$6 -> 0.02 | AN24: =AN6*0.02 -> 4.7234 | AO24: =AN24/AN$6 -> 0.02 | AQ24: =AQ6*0.02 -> 10.719 | AR24: =AQ24/AQ$6 -> 0.02 | AS24: =AS6*0.02 -> 39.5558 | AT24: =AS24/AS$6 -> 0.02 | AV24: =AV6*0.02 -> 2.89216 | AW24: =AV24/AV$6 -> 0.02 | AX24: =AX6*0.02 -> 5.56432 | AY24: =AX24/AX$6 -> 0.02 | BA24: =BA6*0.02 -> 11.02864 | BB24: =BA24/BA$6 -> 0.02 | BC24: =BC6*0.02 -> 43 | BD24: =BC24/BC$6 -> 0.02 | BF24: =BF6*0.02 -> 38 | BG24: =BF24/BF$6 -> 0.02
B25: ='Pricing Trends'!R31 -> RBD CANOLA OIL | C25: ='Pricing Trends'!S31 -> 45269 | D25: ='Pricing Trends'!U31 -> 73.180847 | E25: FALSE | G25: Marketing Expenses - Trade Investment | I25: =I6*0.05 -> 2.1544301 | J25: =I25/I$6 -> 0.05 | K25: =K6*0.05 -> 3.0227572 | L25: =K25/K$6 -> 0.05 | M25: =M6*0.05 -> 5.8430145 | N25: =M25/M$6 -> 0.05 | O25: =O6*0.05 -> 5.8430145 | P25: =O25/O$6 -> 0.05 | Q25: =Q6*0.05 -> 11.311029 | R25: =Q25/Q$6 -> 0.05 | S25: =S6*0.05 -> 11.311029 | T25: =S25/S$6 -> 0.05 | V25: =V6*0.05 -> 1.1224026 | W25: =V25/V$6 -> 0.05 | X25: =X6*0.05 -> 1.8040043 | Y25: =X25/X$6 -> 0.05 | Z25: =Z6*0.05 -> 2.9400072 | AA25: =Z25/Z$6 -> 0.05 | AB25: =AB6*0.05 -> 5.6800145 | AC25: =AB25/AB$6 -> 0.05 | AD25: =AD6*0.05 -> 11.125813 | AE25: =AD25/AD$6 -> 0.05 | AG25: =AG6*0.05 -> 22.372058 | AH25: =AG25/AG$6 -> 0.05 | AJ25: =AI25/AI$6 -> 0 | AL25: =AL6*0.05 -> 6.425 | AM25: =AL25/AL$6 -> 0.05 | AN25: =AN6*0.05 -> 11.8085 | AO25: =AN25/AN$6 -> 0.05 | AQ25: =AQ6*0.05 -> 26.7975 | AR25: =AQ25/AQ$6 -> 0.05 | AT25: =AS25/AS$6 -> 0 | AV25: =AV6*0.05 -> 7.2304 | AW25: =AV25/AV$6 -> 0.05 | AX25: =AX6*0.05 -> 13.9108 | AY25: =AX25/AX$6 -> 0.05 | BA25: =BA6*0.05 -> 27.5716 | BB25: =BA25/BA$6 -> 0.05 | BD25: =BC25/BC$6 -> 0 | BG25: =BF25/BF$6 -> 0
B26: ='Pricing Trends'!R32 -> RBD CANOLA OIL | C26: ='Pricing Trends'!S32 -> 45118 | D26: ='Pricing Trends'!U32 -> 80.463781 | E26: FALSE | G26: Marketing Expenses - Brand Building | I26: =I6*0.05 -> 2.1544301 | J26: =I26/I$6 -> 0.05 | K26: =K6*0.05 -> 3.0227572 | L26: =K26/K$6 -> 0.05 | M26: =M6*0.05 -> 5.8430145 | N26: =M26/M$6 -> 0.05 | O26: =O6*0.05 -> 5.8430145 | P26: =O26/O$6 -> 0.05 | Q26: =Q6*0.05 -> 11.311029 | R26: =Q26/Q$6 -> 0.05 | S26: =S6*0.05 -> 11.311029 | T26: =S26/S$6 -> 0.05 | V26: =V6*0.05 -> 1.1224026 | W26: =V26/V$6 -> 0.05 | X26: =X6*0.05 -> 1.8040043 | Y26: =X26/X$6 -> 0.05 | Z26: =Z6*0.05 -> 2.9400072 | AA26: =Z26/Z$6 -> 0.05 | AB26: =AB6*0.05 -> 5.6800145 | AC26: =AB26/AB$6 -> 0.05 | AD26: =AD6*0.05 -> 11.125813 | AE26: =AD26/AD$6 -> 0.05 | AG26: =AG6*0.05 -> 22.372058 | AH26: =AG26/AG$6 -> 0.05 | AJ26: =AI26/AI$6 -> 0 | AL26: =AL6*0.05 -> 6.425 | AM26: =AL26/AL$6 -> 0.05 | AN26: =AN6*0.05 -> 11.8085 | AO26: =AN26/AN$6 -> 0.05 | AQ26: =AQ6*0.05 -> 26.7975 | AR26: =AQ26/AQ$6 -> 0.05 | AT26: =AS26/AS$6 -> 0 | AW26: =AV26/AV$6 -> #VALUE! | AX26: =AX6*0.05 -> 13.9108 | AY26: =AX26/AX$6 -> 0.05 | BA26: =BA6*0.05 -> 27.5716 | BB26: =BA26/BA$6 -> 0.05 | BD26: =BC26/BC$6 -> 0 | BG26: =BF26/BF$6 -> 0
B27: ='Pricing Trends'!R33 -> 0 | C27: ='Pricing Trends'!S33 -> 0 | D27: ='Pricing Trends'!U33 -> 0 | E27: FALSE | G27: General and Administrative Expenses | I27: =I6*0.01 -> 0.43088601 | J27: =I27/I$6 -> 0.01 | K27: =K6*0.01 -> 0.60455145 | L27: =K27/K$6 -> 0.01 | M27: =M6*0.01 -> 1.1686029 | N27: =M27/M$6 -> 0.01 | O27: =O6*0.01 -> 1.1686029 | P27: =O27/O$6 -> 0.01 | Q27: =Q6*0.01 -> 2.2622058 | R27: =Q27/Q$6 -> 0.01 | S27: =S6*0.01 -> 2.2622058 | T27: =S27/S$6 -> 0.01 | V27: =V6*0.01 -> 0.22448052 | W27: =V27/V$6 -> 0.01 | X27: =X6*0.01 -> 0.36080087 | Y27: =X27/X$6 -> 0.01 | Z27: =Z6*0.01 -> 0.58800145 | AA27: =Z27/Z$6 -> 0.01 | AB27: =AB6*0.01 -> 1.1360029 | AC27: =AB27/AB$6 -> 0.01 | AD27: =AD6*0.01 -> 2.2251625 | AE27: =AD27/AD$6 -> 0.01 | AG27: =AG6*0.01 -> 4.4744116 | AH27: =AG27/AG$6 -> 0.01 | AI27: =AI6*0.01 -> 16 | AJ27: =AI27/AI$6 -> 0.01 | AL27: =AL6*0.01 -> 1.285 | AM27: =AL27/AL$6 -> 0.01 | AN27: =AN6*0.01 -> 2.3617 | AO27: =AN27/AN$6 -> 0.01 | AQ27: =AQ6*0.01 -> 5.3595 | AR27: =AQ27/AQ$6 -> 0.01 | AS27: =AS6*0.01 -> 19.7779 | AT27: =AS27/AS$6 -> 0.01 | AV27: =AV6*0.01 -> 1.44608 | AW27: =AV27/AV$6 -> 0.01 | AX27: =AX6*0.01 -> 2.78216 | AY27: =AX27/AX$6 -> 0.01 | BA27: =BA6*0.01 -> 5.51432 | BB27: =BA27/BA$6 -> 0.01 | BC27: =BC6*0.01 -> 21.5 | BD27: =BC27/BC$6 -> 0.01 | BF27: =BF6*0.01 -> 19 | BG27: =BF27/BF$6 -> 0.01
B28: ='Pricing Trends'!R34 -> 0 | C28: ='Pricing Trends'!S34 -> 0 | D28: ='Pricing Trends'!U34 -> 0 | E28: FALSE | G28: Utilities Expenses | I28: =I6*0.01 -> 0.43088601 | J28: =I28/I$6 -> 0.01 | K28: =K6*0.01 -> 0.60455145 | L28: =K28/K$6 -> 0.01 | M28: =M6*0.01 -> 1.1686029 | N28: =M28/M$6 -> 0.01 | O28: =O6*0.01 -> 1.1686029 | P28: =O28/O$6 -> 0.01 | Q28: =Q6*0.01 -> 2.2622058 | R28: =Q28/Q$6 -> 0.01 | S28: =S6*0.01 -> 2.2622058 | T28: =S28/S$6 -> 0.01 | V28: =V6*0.01 -> 0.22448052 | W28: =V28/V$6 -> 0.01 | X28: =X6*0.01 -> 0.36080087 | Y28: =X28/X$6 -> 0.01 | Z28: =Z6*0.01 -> 0.58800145 | AA28: =Z28/Z$6 -> 0.01 | AB28: =AB6*0.01 -> 1.1360029 | AC28: =AB28/AB$6 -> 0.01 | AD28: =AD6*0.01 -> 2.2251625 | AE28: =AD28/AD$6 -> 0.01 | AG28: =AG6*0.01 -> 4.4744116 | AH28: =AG28/AG$6 -> 0.01 | AI28: =AI6*0.01 -> 16 | AJ28: =AI28/AI$6 -> 0.01 | AL28: =AL6*0.01 -> 1.285 | AM28: =AL28/AL$6 -> 0.01 | AN28: =AN6*0.01 -> 2.3617 | AO28: =AN28/AN$6 -> 0.01 | AQ28: =AQ6*0.01 -> 5.3595 | AR28: =AQ28/AQ$6 -> 0.01 | AS28: =AS6*0.01 -> 19.7779 | AT28: =AS28/AS$6 -> 0.01 | AV28: =AV6*0.01 -> 1.44608 | AW28: =AV28/AV$6 -> 0.01 | AX28: =AX6*0.01 -> 2.78216 | AY28: =AX28/AX$6 -> 0.01 | BA28: =BA6*0.01 -> 5.51432 | BB28: =BA28/BA$6 -> 0.01 | BC28: =BC6*0.01 -> 21.5 | BD28: =BC28/BC$6 -> 0.01 | BF28: =BF6*0.01 -> 19 | BG28: =BF28/BF$6 -> 0.01
B29: ='Pricing Trends'!R35 -> 0 | C29: ='Pricing Trends'!S35 -> 0 | D29: ='Pricing Trends'!U35 -> 0 | E29: FALSE | G29: Logistics Expenses - Delivery | I29: =I6*0.03 -> 1.292658 | J29: =I29/I$6 -> 0.03 | K29: =K6*0.03 -> 1.8136543 | L29: =K29/K$6 -> 0.03 | M29: =M6*0.03 -> 3.5058087 | N29: =M29/M$6 -> 0.03 | O29: =O6*0.03 -> 3.5058087 | P29: =O29/O$6 -> 0.03 | Q29: =Q6*0.03 -> 6.7866174 | R29: =Q29/Q$6 -> 0.03 | S29: =S6*0.03 -> 6.7866174 | T29: =S29/S$6 -> 0.03 | V29: =V6*0.03 -> 0.67344157 | W29: =V29/V$6 -> 0.03 | X29: =X6*0.03 -> 1.0824026 | Y29: =X29/X$6 -> 0.03 | Z29: =Z6*0.03 -> 1.7640043 | AA29: =Z29/Z$6 -> 0.03 | AB29: =AB6*0.03 -> 3.4080087 | AC29: =AB29/AB$6 -> 0.03 | AD29: =AD6*0.03 -> 6.6754875 | AE29: =AD29/AD$6 -> 0.03 | AG29: =AG6*0.03 -> 13.423235 | AH29: =AG29/AG$6 -> 0.03 | AI29: =AI6*0.03 -> 48 | AJ29: =AI29/AI$6 -> 0.03 | AL29: =AL6*0.03 -> 3.855 | AM29: =AL29/AL$6 -> 0.03 | AN29: =AN6*0.03 -> 7.0851 | AO29: =AN29/AN$6 -> 0.03 | AQ29: =AQ6*0.03 -> 16.0785 | AR29: =AQ29/AQ$6 -> 0.03 | AS29: =AS6*0.03 -> 59.3337 | AT29: =AS29/AS$6 -> 0.03 | AV29: =AV6*0.03 -> 4.33824 | AW29: =AV29/AV$6 -> 0.03 | AX29: =AX6*0.03 -> 8.34648 | AY29: =AX29/AX$6 -> 0.03 | BA29: =BA6*0.03 -> 16.54296 | BB29: =BA29/BA$6 -> 0.03 | BC29: =BC6*0.03 -> 64.5 | BD29: =BC29/BC$6 -> 0.03 | BF29: =BF6*0.03 -> 57 | BG29: =BF29/BF$6 -> 0.03
B30: ='Pricing Trends'!R36 -> 0 | C30: ='Pricing Trends'!S36 -> 0 | D30: ='Pricing Trends'!U36 -> 0 | E30: FALSE | G30: Logistics Expenses - Pick Up | H30: l | I30: =M30*0.35 -> 0 | J30: =I30/I$6 -> 0 | K30: =M30*0.5 -> 0 | L30: =K30/K$6 -> 0 | M30: =((IFERROR(VLOOKUP(I2&$G$11,Validation!$E:$F,2,FALSE),0)*'Pick Up Cost'!$C$16)+(IFERROR(VLOOKUP(I2&$G$8,Validation!$E:$F,2,FALSE),0)*'Pick Up Cost'!$C$16)) -> 0 | N30: =M30/M$6 -> 0 | O30: =((IFERROR(VLOOKUP(I2&$G$11,Validation!$E:$F,2,FALSE),0)*'Pick Up Cost'!$C$16)+(IFERROR(VLOOKUP(I2&$G$8,Validation!$E:$F,2,FALSE),0)*'Pick Up Cost'!$C$16)) -> 0 | P30: =O30/O$6 -> 0 | Q30: =M30*2 -> 0 | R30: =Q30/Q$6 -> 0 | S30: =M30*2 -> 0 | T30: =S30/S$6 -> 0 | V30: =$AB30*0.18 -> 0 | W30: =V30/V$6 -> 0 | X30: =$AB30*0.3 -> 0 | Y30: =X30/X$6 -> 0 | Z30: =$AB30*0.5 -> 0 | AA30: =Z30/Z$6 -> 0 | AB30: =((IFERROR(VLOOKUP(V2&$G$11,Validation!$E:$F,2,FALSE),0)*'Pick Up Cost'!$C$16)+(IFERROR(VLOOKUP(V2&$G$8,Validation!$E:$F,2,FALSE),0)*'Pick Up Cost'!$C$16)) -> 0 | AC30: =AB30/AB$6 -> 0 | AD30: =$AB30*2 -> 0 | AE30: =AD30/AD$6 -> 0 | AG30: =((IFERROR(VLOOKUP(AG2&$G$11,Validation!$E:$F,2,FALSE),0)*'Pick Up Cost'!$C$16)+(IFERROR(VLOOKUP(AG2&$G$8,Validation!$E:$F,2,FALSE),0)*'Pick Up Cost'!$C$16))*AH5 -> 0 | AH30: =AG30/AG$6 -> 0 | AI30: =((IFERROR(VLOOKUP(AG2&$G$11,Validation!$E:$F,2,FALSE),0)*'Pick Up Cost'!$C$16)+(IFERROR(VLOOKUP(AG2&$G$8,Validation!$E:$F,2,FALSE),0)*'Pick Up Cost'!$C$16))*15.66*1.1364 -> 0 | AJ30: =AI30/AI$6 -> 0 | AL30: =((IFERROR(VLOOKUP(AL2&$G$11,Validation!$E:$F,2,FALSE),0)*'Pick Up Cost'!$C$16)+(IFERROR(VLOOKUP(AL2&$G$8,Validation!$E:$F,2,FALSE),0)*'Pick Up Cost'!$C$16)) -> 0 | AM30: =AL30/AL$6 -> 0 | AN30: =AL30*2 -> 0 | AO30: =AN30/AN$6 -> 0 | AQ30: =((IFERROR(VLOOKUP(AQ2&$G$11,Validation!$E:$F,2,FALSE),0)*'Pick Up Cost'!$C$16)+(IFERROR(VLOOKUP(AQ2&$G$8,Validation!$E:$F,2,FALSE),0)*'Pick Up Cost'!$C$16))*AR5 -> 0 | AR30: =AQ30/AQ$6 -> 0 | AS30: =((IFERROR(VLOOKUP(AQ2&$G$11,Validation!$E:$F,2,FALSE),0)*'Pick Up Cost'!$C$16)+(IFERROR(VLOOKUP(AQ2&$G$8,Validation!$E:$F,2,FALSE),0)*'Pick Up Cost'!$C$16))*AR5*15.66*1.1364 -> 0 | AT30: =AS30/AS$6 -> 0 | AV30: =((IFERROR(VLOOKUP(AV2&$G$11,Validation!$E:$F,2,FALSE),0)*'Pick Up Cost'!$C$16)+(IFERROR(VLOOKUP(AV2&$G$8,Validation!$E:$F,2,FALSE),0)*'Pick Up Cost'!$C$16)) -> 0 | AW30: =AV30/AV$6 -> 0 | AX30: =AV30*2 -> 0 | AY30: =AX30/AX$6 -> 0 | BA30: =((IFERROR(VLOOKUP(I2&$G$11,Validation!$E:$F,2,FALSE),0)*'Pick Up Cost'!$C$16)+(IFERROR(VLOOKUP(I2&$G$8,Validation!$E:$F,2,FALSE),0)*'Pick Up Cost'!$C$16))*BB5 -> 0 | BB30: =BA30/BA$6 -> 0 | BC30: =((IFERROR(VLOOKUP(I2&$G$11,Validation!$E:$F,2,FALSE),0)*'Pick Up Cost'!$C$16)+(IFERROR(VLOOKUP(I2&$G$8,Validation!$E:$F,2,FALSE),0)*'Pick Up Cost'!$C$16))*15.66*1.1364 -> 0 | BD30: =BC30/BC$6 -> 0 | BF30: =((IFERROR(VLOOKUP(BF2&$G$11,Validation!$E:$F,2,FALSE),0)*'Pick Up Cost'!$C$16)+(IFERROR(VLOOKUP(BF2&$G$8,Validation!$E:$F,2,FALSE),0)*'Pick Up Cost'!$C$16))*15.66*1.1364 -> 31.143042 | BG30: =BF30/BF$6 -> 0.016391075
